Workbook
Name switch: #REF!
Name switch: #REF!
Name switch: #REF!
Name achieve: #REF!
Name switch: #REF!
Name switch: #REF!
Name achieve: #REF!
Name switch: #REF!
Name form_income: #REF!
Name achieve: #REF!
Name form_invest: #REF!
Name form_enemy: #REF!
Name achieve: '年間推移シート'!$C$13:$Q$63
Name switch: #REF!
Name switch: #REF!
Name achieve: #REF!
Name achieve: #REF!
Name achieve: #REF!
Name achieve: #REF!
Name switch: #REF!
Name switch: #REF!
Name switch: #REF!
Name achieve: #REF!
Name achieve: #REF!
Name achieve: #REF!
Name switch: #REF!
Name achieve: #REF!
Name achieve: #REF!
Name achieve: #REF!
Name switch: #REF!
Name switch: #REF!

Sheet 説明
F5: 必ずコピーしてお使いください
F7: ①「ファイル」を押す→②「コピーを作成」を押す→③好きな名前に変更して保存
F8: 👈イメージ図はコチラ
F12: 記入例はコチラ
F13: https://docs.google.com/spreadsheets/d/17IY06cKMxbN9RkT_RKE8P9Hi3TCbj9vyqdSf7Ji-IQU/edit?usp=sharing
F16: 使い方ガイドはコチラ | I16: ※1つあたり5分以内の短い動画です（音声を速めて聞くのをオススメします）
F17: ① 家計簿フォーマットの使い方 | H17: https://www.loom.com/share/37b2dd6e3192492cad6bd00e9eec2e59?sid=942f5ea2-309b-4961-a169-0edd331df914
F18: ② 週予算管理の使い方 | H18: https://www.loom.com/share/22315fc3571547b08d7fb8604cdd833b
F19: ③ 年間推移シートの使い方 | H19: https://www.loom.com/share/89c1cf4ee43145dca461fe9334c9dd6f?sid=2a5acbce-cc47-4e1f-b258-f597eeb6d21c
F20: ④ 収支可視化シートの使い方 | H20: https://www.loom.com/share/a11131eea75e4983a4cd70746b292bea?sid=d7ec20dd-8da5-48c0-a97f-9e07cfbbc26d
F21: ⑤ 特別費管理シート＆積立管理シートの使い方 | H21: https://www.loom.com/share/ec77e9ddfe4f4ecdb27c69937ac317c6?sid=0b5f8703-987c-4617-82b4-51dfa63dd329
F22: ⑥ 家計簿フォーマットの印刷方法 | H22: https://www.loom.com/share/468b7c509ef041ecbabe6457f7a6cb27
F23: ⑦ 注意点 | H23: https://www.loom.com/share/fc6dcc39dfc84e028cd50287b05d48bd
F24: ⑧ 支払管理シートの使い方 | H24: https://www.loom.com/share/78292bbc3862419c99e4e5c73a5361a7
F25: ⑨ 変動費明細の追加方法 | H25: https://www.loom.com/share/c84a9fac4d4c455990c32c65b0127334
F26: ⑩ 変動費明細を日付順で並び替える方法 | H26: https://www.loom.com/share/7df2fd3f96d8450eaead1efa6d80f9ae
F27: ⑪ 収入・固定費・変動費・週予算管理の行の追加方法 | H27: https://www.loom.com/share/c5822df7b4aa432da211e2d1040d1c62

Sheet 1月
B1: 1 | D1: ← 年・月を変更するとカレンダーが自動更新されます | J1: ※グレーのセルは自動反映します（入力不要）
B2: 2025 | J2: =DATE(B2,B1,1) -> 45658 | R2: 変動費 明細
B4: 収入 | F4: 先取り貯金・投資 | J4: 月 | K4: 火 | L4: 水 | M4: 木 | N4: 金 | O4: 土 | P4: 日 | R4: 日付 | S4: 週 | T4: 支払方法 | U4: 費目 | V4: 詳細 | X4: 金額 | Y4: 満足度
B5: 費目 | C5: 入金口座 | D5: 金額 | F5: 費目 | G5: 支払方法 | H5: 金額 | J5: =$J$2-weekday($J$2)+2 -> 45656 | K5: =J5+1 -> 45657 | L5: =K5+1 -> 45658 | M5: =L5+1 -> 45659 | N5: =M5+1 -> 45660 | O5: =N5+1 -> 45661 | P5: =O5+1 -> 45662 | R5: 45658 | S5: 1week | T5: 現金 | U5: 🍙 食費 | X5: 1000
B6: 💰 パパ給与 | C6: Ｃ銀行 | D6: 250000 | F6: 💴 貯金 | H6: 20000 | J6: =sumifs($X:$X,$R:$R,J5) -> 0 | K6: =sumifs($X:$X,$R:$R,K5) -> 0 | L6: =sumifs($X:$X,$R:$R,L5) -> 1000 | M6: =sumifs($X:$X,$R:$R,M5) -> 0 | N6: =sumifs($X:$X,$R:$R,N5) -> 0 | O6: =sumifs($X:$X,$R:$R,O5) -> 0 | P6: =sumifs($X:$X,$R:$R,P5) -> 0
B7: 💰 ママ給与 | C7: Ｄ銀行 | D7: 150000 | F7: 💴 NISA | G7: クレカＡ | H7: 30000 | J7: =J5+7 -> 45663 | K7: =K5+7 -> 45664 | L7: =L5+7 -> 45665 | M7: =M5+7 -> 45666 | N7: =N5+7 -> 45667 | O7: =O5+7 -> 45668 | P7: =P5+7 -> 45669
F8: 💴 特別費積み立て | H8: 30000 | J8: =sumifs($X:$X,$R:$R,J7) -> 0 | K8: =sumifs($X:$X,$R:$R,K7) -> 0 | L8: =sumifs($X:$X,$R:$R,L7) -> 0 | M8: =sumifs($X:$X,$R:$R,M7) -> 0 | N8: =sumifs($X:$X,$R:$R,N7) -> 0 | O8: =sumifs($X:$X,$R:$R,O7) -> 0 | P8: =sumifs($X:$X,$R:$R,P7) -> 0
J9: =J7+7 -> 45670 | K9: =K7+7 -> 45671 | L9: =L7+7 -> 45672 | M9: =M7+7 -> 45673 | N9: =N7+7 -> 45674 | O9: =O7+7 -> 45675 | P9: =P7+7 -> 45676
J10: =sumifs($X:$X,$R:$R,J9) -> 0 | K10: =sumifs($X:$X,$R:$R,K9) -> 0 | L10: =sumifs($X:$X,$R:$R,L9) -> 0 | M10: =sumifs($X:$X,$R:$R,M9) -> 0 | N10: =sumifs($X:$X,$R:$R,N9) -> 0 | O10: =sumifs($X:$X,$R:$R,O9) -> 0 | P10: =sumifs($X:$X,$R:$R,P9) -> 0
J11: =J9+7 -> 45677 | K11: =K9+7 -> 45678 | L11: =L9+7 -> 45679 | M11: =M9+7 -> 45680 | N11: =N9+7 -> 45681 | O11: =O9+7 -> 45682 | P11: =P9+7 -> 45683
J12: =sumifs($X:$X,$R:$R,J11) -> 0 | K12: =sumifs($X:$X,$R:$R,K11) -> 0 | L12: =sumifs($X:$X,$R:$R,L11) -> 0 | M12: =sumifs($X:$X,$R:$R,M11) -> 0 | N12: =sumifs($X:$X,$R:$R,N11) -> 0 | O12: =sumifs($X:$X,$R:$R,O11) -> 0 | P12: =sumifs($X:$X,$R:$R,P11) -> 0
J13: =J11+7 -> 45684 | K13: =K11+7 -> 45685 | L13: =L11+7 -> 45686 | M13: =M11+7 -> 45687 | N13: =N11+7 -> 45688 | O13: =O11+7 -> 45689 | P13: =P11+7 -> 45690
B14: 合計 | D14: =SUM(D6:D13) -> 400000 | F14: 合計 | H14: =SUM(H6:H13) -> 80000 | J14: =sumifs($X:$X,$R:$R,J13) -> 0 | K14: =sumifs($X:$X,$R:$R,K13) -> 0 | L14: =sumifs($X:$X,$R:$R,L13) -> 0 | M14: =sumifs($X:$X,$R:$R,M13) -> 0 | N14: =sumifs($X:$X,$R:$R,N13) -> 0 | O14: =sumifs($X:$X,$R:$R,O13) -> 0 | P14: =sumifs($X:$X,$R:$R,P13) -> 0
B16: 支出 | F16: 支出 | J16: 週予算 管理
B17: 固定費 | F17: 変動費
B18: 費目 | C18: 支払方法 | D18: 金額 | F18: 費目 | G18: 予算 | H18: 金額 | J18: 項目 | L18: 1week | O18: 2week
B19: 🏠 住宅 | C19: クレカＡ | D19: 100000 | F19: 🍙 食費 | H19: =sumifs($X:$X,$U:$U,F19) -> 1000 | K19: 予算 | L19: 金額 | M19: 差分 | N19: 予算 | O19: 金額 | P19: 差分
B20: 💡 電気 | C20: クレカＢ | D20: 8000 | F20: 🧴 日用品 | H20: =sumifs($X:$X,$U:$U,F20) -> 0 | J20: 🍙 食費 | K20: 10000 | L20: =sumifs($X:$X,$S:$S,$L$18,$U:$U,J20) -> 1000 | M20: =K20-L20 -> 9000 | O20: =sumifs($X:$X,$S:$S,$O$18,$U:$U,J20) -> 0 | P20: =N20-O20 -> 0
B21: 🔥 ガス | C21: クレカＢ | D21: 5000 | F21: ⛺️ 趣味・娯楽 | H21: =sumifs($X:$X,$U:$U,F21) -> 0 | L21: =sumifs($X:$X,$S:$S,$L$18,$U:$U,J21) -> 0 | M21: =K21-L21 -> 0 | O21: =sumifs($X:$X,$S:$S,$O$18,$U:$U,J21) -> 0 | P21: =N21-O21 -> 0
B22: 🚰 水道 | C22: Ｃ銀行 | D22: 2000 | F22: 🍼 子ども | H22: =sumifs($X:$X,$U:$U,F22) -> 0 | L22: =sumifs($X:$X,$S:$S,$L$18,$U:$U,J22) -> 0 | M22: =K22-L22 -> 0 | O22: =sumifs($X:$X,$S:$S,$O$18,$U:$U,J22) -> 0 | P22: =N22-O22 -> 0
B23: 📱 通信費 | C23: クレカＢ | D23: 5000 | F23: 🏥 健康・医療 | H23: =sumifs($X:$X,$U:$U,F23) -> 0 | L23: =sumifs($X:$X,$S:$S,$L$18,$U:$U,J23) -> 0 | M23: =K23-L23 -> 0 | O23: =sumifs($X:$X,$S:$S,$O$18,$U:$U,J23) -> 0 | P23: =N23-O23 -> 0
B24: 📽️ サブスク | C24: クレカＢ | D24: 2000 | F24: ❓ その他 | H24: =sumifs($X:$X,$U:$U,F24) -> 0 | L24: =sumifs($X:$X,$S:$S,$L$18,$U:$U,J24) -> 0 | M24: =K24-L24 -> 0 | O24: =sumifs($X:$X,$S:$S,$O$18,$U:$U,J24) -> 0 | P24: =N24-O24 -> 0
B25: 📃 保険 | C25: Ｃ銀行 | D25: 5000 | H25: =sumifs($X:$X,$U:$U,F25) -> 0 | L25: =sumifs($X:$X,$S:$S,$L$18,$U:$U,J25) -> 0 | M25: =K25-L25 -> 0 | O25: =sumifs($X:$X,$S:$S,$O$18,$U:$U,J25) -> 0 | P25: =N25-O25 -> 0
B26: 🎓 教養・教育 | C26: Ｄ銀行 | D26: 30000 | H26: =sumifs($X:$X,$U:$U,F26) -> 0 | L26: =sumifs($X:$X,$S:$S,$L$18,$U:$U,J26) -> 0 | M26: =K26-L26 -> 0 | O26: =sumifs($X:$X,$S:$S,$O$18,$U:$U,J26) -> 0 | P26: =N26-O26 -> 0
H27: =sumifs($X:$X,$U:$U,F27) -> 0 | J27: ALL | K27: =SUM(K20:K26) -> 10000 | L27: =SUM(L20:L26) -> 1000 | M27: =K27-L27 -> 9000 | N27: =SUM(N20:N26) -> 0 | O27: =SUM(O20:O26) -> 0 | P27: =N27-O27 -> 0
H28: =sumifs($X:$X,$U:$U,F28) -> 0
H29: =sumifs($X:$X,$U:$U,F29) -> 0 | J29: 項目 | L29: 3week | O29: 4week
H30: =sumifs($X:$X,$U:$U,F30) -> 0 | K30: 予算 | L30: 金額 | M30: 差分 | N30: 予算 | O30: 金額 | P30: 差分
B31: 合計 | D31: =SUM(D19:D30) -> 157000 | F31: 合計 | G31: =SUM(G19:G30) -> 0 | H31: =SUM(H19:H30) -> 1000 | L31: =sumifs($X:$X,$S:$S,$L$29,$U:$U,J31) -> 0 | M31: =K31-L31 -> 0 | O31: =sumifs($X:$X,$S:$S,$O$29,$U:$U,J31) -> 0 | P31: =N31-O31 -> 0
L32: =sumifs($X:$X,$S:$S,$L$29,$U:$U,J32) -> 0 | M32: =K32-L32 -> 0 | O32: =sumifs($X:$X,$S:$S,$O$29,$U:$U,J32) -> 0 | P32: =N32-O32 -> 0
B33: 特別費 | F33: 今月の収支 | H33: 金額 | L33: =sumifs($X:$X,$S:$S,$L$29,$U:$U,J33) -> 0 | M33: =K33-L33 -> 0 | O33: =sumifs($X:$X,$S:$S,$O$29,$U:$U,J33) -> 0 | P33: =N33-O33 -> 0
B34: 費目 | C34: 支払方法 | D34: 金額 | F34: 収入（a） | H34: =D14 -> 400000 | L34: =sumifs($X:$X,$S:$S,$L$29,$U:$U,J34) -> 0 | M34: =K34-L34 -> 0 | O34: =sumifs($X:$X,$S:$S,$O$29,$U:$U,J34) -> 0 | P34: =N34-O34 -> 0
B35: 🍴 食事 | C35: クレカＢ | D35: 12000 | F35: 先取り貯金・投資（b） | H35: =H14 -> 80000 | L35: =sumifs($X:$X,$S:$S,$L$29,$U:$U,J35) -> 0 | M35: =K35-L35 -> 0 | O35: =sumifs($X:$X,$S:$S,$O$29,$U:$U,J35) -> 0 | P35: =N35-O35 -> 0
F36: 支出（c） | H36: =D31+H31 -> 158000 | L36: =sumifs($X:$X,$S:$S,$L$29,$U:$U,J36) -> 0 | M36: =K36-L36 -> 0 | O36: =sumifs($X:$X,$S:$S,$O$29,$U:$U,J36) -> 0 | P36: =N36-O36 -> 0
F37: 余り貯金（d）※a-b-c | H37: =H34-H35-H36 -> 162000 | L37: =sumifs($X:$X,$S:$S,$L$29,$U:$U,J37) -> 0 | M37: =K37-L37 -> 0 | O37: =sumifs($X:$X,$S:$S,$O$29,$U:$U,J37) -> 0 | P37: =N37-O37 -> 0
F38: 貯蓄合計（e）※b+d | H38: =H35+H37 -> 242000 | J38: ALL | K38: =SUM(K31:K37) -> 0 | L38: =SUM(L31:L37) -> 0 | M38: =K38-L38 -> 0 | N38: =SUM(N31:N37) -> 0 | O38: =SUM(O31:O37) -> 0 | P38: =N38-O38 -> 0
F40: 支出率（c/a)×100 | G40: 貯蓄率 （e/a)×100 | J40: 項目 | L40: 5week | O40: ALL
F41: =H36/H34 -> 0.395 | G41: =H38/H34 -> 0.605 | K41: 予算 | L41: 金額 | M41: 差分 | N41: 予算 | O41: 金額 | P41: 差分
B42: 合計 | D42: =SUM(D35:D41) -> 12000 | L42: =sumifs($X:$X,$S:$S,$L$40,$U:$U,J42) -> 0 | M42: =K42-L42 -> 0 | N42: =K20+N20+K31+N31+K42 -> 10000 | O42: =L20+O20+L31+O31+L42 -> 1000 | P42: =N42-O42 -> 9000
D43: ※収支の計算外 | F43: ※目標：80%以下 | H43: ※目標：20%以上 | L43: =sumifs($X:$X,$S:$S,$L$40,$U:$U,J43) -> 0 | M43: =K43-L43 -> 0 | N43: =K21+N21+K32+N32+K43 -> 0 | O43: =L21+O21+L32+O32+L43 -> 0 | P43: =N43-O43 -> 0
B44: 振り返り | L44: =sumifs($X:$X,$S:$S,$L$40,$U:$U,J44) -> 0 | M44: =K44-L44 -> 0 | N44: =K22+N22+K33+N33+K44 -> 0 | O44: =L22+O22+L33+O33+L44 -> 0 | P44: =N44-O44 -> 0
L45: =sumifs($X:$X,$S:$S,$L$40,$U:$U,J45) -> 0 | M45: =K45-L45 -> 0 | N45: =K23+N23+K34+N34+K45 -> 0 | O45: =L23+O23+L34+O34+L45 -> 0 | P45: =N45-O45 -> 0
L46: =sumifs($X:$X,$S:$S,$L$40,$U:$U,J46) -> 0 | M46: =K46-L46 -> 0 | N46: =K24+N24+K35+N35+K46 -> 0 | O46: =L24+O24+L35+O35+L46 -> 0 | P46: =N46-O46 -> 0
L47: =sumifs($X:$X,$S:$S,$L$40,$U:$U,J47) -> 0 | M47: =K47-L47 -> 0 | N47: =K25+N25+K36+N36+K47 -> 0 | O47: =L25+O25+L36+O36+L47 -> 0 | P47: =N47-O47 -> 0
L48: =sumifs($X:$X,$S:$S,$L$40,$U:$U,J48) -> 0 | M48: =K48-L48 -> 0 | N48: =K26+N26+K37+N37+K48 -> 0 | O48: =L26+O26+L37+O37+L48 -> 0 | P48: =N48-O48 -> 0
J49: ALL | K49: =SUM(K42:K48) -> 0 | L49: =SUM(L42:L48) -> 0 | M49: =K49-L49 -> 0 | N49: =SUM(N42:N48) -> 10000 | O49: =SUM(O42:O48) -> 1000 | P49: =N49-O49 -> 9000

Sheet 2月
B1: 2 | D1: ← 年・月を変更するとカレンダーが自動更新されます | J1: ※グレーのセルは自動反映します（入力不要）
B2: 2025 | J2: =DATE(B2,B1,1) -> 45689 | R2: 変動費 明細
B4: 収入 | F4: 先取り貯金・投資 | J4: 月 | K4: 火 | L4: 水 | M4: 木 | N4: 金 | O4: 土 | P4: 日 | R4: 日付 | S4: 週 | T4: 支払方法 | U4: 費目 | V4: 詳細 | X4: 金額 | Y4: 満足度
B5: 費目 | C5: 入金口座 | D5: 金額 | F5: 費目 | G5: 支払方法 | H5: 金額 | J5: =$J$2-weekday($J$2)+2 -> 45684 | K5: =J5+1 -> 45685 | L5: =K5+1 -> 45686 | M5: =L5+1 -> 45687 | N5: =M5+1 -> 45688 | O5: =N5+1 -> 45689 | P5: =O5+1 -> 45690 | R5: 45689
J6: =sumifs($X:$X,$R:$R,J5) -> 0 | K6: =sumifs($X:$X,$R:$R,K5) -> 0 | L6: =sumifs($X:$X,$R:$R,L5) -> 0 | M6: =sumifs($X:$X,$R:$R,M5) -> 0 | N6: =sumifs($X:$X,$R:$R,N5) -> 0 | O6: =sumifs($X:$X,$R:$R,O5) -> 0 | P6: =sumifs($X:$X,$R:$R,P5) -> 0
J7: =J5+7 -> 45691 | K7: =K5+7 -> 45692 | L7: =L5+7 -> 45693 | M7: =M5+7 -> 45694 | N7: =N5+7 -> 45695 | O7: =O5+7 -> 45696 | P7: =P5+7 -> 45697
J8: =sumifs($X:$X,$R:$R,J7) -> 0 | K8: =sumifs($X:$X,$R:$R,K7) -> 0 | L8: =sumifs($X:$X,$R:$R,L7) -> 0 | M8: =sumifs($X:$X,$R:$R,M7) -> 0 | N8: =sumifs($X:$X,$R:$R,N7) -> 0 | O8: =sumifs($X:$X,$R:$R,O7) -> 0 | P8: =sumifs($X:$X,$R:$R,P7) -> 0
J9: =J7+7 -> 45698 | K9: =K7+7 -> 45699 | L9: =L7+7 -> 45700 | M9: =M7+7 -> 45701 | N9: =N7+7 -> 45702 | O9: =O7+7 -> 45703 | P9: =P7+7 -> 45704
J10: =sumifs($X:$X,$R:$R,J9) -> 0 | K10: =sumifs($X:$X,$R:$R,K9) -> 0 | L10: =sumifs($X:$X,$R:$R,L9) -> 0 | M10: =sumifs($X:$X,$R:$R,M9) -> 0 | N10: =sumifs($X:$X,$R:$R,N9) -> 0 | O10: =sumifs($X:$X,$R:$R,O9) -> 0 | P10: =sumifs($X:$X,$R:$R,P9) -> 0
J11: =J9+7 -> 45705 | K11: =K9+7 -> 45706 | L11: =L9+7 -> 45707 | M11: =M9+7 -> 45708 | N11: =N9+7 -> 45709 | O11: =O9+7 -> 45710 | P11: =P9+7 -> 45711
J12: =sumifs($X:$X,$R:$R,J11) -> 0 | K12: =sumifs($X:$X,$R:$R,K11) -> 0 | L12: =sumifs($X:$X,$R:$R,L11) -> 0 | M12: =sumifs($X:$X,$R:$R,M11) -> 0 | N12: =sumifs($X:$X,$R:$R,N11) -> 0 | O12: =sumifs($X:$X,$R:$R,O11) -> 0 | P12: =sumifs($X:$X,$R:$R,P11) -> 0
J13: =J11+7 -> 45712 | K13: =K11+7 -> 45713 | L13: =L11+7 -> 45714 | M13: =M11+7 -> 45715 | N13: =N11+7 -> 45716 | O13: =O11+7 -> 45717 | P13: =P11+7 -> 45718
B14: 合計 | D14: =SUM(D6:D13) -> 0 | F14: 合計 | H14: =SUM(H6:H13) -> 0 | J14: =sumifs($X:$X,$R:$R,J13) -> 0 | K14: =sumifs($X:$X,$R:$R,K13) -> 0 | L14: =sumifs($X:$X,$R:$R,L13) -> 0 | M14: =sumifs($X:$X,$R:$R,M13) -> 0 | N14: =sumifs($X:$X,$R:$R,N13) -> 0 | O14: =sumifs($X:$X,$R:$R,O13) -> 0 | P14: =sumifs($X:$X,$R:$R,P13) -> 0
B16: 支出 | F16: 支出 | J16: 週予算 管理
B17: 固定費 | F17: 変動費
B18: 費目 | C18: 支払方法 | D18: 金額 | F18: 費目 | G18: 予算 | H18: 金額 | J18: 項目 | L18: 1week | O18: 2week
H19: =sumifs($X:$X,$U:$U,F19) -> 0 | K19: 予算 | L19: 金額 | M19: 差分 | N19: 予算 | O19: 金額 | P19: 差分
H20: =sumifs($X:$X,$U:$U,F20) -> 0 | L20: =sumifs($X:$X,$S:$S,$L$18,$U:$U,J20) -> 0 | M20: =K20-L20 -> 0 | O20: =sumifs($X:$X,$S:$S,$O$18,$U:$U,J20) -> 0 | P20: =N20-O20 -> 0
H21: =sumifs($X:$X,$U:$U,F21) -> 0 | L21: =sumifs($X:$X,$S:$S,$L$18,$U:$U,J21) -> 0 | M21: =K21-L21 -> 0 | O21: =sumifs($X:$X,$S:$S,$O$18,$U:$U,J21) -> 0 | P21: =N21-O21 -> 0
H22: =sumifs($X:$X,$U:$U,F22) -> 0 | L22: =sumifs($X:$X,$S:$S,$L$18,$U:$U,J22) -> 0 | M22: =K22-L22 -> 0 | O22: =sumifs($X:$X,$S:$S,$O$18,$U:$U,J22) -> 0 | P22: =N22-O22 -> 0
H23: =sumifs($X:$X,$U:$U,F23) -> 0 | L23: =sumifs($X:$X,$S:$S,$L$18,$U:$U,J23) -> 0 | M23: =K23-L23 -> 0 | O23: =sumifs($X:$X,$S:$S,$O$18,$U:$U,J23) -> 0 | P23: =N23-O23 -> 0
H24: =sumifs($X:$X,$U:$U,F24) -> 0 | L24: =sumifs($X:$X,$S:$S,$L$18,$U:$U,J24) -> 0 | M24: =K24-L24 -> 0 | O24: =sumifs($X:$X,$S:$S,$O$18,$U:$U,J24) -> 0 | P24: =N24-O24 -> 0
H25: =sumifs($X:$X,$U:$U,F25) -> 0 | L25: =sumifs($X:$X,$S:$S,$L$18,$U:$U,J25) -> 0 | M25: =K25-L25 -> 0 | O25: =sumifs($X:$X,$S:$S,$O$18,$U:$U,J25) -> 0 | P25: =N25-O25 -> 0
H26: =sumifs($X:$X,$U:$U,F26) -> 0 | L26: =sumifs($X:$X,$S:$S,$L$18,$U:$U,J26) -> 0 | M26: =K26-L26 -> 0 | O26: =sumifs($X:$X,$S:$S,$O$18,$U:$U,J26) -> 0 | P26: =N26-O26 -> 0
H27: =sumifs($X:$X,$U:$U,F27) -> 0 | J27: ALL | K27: =SUM(K20:K26) -> 0 | L27: =SUM(L20:L26) -> 0 | M27: =K27-L27 -> 0 | N27: =SUM(N20:N26) -> 0 | O27: =SUM(O20:O26) -> 0 | P27: =N27-O27 -> 0
H28: =sumifs($X:$X,$U:$U,F28) -> 0
H29: =sumifs($X:$X,$U:$U,F29) -> 0 | J29: 項目 | L29: 3week | O29: 4week
H30: =sumifs($X:$X,$U:$U,F30) -> 0 | K30: 予算 | L30: 金額 | M30: 差分 | N30: 予算 | O30: 金額 | P30: 差分
B31: 合計 | D31: =SUM(D19:D30) -> 0 | F31: 合計 | G31: =SUM(G19:G30) -> 0 | H31: =SUM(H19:H30) -> 0 | L31: =sumifs($X:$X,$S:$S,$L$29,$U:$U,J31) -> 0 | M31: =K31-L31 -> 0 | O31: =sumifs($X:$X,$S:$S,$O$29,$U:$U,J31) -> 0 | P31: =N31-O31 -> 0
L32: =sumifs($X:$X,$S:$S,$L$29,$U:$U,J32) -> 0 | M32: =K32-L32 -> 0 | O32: =sumifs($X:$X,$S:$S,$O$29,$U:$U,J32) -> 0 | P32: =N32-O32 -> 0
B33: 特別費 | F33: 今月の収支 | H33: 金額 | L33: =sumifs($X:$X,$S:$S,$L$29,$U:$U,J33) -> 0 | M33: =K33-L33 -> 0 | O33: =sumifs($X:$X,$S:$S,$O$29,$U:$U,J33) -> 0 | P33: =N33-O33 -> 0
B34: 費目 | C34: 支払方法 | D34: 金額 | F34: 収入（a） | H34: =D14 -> 0 | L34: =sumifs($X:$X,$S:$S,$L$29,$U:$U,J34) -> 0 | M34: =K34-L34 -> 0 | O34: =sumifs($X:$X,$S:$S,$O$29,$U:$U,J34) -> 0 | P34: =N34-O34 -> 0
F35: 先取り貯金・投資（b） | H35: =H14 -> 0 | L35: =sumifs($X:$X,$S:$S,$L$29,$U:$U,J35) -> 0 | M35: =K35-L35 -> 0 | O35: =sumifs($X:$X,$S:$S,$O$29,$U:$U,J35) -> 0 | P35: =N35-O35 -> 0
F36: 支出（c） | H36: =D31+H31 -> 0 | L36: =sumifs($X:$X,$S:$S,$L$29,$U:$U,J36) -> 0 | M36: =K36-L36 -> 0 | O36: =sumifs($X:$X,$S:$S,$O$29,$U:$U,J36) -> 0 | P36: =N36-O36 -> 0
F37: 余り貯金（d）※a-b-c | H37: =H34-H35-H36 -> 0 | L37: =sumifs($X:$X,$S:$S,$L$29,$U:$U,J37) -> 0 | M37: =K37-L37 -> 0 | O37: =sumifs($X:$X,$S:$S,$O$29,$U:$U,J37) -> 0 | P37: =N37-O37 -> 0
F38: 貯蓄合計（e）※b+d | H38: =H35+H37 -> 0 | J38: ALL | K38: =SUM(K31:K37) -> 0 | L38: =SUM(L31:L37) -> 0 | M38: =K38-L38 -> 0 | N38: =SUM(N31:N37) -> 0 | O38: =SUM(O31:O37) -> 0 | P38: =N38-O38 -> 0
F40: 支出率（c/a)×100 | G40: 貯蓄率 （e/a)×100 | J40: 項目 | L40: 5week | O40: ALL
F41: =H36/H34 -> #DIV/0! | G41: =H38/H34 -> #DIV/0! | K41: 予算 | L41: 金額 | M41: 差分 | N41: 予算 | O41: 金額 | P41: 差分
B42: 合計 | D42: =SUM(D35:D41) -> 0 | L42: =sumifs($X:$X,$S:$S,$L$40,$U:$U,J42) -> 0 | M42: =K42-L42 -> 0 | N42: =K20+N20+K31+N31+K42 -> 0 | O42: =L20+O20+L31+O31+L42 -> 0 | P42: =N42-O42 -> 0
D43: ※収支の計算外 | F43: ※目標：80%以下 | H43: ※目標：20%以上 | L43: =sumifs($X:$X,$S:$S,$L$40,$U:$U,J43) -> 0 | M43: =K43-L43 -> 0 | N43: =K21+N21+K32+N32+K43 -> 0 | O43: =L21+O21+L32+O32+L43 -> 0 | P43: =N43-O43 -> 0
B44: 振り返り | L44: =sumifs($X:$X,$S:$S,$L$40,$U:$U,J44) -> 0 | M44: =K44-L44 -> 0 | N44: =K22+N22+K33+N33+K44 -> 0 | O44: =L22+O22+L33+O33+L44 -> 0 | P44: =N44-O44 -> 0
L45: =sumifs($X:$X,$S:$S,$L$40,$U:$U,J45) -> 0 | M45: =K45-L45 -> 0 | N45: =K23+N23+K34+N34+K45 -> 0 | O45: =L23+O23+L34+O34+L45 -> 0 | P45: =N45-O45 -> 0
L46: =sumifs($X:$X,$S:$S,$L$40,$U:$U,J46) -> 0 | M46: =K46-L46 -> 0 | N46: =K24+N24+K35+N35+K46 -> 0 | O46: =L24+O24+L35+O35+L46 -> 0 | P46: =N46-O46 -> 0
L47: =sumifs($X:$X,$S:$S,$L$40,$U:$U,J47) -> 0 | M47: =K47-L47 -> 0 | N47: =K25+N25+K36+N36+K47 -> 0 | O47: =L25+O25+L36+O36+L47 -> 0 | P47: =N47-O47 -> 0
L48: =sumifs($X:$X,$S:$S,$L$40,$U:$U,J48) -> 0 | M48: =K48-L48 -> 0 | N48: =K26+N26+K37+N37+K48 -> 0 | O48: =L26+O26+L37+O37+L48 -> 0 | P48: =N48-O48 -> 0
J49: ALL | K49: =SUM(K42:K48) -> 0 | L49: =SUM(L42:L48) -> 0 | M49: =K49-L49 -> 0 | N49: =SUM(N42:N48) -> 0 | O49: =SUM(O42:O48) -> 0 | P49: =N49-O49 -> 0

Sheet 3月
B1: 3 | D1: ← 年・月を変更するとカレンダーが自動更新されます | J1: ※グレーのセルは自動反映します（入力不要）
B2: 2025 | J2: =DATE(B2,B1,1) -> 45717 | R2: 変動費 明細
B4: 収入 | F4: 先取り貯金・投資 | J4: 月 | K4: 火 | L4: 水 | M4: 木 | N4: 金 | O4: 土 | P4: 日 | R4: 日付 | S4: 週 | T4: 支払方法 | U4: 費目 | V4: 詳細 | X4: 金額 | Y4: 満足度
B5: 費目 | C5: 入金口座 | D5: 金額 | F5: 費目 | G5: 支払方法 | H5: 金額 | J5: =$J$2-weekday($J$2)+2 -> 45712 | K5: =J5+1 -> 45713 | L5: =K5+1 -> 45714 | M5: =L5+1 -> 45715 | N5: =M5+1 -> 45716 | O5: =N5+1 -> 45717 | P5: =O5+1 -> 45718 | R5: 45717
J6: =sumifs($X:$X,$R:$R,J5) -> 0 | K6: =sumifs($X:$X,$R:$R,K5) -> 0 | L6: =sumifs($X:$X,$R:$R,L5) -> 0 | M6: =sumifs($X:$X,$R:$R,M5) -> 0 | N6: =sumifs($X:$X,$R:$R,N5) -> 0 | O6: =sumifs($X:$X,$R:$R,O5) -> 0 | P6: =sumifs($X:$X,$R:$R,P5) -> 0
J7: =J5+7 -> 45719 | K7: =K5+7 -> 45720 | L7: =L5+7 -> 45721 | M7: =M5+7 -> 45722 | N7: =N5+7 -> 45723 | O7: =O5+7 -> 45724 | P7: =P5+7 -> 45725
J8: =sumifs($X:$X,$R:$R,J7) -> 0 | K8: =sumifs($X:$X,$R:$R,K7) -> 0 | L8: =sumifs($X:$X,$R:$R,L7) -> 0 | M8: =sumifs($X:$X,$R:$R,M7) -> 0 | N8: =sumifs($X:$X,$R:$R,N7) -> 0 | O8: =sumifs($X:$X,$R:$R,O7) -> 0 | P8: =sumifs($X:$X,$R:$R,P7) -> 0
J9: =J7+7 -> 45726 | K9: =K7+7 -> 45727 | L9: =L7+7 -> 45728 | M9: =M7+7 -> 45729 | N9: =N7+7 -> 45730 | O9: =O7+7 -> 45731 | P9: =P7+7 -> 45732
J10: =sumifs($X:$X,$R:$R,J9) -> 0 | K10: =sumifs($X:$X,$R:$R,K9) -> 0 | L10: =sumifs($X:$X,$R:$R,L9) -> 0 | M10: =sumifs($X:$X,$R:$R,M9) -> 0 | N10: =sumifs($X:$X,$R:$R,N9) -> 0 | O10: =sumifs($X:$X,$R:$R,O9) -> 0 | P10: =sumifs($X:$X,$R:$R,P9) -> 0
J11: =J9+7 -> 45733 | K11: =K9+7 -> 45734 | L11: =L9+7 -> 45735 | M11: =M9+7 -> 45736 | N11: =N9+7 -> 45737 | O11: =O9+7 -> 45738 | P11: =P9+7 -> 45739
J12: =sumifs($X:$X,$R:$R,J11) -> 0 | K12: =sumifs($X:$X,$R:$R,K11) -> 0 | L12: =sumifs($X:$X,$R:$R,L11) -> 0 | M12: =sumifs($X:$X,$R:$R,M11) -> 0 | N12: =sumifs($X:$X,$R:$R,N11) -> 0 | O12: =sumifs($X:$X,$R:$R,O11) -> 0 | P12: =sumifs($X:$X,$R:$R,P11) -> 0
J13: =J11+7 -> 45740 | K13: =K11+7 -> 45741 | L13: =L11+7 -> 45742 | M13: =M11+7 -> 45743 | N13: =N11+7 -> 45744 | O13: =O11+7 -> 45745 | P13: =P11+7 -> 45746
B14: 合計 | D14: =SUM(D6:D13) -> 0 | F14: 合計 | H14: =SUM(H6:H13) -> 0 | J14: =sumifs($X:$X,$R:$R,J13) -> 0 | K14: =sumifs($X:$X,$R:$R,K13) -> 0 | L14: =sumifs($X:$X,$R:$R,L13) -> 0 | M14: =sumifs($X:$X,$R:$R,M13) -> 0 | N14: =sumifs($X:$X,$R:$R,N13) -> 0 | O14: =sumifs($X:$X,$R:$R,O13) -> 0 | P14: =sumifs($X:$X,$R:$R,P13) -> 0
B16: 支出 | F16: 支出 | J16: 週予算 管理
B17: 固定費 | F17: 変動費
B18: 費目 | C18: 支払方法 | D18: 金額 | F18: 費目 | G18: 予算 | H18: 金額 | J18: 項目 | L18: 1week | O18: 2week
H19: =sumifs($X:$X,$U:$U,F19) -> 0 | K19: 予算 | L19: 金額 | M19: 差分 | N19: 予算 | O19: 金額 | P19: 差分
H20: =sumifs($X:$X,$U:$U,F20) -> 0 | L20: =sumifs($X:$X,$S:$S,$L$18,$U:$U,J20) -> 0 | M20: =K20-L20 -> 0 | O20: =sumifs($X:$X,$S:$S,$O$18,$U:$U,J20) -> 0 | P20: =N20-O20 -> 0
H21: =sumifs($X:$X,$U:$U,F21) -> 0 | L21: =sumifs($X:$X,$S:$S,$L$18,$U:$U,J21) -> 0 | M21: =K21-L21 -> 0 | O21: =sumifs($X:$X,$S:$S,$O$18,$U:$U,J21) -> 0 | P21: =N21-O21 -> 0
H22: =sumifs($X:$X,$U:$U,F22) -> 0 | L22: =sumifs($X:$X,$S:$S,$L$18,$U:$U,J22) -> 0 | M22: =K22-L22 -> 0 | O22: =sumifs($X:$X,$S:$S,$O$18,$U:$U,J22) -> 0 | P22: =N22-O22 -> 0
H23: =sumifs($X:$X,$U:$U,F23) -> 0 | L23: =sumifs($X:$X,$S:$S,$L$18,$U:$U,J23) -> 0 | M23: =K23-L23 -> 0 | O23: =sumifs($X:$X,$S:$S,$O$18,$U:$U,J23) -> 0 | P23: =N23-O23 -> 0
H24: =sumifs($X:$X,$U:$U,F24) -> 0 | L24: =sumifs($X:$X,$S:$S,$L$18,$U:$U,J24) -> 0 | M24: =K24-L24 -> 0 | O24: =sumifs($X:$X,$S:$S,$O$18,$U:$U,J24) -> 0 | P24: =N24-O24 -> 0
H25: =sumifs($X:$X,$U:$U,F25) -> 0 | L25: =sumifs($X:$X,$S:$S,$L$18,$U:$U,J25) -> 0 | M25: =K25-L25 -> 0 | O25: =sumifs($X:$X,$S:$S,$O$18,$U:$U,J25) -> 0 | P25: =N25-O25 -> 0
H26: =sumifs($X:$X,$U:$U,F26) -> 0 | L26: =sumifs($X:$X,$S:$S,$L$18,$U:$U,J26) -> 0 | M26: =K26-L26 -> 0 | O26: =sumifs($X:$X,$S:$S,$O$18,$U:$U,J26) -> 0 | P26: =N26-O26 -> 0
H27: =sumifs($X:$X,$U:$U,F27) -> 0 | J27: ALL | K27: =SUM(K20:K26) -> 0 | L27: =SUM(L20:L26) -> 0 | M27: =K27-L27 -> 0 | N27: =SUM(N20:N26) -> 0 | O27: =SUM(O20:O26) -> 0 | P27: =N27-O27 -> 0
H28: =sumifs($X:$X,$U:$U,F28) -> 0
H29: =sumifs($X:$X,$U:$U,F29) -> 0 | J29: 項目 | L29: 3week | O29: 4week
H30: =sumifs($X:$X,$U:$U,F30) -> 0 | K30: 予算 | L30: 金額 | M30: 差分 | N30: 予算 | O30: 金額 | P30: 差分
B31: 合計 | D31: =SUM(D19:D30) -> 0 | F31: 合計 | G31: =SUM(G19:G30) -> 0 | H31: =SUM(H19:H30) -> 0 | L31: =sumifs($X:$X,$S:$S,$L$29,$U:$U,J31) -> 0 | M31: =K31-L31 -> 0 | O31: =sumifs($X:$X,$S:$S,$O$29,$U:$U,J31) -> 0 | P31: =N31-O31 -> 0
L32: =sumifs($X:$X,$S:$S,$L$29,$U:$U,J32) -> 0 | M32: =K32-L32 -> 0 | O32: =sumifs($X:$X,$S:$S,$O$29,$U:$U,J32) -> 0 | P32: =N32-O32 -> 0
B33: 特別費 | F33: 今月の収支 | H33: 金額 | L33: =sumifs($X:$X,$S:$S,$L$29,$U:$U,J33) -> 0 | M33: =K33-L33 -> 0 | O33: =sumifs($X:$X,$S:$S,$O$29,$U:$U,J33) -> 0 | P33: =N33-O33 -> 0
B34: 費目 | C34: 支払方法 | D34: 金額 | F34: 収入（a） | H34: =D14 -> 0 | L34: =sumifs($X:$X,$S:$S,$L$29,$U:$U,J34) -> 0 | M34: =K34-L34 -> 0 | O34: =sumifs($X:$X,$S:$S,$O$29,$U:$U,J34) -> 0 | P34: =N34-O34 -> 0
F35: 先取り貯金・投資（b） | H35: =H14 -> 0 | L35: =sumifs($X:$X,$S:$S,$L$29,$U:$U,J35) -> 0 | M35: =K35-L35 -> 0 | O35: =sumifs($X:$X,$S:$S,$O$29,$U:$U,J35) -> 0 | P35: =N35-O35 -> 0
F36: 支出（c） | H36: =D31+H31 -> 0 | L36: =sumifs($X:$X,$S:$S,$L$29,$U:$U,J36) -> 0 | M36: =K36-L36 -> 0 | O36: =sumifs($X:$X,$S:$S,$O$29,$U:$U,J36) -> 0 | P36: =N36-O36 -> 0
F37: 余り貯金（d）※a-b-c | H37: =H34-H35-H36 -> 0 | L37: =sumifs($X:$X,$S:$S,$L$29,$U:$U,J37) -> 0 | M37: =K37-L37 -> 0 | O37: =sumifs($X:$X,$S:$S,$O$29,$U:$U,J37) -> 0 | P37: =N37-O37 -> 0
F38: 貯蓄合計（e）※b+d | H38: =H35+H37 -> 0 | J38: ALL | K38: =SUM(K31:K37) -> 0 | L38: =SUM(L31:L37) -> 0 | M38: =K38-L38 -> 0 | N38: =SUM(N31:N37) -> 0 | O38: =SUM(O31:O37) -> 0 | P38: =N38-O38 -> 0
F40: 支出率（c/a)×100 | G40: 貯蓄率 （e/a)×100 | J40: 項目 | L40: 5week | O40: ALL
F41: =H36/H34 -> #DIV/0! | G41: =H38/H34 -> #DIV/0! | K41: 予算 | L41: 金額 | M41: 差分 | N41: 予算 | O41: 金額 | P41: 差分
B42: 合計 | D42: =SUM(D35:D41) -> 0 | L42: =sumifs($X:$X,$S:$S,$L$40,$U:$U,J42) -> 0 | M42: =K42-L42 -> 0 | N42: =K20+N20+K31+N31+K42 -> 0 | O42: =L20+O20+L31+O31+L42 -> 0 | P42: =N42-O42 -> 0
D43: ※収支の計算外 | F43: ※目標：80%以下 | H43: ※目標：20%以上 | L43: =sumifs($X:$X,$S:$S,$L$40,$U:$U,J43) -> 0 | M43: =K43-L43 -> 0 | N43: =K21+N21+K32+N32+K43 -> 0 | O43: =L21+O21+L32+O32+L43 -> 0 | P43: =N43-O43 -> 0
B44: 振り返り | L44: =sumifs($X:$X,$S:$S,$L$40,$U:$U,J44) -> 0 | M44: =K44-L44 -> 0 | N44: =K22+N22+K33+N33+K44 -> 0 | O44: =L22+O22+L33+O33+L44 -> 0 | P44: =N44-O44 -> 0
L45: =sumifs($X:$X,$S:$S,$L$40,$U:$U,J45) -> 0 | M45: =K45-L45 -> 0 | N45: =K23+N23+K34+N34+K45 -> 0 | O45: =L23+O23+L34+O34+L45 -> 0 | P45: =N45-O45 -> 0
L46: =sumifs($X:$X,$S:$S,$L$40,$U:$U,J46) -> 0 | M46: =K46-L46 -> 0 | N46: =K24+N24+K35+N35+K46 -> 0 | O46: =L24+O24+L35+O35+L46 -> 0 | P46: =N46-O46 -> 0
L47: =sumifs($X:$X,$S:$S,$L$40,$U:$U,J47) -> 0 | M47: =K47-L47 -> 0 | N47: =K25+N25+K36+N36+K47 -> 0 | O47: =L25+O25+L36+O36+L47 -> 0 | P47: =N47-O47 -> 0
L48: =sumifs($X:$X,$S:$S,$L$40,$U:$U,J48) -> 0 | M48: =K48-L48 -> 0 | N48: =K26+N26+K37+N37+K48 -> 0 | O48: =L26+O26+L37+O37+L48 -> 0 | P48: =N48-O48 -> 0
J49: ALL | K49: =SUM(K42:K48) -> 0 | L49: =SUM(L42:L48) -> 0 | M49: =K49-L49 -> 0 | N49: =SUM(N42:N48) -> 0 | O49: =SUM(O42:O48) -> 0 | P49: =N49-O49 -> 0

Sheet 4月
B1: 4 | D1: ← 年・月を変更するとカレンダーが自動更新されます | J1: ※グレーのセルは自動反映します（入力不要）
B2: 2025 | J2: =DATE(B2,B1,1) -> 45748 | R2: 変動費 明細
B4: 収入 | F4: 先取り貯金・投資 | J4: 月 | K4: 火 | L4: 水 | M4: 木 | N4: 金 | O4: 土 | P4: 日 | R4: 日付 | S4: 週 | T4: 支払方法 | U4: 費目 | V4: 詳細 | X4: 金額 | Y4: 満足度
B5: 費目 | C5: 入金口座 | D5: 金額 | F5: 費目 | G5: 支払方法 | H5: 金額 | J5: =$J$2-weekday($J$2)+2 -> 45747 | K5: =J5+1 -> 45748 | L5: =K5+1 -> 45749 | M5: =L5+1 -> 45750 | N5: =M5+1 -> 45751 | O5: =N5+1 -> 45752 | P5: =O5+1 -> 45753 | R5: 45748
J6: =sumifs($X:$X,$R:$R,J5) -> 0 | K6: =sumifs($X:$X,$R:$R,K5) -> 0 | L6: =sumifs($X:$X,$R:$R,L5) -> 0 | M6: =sumifs($X:$X,$R:$R,M5) -> 0 | N6: =sumifs($X:$X,$R:$R,N5) -> 0 | O6: =sumifs($X:$X,$R:$R,O5) -> 0 | P6: =sumifs($X:$X,$R:$R,P5) -> 0
J7: =J5+7 -> 45754 | K7: =K5+7 -> 45755 | L7: =L5+7 -> 45756 | M7: =M5+7 -> 45757 | N7: =N5+7 -> 45758 | O7: =O5+7 -> 45759 | P7: =P5+7 -> 45760
J8: =sumifs($X:$X,$R:$R,J7) -> 0 | K8: =sumifs($X:$X,$R:$R,K7) -> 0 | L8: =sumifs($X:$X,$R:$R,L7) -> 0 | M8: =sumifs($X:$X,$R:$R,M7) -> 0 | N8: =sumifs($X:$X,$R:$R,N7) -> 0 | O8: =sumifs($X:$X,$R:$R,O7) -> 0 | P8: =sumifs($X:$X,$R:$R,P7) -> 0
J9: =J7+7 -> 45761 | K9: =K7+7 -> 45762 | L9: =L7+7 -> 45763 | M9: =M7+7 -> 45764 | N9: =N7+7 -> 45765 | O9: =O7+7 -> 45766 | P9: =P7+7 -> 45767
J10: =sumifs($X:$X,$R:$R,J9) -> 0 | K10: =sumifs($X:$X,$R:$R,K9) -> 0 | L10: =sumifs($X:$X,$R:$R,L9) -> 0 | M10: =sumifs($X:$X,$R:$R,M9) -> 0 | N10: =sumifs($X:$X,$R:$R,N9) -> 0 | O10: =sumifs($X:$X,$R:$R,O9) -> 0 | P10: =sumifs($X:$X,$R:$R,P9) -> 0
J11: =J9+7 -> 45768 | K11: =K9+7 -> 45769 | L11: =L9+7 -> 45770 | M11: =M9+7 -> 45771 | N11: =N9+7 -> 45772 | O11: =O9+7 -> 45773 | P11: =P9+7 -> 45774
J12: =sumifs($X:$X,$R:$R,J11) -> 0 | K12: =sumifs($X:$X,$R:$R,K11) -> 0 | L12: =sumifs($X:$X,$R:$R,L11) -> 0 | M12: =sumifs($X:$X,$R:$R,M11) -> 0 | N12: =sumifs($X:$X,$R:$R,N11) -> 0 | O12: =sumifs($X:$X,$R:$R,O11) -> 0 | P12: =sumifs($X:$X,$R:$R,P11) -> 0
J13: =J11+7 -> 45775 | K13: =K11+7 -> 45776 | L13: =L11+7 -> 45777 | M13: =M11+7 -> 45778 | N13: =N11+7 -> 45779 | O13: =O11+7 -> 45780 | P13: =P11+7 -> 45781
B14: 合計 | D14: =SUM(D6:D13) -> 0 | F14: 合計 | H14: =SUM(H6:H13) -> 0 | J14: =sumifs($X:$X,$R:$R,J13) -> 0 | K14: =sumifs($X:$X,$R:$R,K13) -> 0 | L14: =sumifs($X:$X,$R:$R,L13) -> 0 | M14: =sumifs($X:$X,$R:$R,M13) -> 0 | N14: =sumifs($X:$X,$R:$R,N13) -> 0 | O14: =sumifs($X:$X,$R:$R,O13) -> 0 | P14: =sumifs($X:$X,$R:$R,P13) -> 0
B16: 支出 | F16: 支出 | J16: 週予算 管理
B17: 固定費 | F17: 変動費
B18: 費目 | C18: 支払方法 | D18: 金額 | F18: 費目 | G18: 予算 | H18: 金額 | J18: 項目 | L18: 1week | O18: 2week
H19: =sumifs($X:$X,$U:$U,F19) -> 0 | K19: 予算 | L19: 金額 | M19: 差分 | N19: 予算 | O19: 金額 | P19: 差分
H20: =sumifs($X:$X,$U:$U,F20) -> 0 | L20: =sumifs($X:$X,$S:$S,$L$18,$U:$U,J20) -> 0 | M20: =K20-L20 -> 0 | O20: =sumifs($X:$X,$S:$S,$O$18,$U:$U,J20) -> 0 | P20: =N20-O20 -> 0
H21: =sumifs($X:$X,$U:$U,F21) -> 0 | L21: =sumifs($X:$X,$S:$S,$L$18,$U:$U,J21) -> 0 | M21: =K21-L21 -> 0 | O21: =sumifs($X:$X,$S:$S,$O$18,$U:$U,J21) -> 0 | P21: =N21-O21 -> 0
H22: =sumifs($X:$X,$U:$U,F22) -> 0 | L22: =sumifs($X:$X,$S:$S,$L$18,$U:$U,J22) -> 0 | M22: =K22-L22 -> 0 | O22: =sumifs($X:$X,$S:$S,$O$18,$U:$U,J22) -> 0 | P22: =N22-O22 -> 0
H23: =sumifs($X:$X,$U:$U,F23) -> 0 | L23: =sumifs($X:$X,$S:$S,$L$18,$U:$U,J23) -> 0 | M23: =K23-L23 -> 0 | O23: =sumifs($X:$X,$S:$S,$O$18,$U:$U,J23) -> 0 | P23: =N23-O23 -> 0
H24: =sumifs($X:$X,$U:$U,F24) -> 0 | L24: =sumifs($X:$X,$S:$S,$L$18,$U:$U,J24) -> 0 | M24: =K24-L24 -> 0 | O24: =sumifs($X:$X,$S:$S,$O$18,$U:$U,J24) -> 0 | P24: =N24-O24 -> 0
H25: =sumifs($X:$X,$U:$U,F25) -> 0 | L25: =sumifs($X:$X,$S:$S,$L$18,$U:$U,J25) -> 0 | M25: =K25-L25 -> 0 | O25: =sumifs($X:$X,$S:$S,$O$18,$U:$U,J25) -> 0 | P25: =N25-O25 -> 0
H26: =sumifs($X:$X,$U:$U,F26) -> 0 | L26: =sumifs($X:$X,$S:$S,$L$18,$U:$U,J26) -> 0 | M26: =K26-L26 -> 0 | O26: =sumifs($X:$X,$S:$S,$O$18,$U:$U,J26) -> 0 | P26: =N26-O26 -> 0
H27: =sumifs($X:$X,$U:$U,F27) -> 0 | J27: ALL | K27: =SUM(K20:K26) -> 0 | L27: =SUM(L20:L26) -> 0 | M27: =K27-L27 -> 0 | N27: =SUM(N20:N26) -> 0 | O27: =SUM(O20:O26) -> 0 | P27: =N27-O27 -> 0
H28: =sumifs($X:$X,$U:$U,F28) -> 0
H29: =sumifs($X:$X,$U:$U,F29) -> 0 | J29: 項目 | L29: 3week | O29: 4week
H30: =sumifs($X:$X,$U:$U,F30) -> 0 | K30: 予算 | L30: 金額 | M30: 差分 | N30: 予算 | O30: 金額 | P30: 差分
B31: 合計 | D31: =SUM(D19:D30) -> 0 | F31: 合計 | G31: =SUM(G19:G30) -> 0 | H31: =SUM(H19:H30) -> 0 | L31: =sumifs($X:$X,$S:$S,$L$29,$U:$U,J31) -> 0 | M31: =K31-L31 -> 0 | O31: =sumifs($X:$X,$S:$S,$O$29,$U:$U,J31) -> 0 | P31: =N31-O31 -> 0
L32: =sumifs($X:$X,$S:$S,$L$29,$U:$U,J32) -> 0 | M32: =K32-L32 -> 0 | O32: =sumifs($X:$X,$S:$S,$O$29,$U:$U,J32) -> 0 | P32: =N32-O32 -> 0
B33: 特別費 | F33: 今月の収支 | H33: 金額 | L33: =sumifs($X:$X,$S:$S,$L$29,$U:$U,J33) -> 0 | M33: =K33-L33 -> 0 | O33: =sumifs($X:$X,$S:$S,$O$29,$U:$U,J33) -> 0 | P33: =N33-O33 -> 0
B34: 費目 | C34: 支払方法 | D34: 金額 | F34: 収入（a） | H34: =D14 -> 0 | L34: =sumifs($X:$X,$S:$S,$L$29,$U:$U,J34) -> 0 | M34: =K34-L34 -> 0 | O34: =sumifs($X:$X,$S:$S,$O$29,$U:$U,J34) -> 0 | P34: =N34-O34 -> 0
F35: 先取り貯金・投資（b） | H35: =H14 -> 0 | L35: =sumifs($X:$X,$S:$S,$L$29,$U:$U,J35) -> 0 | M35: =K35-L35 -> 0 | O35: =sumifs($X:$X,$S:$S,$O$29,$U:$U,J35) -> 0 | P35: =N35-O35 -> 0
F36: 支出（c） | H36: =D31+H31 -> 0 | L36: =sumifs($X:$X,$S:$S,$L$29,$U:$U,J36) -> 0 | M36: =K36-L36 -> 0 | O36: =sumifs($X:$X,$S:$S,$O$29,$U:$U,J36) -> 0 | P36: =N36-O36 -> 0
F37: 余り貯金（d）※a-b-c | H37: =H34-H35-H36 -> 0 | L37: =sumifs($X:$X,$S:$S,$L$29,$U:$U,J37) -> 0 | M37: =K37-L37 -> 0 | O37: =sumifs($X:$X,$S:$S,$O$29,$U:$U,J37) -> 0 | P37: =N37-O37 -> 0
F38: 貯蓄合計（e）※b+d | H38: =H35+H37 -> 0 | J38: ALL | K38: =SUM(K31:K37) -> 0 | L38: =SUM(L31:L37) -> 0 | M38: =K38-L38 -> 0 | N38: =SUM(N31:N37) -> 0 | O38: =SUM(O31:O37) -> 0 | P38: =N38-O38 -> 0
F40: 支出率（c/a)×100 | G40: 貯蓄率 （e/a)×100 | J40: 項目 | L40: 5week | O40: ALL
F41: =H36/H34 -> #DIV/0! | G41: =H38/H34 -> #DIV/0! | K41: 予算 | L41: 金額 | M41: 差分 | N41: 予算 | O41: 金額 | P41: 差分
B42: 合計 | D42: =SUM(D35:D41) -> 0 | L42: =sumifs($X:$X,$S:$S,$L$40,$U:$U,J42) -> 0 | M42: =K42-L42 -> 0 | N42: =K20+N20+K31+N31+K42 -> 0 | O42: =L20+O20+L31+O31+L42 -> 0 | P42: =N42-O42 -> 0
D43: ※収支の計算外 | F43: ※目標：80%以下 | H43: ※目標：20%以上 | L43: =sumifs($X:$X,$S:$S,$L$40,$U:$U,J43) -> 0 | M43: =K43-L43 -> 0 | N43: =K21+N21+K32+N32+K43 -> 0 | O43: =L21+O21+L32+O32+L43 -> 0 | P43: =N43-O43 -> 0
B44: 振り返り | L44: =sumifs($X:$X,$S:$S,$L$40,$U:$U,J44) -> 0 | M44: =K44-L44 -> 0 | N44: =K22+N22+K33+N33+K44 -> 0 | O44: =L22+O22+L33+O33+L44 -> 0 | P44: =N44-O44 -> 0
L45: =sumifs($X:$X,$S:$S,$L$40,$U:$U,J45) -> 0 | M45: =K45-L45 -> 0 | N45: =K23+N23+K34+N34+K45 -> 0 | O45: =L23+O23+L34+O34+L45 -> 0 | P45: =N45-O45 -> 0
L46: =sumifs($X:$X,$S:$S,$L$40,$U:$U,J46) -> 0 | M46: =K46-L46 -> 0 | N46: =K24+N24+K35+N35+K46 -> 0 | O46: =L24+O24+L35+O35+L46 -> 0 | P46: =N46-O46 -> 0
L47: =sumifs($X:$X,$S:$S,$L$40,$U:$U,J47) -> 0 | M47: =K47-L47 -> 0 | N47: =K25+N25+K36+N36+K47 -> 0 | O47: =L25+O25+L36+O36+L47 -> 0 | P47: =N47-O47 -> 0
L48: =sumifs($X:$X,$S:$S,$L$40,$U:$U,J48) -> 0 | M48: =K48-L48 -> 0 | N48: =K26+N26+K37+N37+K48 -> 0 | O48: =L26+O26+L37+O37+L48 -> 0 | P48: =N48-O48 -> 0
J49: ALL | K49: =SUM(K42:K48) -> 0 | L49: =SUM(L42:L48) -> 0 | M49: =K49-L49 -> 0 | N49: =SUM(N42:N48) -> 0 | O49: =SUM(O42:O48) -> 0 | P49: =N49-O49 -> 0

Sheet 5月
B1: 5 | D1: ← 年・月を変更するとカレンダーが自動更新されます | J1: ※グレーのセルは自動反映します（入力不要）
B2: 2025 | J2: =DATE(B2,B1,1) -> 45778 | R2: 変動費 明細
B4: 収入 | F4: 先取り貯金・投資 | J4: 月 | K4: 火 | L4: 水 | M4: 木 | N4: 金 | O4: 土 | P4: 日 | R4: 日付 | S4: 週 | T4: 支払方法 | U4: 費目 | V4: 詳細 | X4: 金額 | Y4: 満足度
B5: 費目 | C5: 入金口座 | D5: 金額 | F5: 費目 | G5: 支払方法 | H5: 金額 | J5: =$J$2-weekday($J$2)+2 -> 45775 | K5: =J5+1 -> 45776 | L5: =K5+1 -> 45777 | M5: =L5+1 -> 45778 | N5: =M5+1 -> 45779 | O5: =N5+1 -> 45780 | P5: =O5+1 -> 45781 | R5: 45778
J6: =sumifs($X:$X,$R:$R,J5) -> 0 | K6: =sumifs($X:$X,$R:$R,K5) -> 0 | L6: =sumifs($X:$X,$R:$R,L5) -> 0 | M6: =sumifs($X:$X,$R:$R,M5) -> 0 | N6: =sumifs($X:$X,$R:$R,N5) -> 0 | O6: =sumifs($X:$X,$R:$R,O5) -> 0 | P6: =sumifs($X:$X,$R:$R,P5) -> 0
J7: =J5+7 -> 45782 | K7: =K5+7 -> 45783 | L7: =L5+7 -> 45784 | M7: =M5+7 -> 45785 | N7: =N5+7 -> 45786 | O7: =O5+7 -> 45787 | P7: =P5+7 -> 45788
J8: =sumifs($X:$X,$R:$R,J7) -> 0 | K8: =sumifs($X:$X,$R:$R,K7) -> 0 | L8: =sumifs($X:$X,$R:$R,L7) -> 0 | M8: =sumifs($X:$X,$R:$R,M7) -> 0 | N8: =sumifs($X:$X,$R:$R,N7) -> 0 | O8: =sumifs($X:$X,$R:$R,O7) -> 0 | P8: =sumifs($X:$X,$R:$R,P7) -> 0
J9: =J7+7 -> 45789 | K9: =K7+7 -> 45790 | L9: =L7+7 -> 45791 | M9: =M7+7 -> 45792 | N9: =N7+7 -> 45793 | O9: =O7+7 -> 45794 | P9: =P7+7 -> 45795
J10: =sumifs($X:$X,$R:$R,J9) -> 0 | K10: =sumifs($X:$X,$R:$R,K9) -> 0 | L10: =sumifs($X:$X,$R:$R,L9) -> 0 | M10: =sumifs($X:$X,$R:$R,M9) -> 0 | N10: =sumifs($X:$X,$R:$R,N9) -> 0 | O10: =sumifs($X:$X,$R:$R,O9) -> 0 | P10: =sumifs($X:$X,$R:$R,P9) -> 0
J11: =J9+7 -> 45796 | K11: =K9+7 -> 45797 | L11: =L9+7 -> 45798 | M11: =M9+7 -> 45799 | N11: =N9+7 -> 45800 | O11: =O9+7 -> 45801 | P11: =P9+7 -> 45802
J12: =sumifs($X:$X,$R:$R,J11) -> 0 | K12: =sumifs($X:$X,$R:$R,K11) -> 0 | L12: =sumifs($X:$X,$R:$R,L11) -> 0 | M12: =sumifs($X:$X,$R:$R,M11) -> 0 | N12: =sumifs($X:$X,$R:$R,N11) -> 0 | O12: =sumifs($X:$X,$R:$R,O11) -> 0 | P12: =sumifs($X:$X,$R:$R,P11) -> 0
J13: =J11+7 -> 45803 | K13: =K11+7 -> 45804 | L13: =L11+7 -> 45805 | M13: =M11+7 -> 45806 | N13: =N11+7 -> 45807 | O13: =O11+7 -> 45808 | P13: =P11+7 -> 45809
B14: 合計 | D14: =SUM(D6:D13) -> 0 | F14: 合計 | H14: =SUM(H6:H13) -> 0 | J14: =sumifs($X:$X,$R:$R,J13) -> 0 | K14: =sumifs($X:$X,$R:$R,K13) -> 0 | L14: =sumifs($X:$X,$R:$R,L13) -> 0 | M14: =sumifs($X:$X,$R:$R,M13) -> 0 | N14: =sumifs($X:$X,$R:$R,N13) -> 0 | O14: =sumifs($X:$X,$R:$R,O13) -> 0 | P14: =sumifs($X:$X,$R:$R,P13) -> 0
B16: 支出 | F16: 支出 | J16: 週予算 管理
B17: 固定費 | F17: 変動費
B18: 費目 | C18: 支払方法 | D18: 金額 | F18: 費目 | G18: 予算 | H18: 金額 | J18: 項目 | L18: 1week | O18: 2week
H19: =sumifs($X:$X,$U:$U,F19) -> 0 | K19: 予算 | L19: 金額 | M19: 差分 | N19: 予算 | O19: 金額 | P19: 差分
H20: =sumifs($X:$X,$U:$U,F20) -> 0 | L20: =sumifs($X:$X,$S:$S,$L$18,$U:$U,J20) -> 0 | M20: =K20-L20 -> 0 | O20: =sumifs($X:$X,$S:$S,$O$18,$U:$U,J20) -> 0 | P20: =N20-O20 -> 0
H21: =sumifs($X:$X,$U:$U,F21) -> 0 | L21: =sumifs($X:$X,$S:$S,$L$18,$U:$U,J21) -> 0 | M21: =K21-L21 -> 0 | O21: =sumifs($X:$X,$S:$S,$O$18,$U:$U,J21) -> 0 | P21: =N21-O21 -> 0
H22: =sumifs($X:$X,$U:$U,F22) -> 0 | L22: =sumifs($X:$X,$S:$S,$L$18,$U:$U,J22) -> 0 | M22: =K22-L22 -> 0 | O22: =sumifs($X:$X,$S:$S,$O$18,$U:$U,J22) -> 0 | P22: =N22-O22 -> 0
H23: =sumifs($X:$X,$U:$U,F23) -> 0 | L23: =sumifs($X:$X,$S:$S,$L$18,$U:$U,J23) -> 0 | M23: =K23-L23 -> 0 | O23: =sumifs($X:$X,$S:$S,$O$18,$U:$U,J23) -> 0 | P23: =N23-O23 -> 0
H24: =sumifs($X:$X,$U:$U,F24) -> 0 | L24: =sumifs($X:$X,$S:$S,$L$18,$U:$U,J24) -> 0 | M24: =K24-L24 -> 0 | O24: =sumifs($X:$X,$S:$S,$O$18,$U:$U,J24) -> 0 | P24: =N24-O24 -> 0
H25: =sumifs($X:$X,$U:$U,F25) -> 0 | L25: =sumifs($X:$X,$S:$S,$L$18,$U:$U,J25) -> 0 | M25: =K25-L25 -> 0 | O25: =sumifs($X:$X,$S:$S,$O$18,$U:$U,J25) -> 0 | P25: =N25-O25 -> 0
H26: =sumifs($X:$X,$U:$U,F26) -> 0 | L26: =sumifs($X:$X,$S:$S,$L$18,$U:$U,J26) -> 0 | M26: =K26-L26 -> 0 | O26: =sumifs($X:$X,$S:$S,$O$18,$U:$U,J26) -> 0 | P26: =N26-O26 -> 0
H27: =sumifs($X:$X,$U:$U,F27) -> 0 | J27: ALL | K27: =SUM(K20:K26) -> 0 | L27: =SUM(L20:L26) -> 0 | M27: =K27-L27 -> 0 | N27: =SUM(N20:N26) -> 0 | O27: =SUM(O20:O26) -> 0 | P27: =N27-O27 -> 0
H28: =sumifs($X:$X,$U:$U,F28) -> 0
H29: =sumifs($X:$X,$U:$U,F29) -> 0 | J29: 項目 | L29: 3week | O29: 4week
H30: =sumifs($X:$X,$U:$U,F30) -> 0 | K30: 予算 | L30: 金額 | M30: 差分 | N30: 予算 | O30: 金額 | P30: 差分
B31: 合計 | D31: =SUM(D19:D30) -> 0 | F31: 合計 | G31: =SUM(G19:G30) -> 0 | H31: =SUM(H19:H30) -> 0 | L31: =sumifs($X:$X,$S:$S,$L$29,$U:$U,J31) -> 0 | M31: =K31-L31 -> 0 | O31: =sumifs($X:$X,$S:$S,$O$29,$U:$U,J31) -> 0 | P31: =N31-O31 -> 0
L32: =sumifs($X:$X,$S:$S,$L$29,$U:$U,J32) -> 0 | M32: =K32-L32 -> 0 | O32: =sumifs($X:$X,$S:$S,$O$29,$U:$U,J32) -> 0 | P32: =N32-O32 -> 0
B33: 特別費 | F33: 今月の収支 | H33: 金額 | L33: =sumifs($X:$X,$S:$S,$L$29,$U:$U,J33) -> 0 | M33: =K33-L33 -> 0 | O33: =sumifs($X:$X,$S:$S,$O$29,$U:$U,J33) -> 0 | P33: =N33-O33 -> 0
B34: 費目 | C34: 支払方法 | D34: 金額 | F34: 収入（a） | H34: =D14 -> 0 | L34: =sumifs($X:$X,$S:$S,$L$29,$U:$U,J34) -> 0 | M34: =K34-L34 -> 0 | O34: =sumifs($X:$X,$S:$S,$O$29,$U:$U,J34) -> 0 | P34: =N34-O34 -> 0
F35: 先取り貯金・投資（b） | H35: =H14 -> 0 | L35: =sumifs($X:$X,$S:$S,$L$29,$U:$U,J35) -> 0 | M35: =K35-L35 -> 0 | O35: =sumifs($X:$X,$S:$S,$O$29,$U:$U,J35) -> 0 | P35: =N35-O35 -> 0
F36: 支出（c） | H36: =D31+H31 -> 0 | L36: =sumifs($X:$X,$S:$S,$L$29,$U:$U,J36) -> 0 | M36: =K36-L36 -> 0 | O36: =sumifs($X:$X,$S:$S,$O$29,$U:$U,J36) -> 0 | P36: =N36-O36 -> 0
F37: 余り貯金（d）※a-b-c | H37: =H34-H35-H36 -> 0 | L37: =sumifs($X:$X,$S:$S,$L$29,$U:$U,J37) -> 0 | M37: =K37-L37 -> 0 | O37: =sumifs($X:$X,$S:$S,$O$29,$U:$U,J37) -> 0 | P37: =N37-O37 -> 0
F38: 貯蓄合計（e）※b+d | H38: =H35+H37 -> 0 | J38: ALL | K38: =SUM(K31:K37) -> 0 | L38: =SUM(L31:L37) -> 0 | M38: =K38-L38 -> 0 | N38: =SUM(N31:N37) -> 0 | O38: =SUM(O31:O37) -> 0 | P38: =N38-O38 -> 0
F40: 支出率（c/a)×100 | G40: 貯蓄率 （e/a)×100 | J40: 項目 | L40: 5week | O40: ALL
F41: =H36/H34 -> #DIV/0! | G41: =H38/H34 -> #DIV/0! | K41: 予算 | L41: 金額 | M41: 差分 | N41: 予算 | O41: 金額 | P41: 差分
B42: 合計 | D42: =SUM(D35:D41) -> 0 | L42: =sumifs($X:$X,$S:$S,$L$40,$U:$U,J42) -> 0 | M42: =K42-L42 -> 0 | N42: =K20+N20+K31+N31+K42 -> 0 | O42: =L20+O20+L31+O31+L42 -> 0 | P42: =N42-O42 -> 0
D43: ※収支の計算外 | F43: ※目標：80%以下 | H43: ※目標：20%以上 | L43: =sumifs($X:$X,$S:$S,$L$40,$U:$U,J43) -> 0 | M43: =K43-L43 -> 0 | N43: =K21+N21+K32+N32+K43 -> 0 | O43: =L21+O21+L32+O32+L43 -> 0 | P43: =N43-O43 -> 0
B44: 振り返り | L44: =sumifs($X:$X,$S:$S,$L$40,$U:$U,J44) -> 0 | M44: =K44-L44 -> 0 | N44: =K22+N22+K33+N33+K44 -> 0 | O44: =L22+O22+L33+O33+L44 -> 0 | P44: =N44-O44 -> 0
L45: =sumifs($X:$X,$S:$S,$L$40,$U:$U,J45) -> 0 | M45: =K45-L45 -> 0 | N45: =K23+N23+K34+N34+K45 -> 0 | O45: =L23+O23+L34+O34+L45 -> 0 | P45: =N45-O45 -> 0
L46: =sumifs($X:$X,$S:$S,$L$40,$U:$U,J46) -> 0 | M46: =K46-L46 -> 0 | N46: =K24+N24+K35+N35+K46 -> 0 | O46: =L24+O24+L35+O35+L46 -> 0 | P46: =N46-O46 -> 0
L47: =sumifs($X:$X,$S:$S,$L$40,$U:$U,J47) -> 0 | M47: =K47-L47 -> 0 | N47: =K25+N25+K36+N36+K47 -> 0 | O47: =L25+O25+L36+O36+L47 -> 0 | P47: =N47-O47 -> 0
L48: =sumifs($X:$X,$S:$S,$L$40,$U:$U,J48) -> 0 | M48: =K48-L48 -> 0 | N48: =K26+N26+K37+N37+K48 -> 0 | O48: =L26+O26+L37+O37+L48 -> 0 | P48: =N48-O48 -> 0
J49: ALL | K49: =SUM(K42:K48) -> 0 | L49: =SUM(L42:L48) -> 0 | M49: =K49-L49 -> 0 | N49: =SUM(N42:N48) -> 0 | O49: =SUM(O42:O48) -> 0 | P49: =N49-O49 -> 0

Sheet 6月
B1: 6 | D1: ← 年・月を変更するとカレンダーが自動更新されます | J1: ※グレーのセルは自動反映します（入力不要）
B2: 2025 | J2: =DATE(B2,B1,1) -> 45809 | R2: 変動費 明細
B4: 収入 | F4: 先取り貯金・投資 | J4: 月 | K4: 火 | L4: 水 | M4: 木 | N4: 金 | O4: 土 | P4: 日 | R4: 日付 | S4: 週 | T4: 支払方法 | U4: 費目 | V4: 詳細 | X4: 金額 | Y4: 満足度
B5: 費目 | C5: 入金口座 | D5: 金額 | F5: 費目 | G5: 支払方法 | H5: 金額 | J5: =$J$2-weekday($J$2)+2 -> 45810 | K5: =J5+1 -> 45811 | L5: =K5+1 -> 45812 | M5: =L5+1 -> 45813 | N5: =M5+1 -> 45814 | O5: =N5+1 -> 45815 | P5: =O5+1 -> 45816 | R5: 45810
J6: =sumifs($X:$X,$R:$R,J5) -> 0 | K6: =sumifs($X:$X,$R:$R,K5) -> 0 | L6: =sumifs($X:$X,$R:$R,L5) -> 0 | M6: =sumifs($X:$X,$R:$R,M5) -> 0 | N6: =sumifs($X:$X,$R:$R,N5) -> 0 | O6: =sumifs($X:$X,$R:$R,O5) -> 0 | P6: =sumifs($X:$X,$R:$R,P5) -> 0
J7: =J5+7 -> 45817 | K7: =K5+7 -> 45818 | L7: =L5+7 -> 45819 | M7: =M5+7 -> 45820 | N7: =N5+7 -> 45821 | O7: =O5+7 -> 45822 | P7: =P5+7 -> 45823
J8: =sumifs($X:$X,$R:$R,J7) -> 0 | K8: =sumifs($X:$X,$R:$R,K7) -> 0 | L8: =sumifs($X:$X,$R:$R,L7) -> 0 | M8: =sumifs($X:$X,$R:$R,M7) -> 0 | N8: =sumifs($X:$X,$R:$R,N7) -> 0 | O8: =sumifs($X:$X,$R:$R,O7) -> 0 | P8: =sumifs($X:$X,$R:$R,P7) -> 0
J9: =J7+7 -> 45824 | K9: =K7+7 -> 45825 | L9: =L7+7 -> 45826 | M9: =M7+7 -> 45827 | N9: =N7+7 -> 45828 | O9: =O7+7 -> 45829 | P9: =P7+7 -> 45830
J10: =sumifs($X:$X,$R:$R,J9) -> 0 | K10: =sumifs($X:$X,$R:$R,K9) -> 0 | L10: =sumifs($X:$X,$R:$R,L9) -> 0 | M10: =sumifs($X:$X,$R:$R,M9) -> 0 | N10: =sumifs($X:$X,$R:$R,N9) -> 0 | O10: =sumifs($X:$X,$R:$R,O9) -> 0 | P10: =sumifs($X:$X,$R:$R,P9) -> 0
J11: =J9+7 -> 45831 | K11: =K9+7 -> 45832 | L11: =L9+7 -> 45833 | M11: =M9+7 -> 45834 | N11: =N9+7 -> 45835 | O11: =O9+7 -> 45836 | P11: =P9+7 -> 45837
J12: =sumifs($X:$X,$R:$R,J11) -> 0 | K12: =sumifs($X:$X,$R:$R,K11) -> 0 | L12: =sumifs($X:$X,$R:$R,L11) -> 0 | M12: =sumifs($X:$X,$R:$R,M11) -> 0 | N12: =sumifs($X:$X,$R:$R,N11) -> 0 | O12: =sumifs($X:$X,$R:$R,O11) -> 0 | P12: =sumifs($X:$X,$R:$R,P11) -> 0
J13: =J11+7 -> 45838 | K13: =K11+7 -> 45839 | L13: =L11+7 -> 45840 | M13: =M11+7 -> 45841 | N13: =N11+7 -> 45842 | O13: =O11+7 -> 45843 | P13: =P11+7 -> 45844
B14: 合計 | D14: =SUM(D6:D13) -> 0 | F14: 合計 | H14: =SUM(H6:H13) -> 0 | J14: =sumifs($X:$X,$R:$R,J13) -> 0 | K14: =sumifs($X:$X,$R:$R,K13) -> 0 | L14: =sumifs($X:$X,$R:$R,L13) -> 0 | M14: =sumifs($X:$X,$R:$R,M13) -> 0 | N14: =sumifs($X:$X,$R:$R,N13) -> 0 | O14: =sumifs($X:$X,$R:$R,O13) -> 0 | P14: =sumifs($X:$X,$R:$R,P13) -> 0
B16: 支出 | F16: 支出 | J16: 週予算 管理
B17: 固定費 | F17: 変動費
B18: 費目 | C18: 支払方法 | D18: 金額 | F18: 費目 | G18: 予算 | H18: 金額 | J18: 項目 | L18: 1week | O18: 2week
H19: =sumifs($X:$X,$U:$U,F19) -> 0 | K19: 予算 | L19: 金額 | M19: 差分 | N19: 予算 | O19: 金額 | P19: 差分
H20: =sumifs($X:$X,$U:$U,F20) -> 0 | L20: =sumifs($X:$X,$S:$S,$L$18,$U:$U,J20) -> 0 | M20: =K20-L20 -> 0 | O20: =sumifs($X:$X,$S:$S,$O$18,$U:$U,J20) -> 0 | P20: =N20-O20 -> 0
H21: =sumifs($X:$X,$U:$U,F21) -> 0 | L21: =sumifs($X:$X,$S:$S,$L$18,$U:$U,J21) -> 0 | M21: =K21-L21 -> 0 | O21: =sumifs($X:$X,$S:$S,$O$18,$U:$U,J21) -> 0 | P21: =N21-O21 -> 0
H22: =sumifs($X:$X,$U:$U,F22) -> 0 | L22: =sumifs($X:$X,$S:$S,$L$18,$U:$U,J22) -> 0 | M22: =K22-L22 -> 0 | O22: =sumifs($X:$X,$S:$S,$O$18,$U:$U,J22) -> 0 | P22: =N22-O22 -> 0
H23: =sumifs($X:$X,$U:$U,F23) -> 0 | L23: =sumifs($X:$X,$S:$S,$L$18,$U:$U,J23) -> 0 | M23: =K23-L23 -> 0 | O23: =sumifs($X:$X,$S:$S,$O$18,$U:$U,J23) -> 0 | P23: =N23-O23 -> 0
H24: =sumifs($X:$X,$U:$U,F24) -> 0 | L24: =sumifs($X:$X,$S:$S,$L$18,$U:$U,J24) -> 0 | M24: =K24-L24 -> 0 | O24: =sumifs($X:$X,$S:$S,$O$18,$U:$U,J24) -> 0 | P24: =N24-O24 -> 0
H25: =sumifs($X:$X,$U:$U,F25) -> 0 | L25: =sumifs($X:$X,$S:$S,$L$18,$U:$U,J25) -> 0 | M25: =K25-L25 -> 0 | O25: =sumifs($X:$X,$S:$S,$O$18,$U:$U,J25) -> 0 | P25: =N25-O25 -> 0
H26: =sumifs($X:$X,$U:$U,F26) -> 0 | L26: =sumifs($X:$X,$S:$S,$L$18,$U:$U,J26) -> 0 | M26: =K26-L26 -> 0 | O26: =sumifs($X:$X,$S:$S,$O$18,$U:$U,J26) -> 0 | P26: =N26-O26 -> 0
H27: =sumifs($X:$X,$U:$U,F27) -> 0 | J27: ALL | K27: =SUM(K20:K26) -> 0 | L27: =SUM(L20:L26) -> 0 | M27: =K27-L27 -> 0 | N27: =SUM(N20:N26) -> 0 | O27: =SUM(O20:O26) -> 0 | P27: =N27-O27 -> 0
H28: =sumifs($X:$X,$U:$U,F28) -> 0
H29: =sumifs($X:$X,$U:$U,F29) -> 0 | J29: 項目 | L29: 3week | O29: 4week
H30: =sumifs($X:$X,$U:$U,F30) -> 0 | K30: 予算 | L30: 金額 | M30: 差分 | N30: 予算 | O30: 金額 | P30: 差分
B31: 合計 | D31: =SUM(D19:D30) -> 0 | F31: 合計 | G31: =SUM(G19:G30) -> 0 | H31: =SUM(H19:H30) -> 0 | L31: =sumifs($X:$X,$S:$S,$L$29,$U:$U,J31) -> 0 | M31: =K31-L31 -> 0 | O31: =sumifs($X:$X,$S:$S,$O$29,$U:$U,J31) -> 0 | P31: =N31-O31 -> 0
L32: =sumifs($X:$X,$S:$S,$L$29,$U:$U,J32) -> 0 | M32: =K32-L32 -> 0 | O32: =sumifs($X:$X,$S:$S,$O$29,$U:$U,J32) -> 0 | P32: =N32-O32 -> 0
B33: 特別費 | F33: 今月の収支 | H33: 金額 | L33: =sumifs($X:$X,$S:$S,$L$29,$U:$U,J33) -> 0 | M33: =K33-L33 -> 0 | O33: =sumifs($X:$X,$S:$S,$O$29,$U:$U,J33) -> 0 | P33: =N33-O33 -> 0
B34: 費目 | C34: 支払方法 | D34: 金額 | F34: 収入（a） | H34: =D14 -> 0 | L34: =sumifs($X:$X,$S:$S,$L$29,$U:$U,J34) -> 0 | M34: =K34-L34 -> 0 | O34: =sumifs($X:$X,$S:$S,$O$29,$U:$U,J34) -> 0 | P34: =N34-O34 -> 0
F35: 先取り貯金・投資（b） | H35: =H14 -> 0 | L35: =sumifs($X:$X,$S:$S,$L$29,$U:$U,J35) -> 0 | M35: =K35-L35 -> 0 | O35: =sumifs($X:$X,$S:$S,$O$29,$U:$U,J35) -> 0 | P35: =N35-O35 -> 0
F36: 支出（c） | H36: =D31+H31 -> 0 | L36: =sumifs($X:$X,$S:$S,$L$29,$U:$U,J36) -> 0 | M36: =K36-L36 -> 0 | O36: =sumifs($X:$X,$S:$S,$O$29,$U:$U,J36) -> 0 | P36: =N36-O36 -> 0
F37: 余り貯金（d）※a-b-c | H37: =H34-H35-H36 -> 0 | L37: =sumifs($X:$X,$S:$S,$L$29,$U:$U,J37) -> 0 | M37: =K37-L37 -> 0 | O37: =sumifs($X:$X,$S:$S,$O$29,$U:$U,J37) -> 0 | P37: =N37-O37 -> 0
F38: 貯蓄合計（e）※b+d | H38: =H35+H37 -> 0 | J38: ALL | K38: =SUM(K31:K37) -> 0 | L38: =SUM(L31:L37) -> 0 | M38: =K38-L38 -> 0 | N38: =SUM(N31:N37) -> 0 | O38: =SUM(O31:O37) -> 0 | P38: =N38-O38 -> 0
F40: 支出率（c/a)×100 | G40: 貯蓄率 （e/a)×100 | J40: 項目 | L40: 5week | O40: ALL
F41: =H36/H34 -> #DIV/0! | G41: =H38/H34 -> #DIV/0! | K41: 予算 | L41: 金額 | M41: 差分 | N41: 予算 | O41: 金額 | P41: 差分
B42: 合計 | D42: =SUM(D35:D41) -> 0 | L42: =sumifs($X:$X,$S:$S,$L$40,$U:$U,J42) -> 0 | M42: =K42-L42 -> 0 | N42: =K20+N20+K31+N31+K42 -> 0 | O42: =L20+O20+L31+O31+L42 -> 0 | P42: =N42-O42 -> 0
D43: ※収支の計算外 | F43: ※目標：80%以下 | H43: ※目標：20%以上 | L43: =sumifs($X:$X,$S:$S,$L$40,$U:$U,J43) -> 0 | M43: =K43-L43 -> 0 | N43: =K21+N21+K32+N32+K43 -> 0 | O43: =L21+O21+L32+O32+L43 -> 0 | P43: =N43-O43 -> 0
B44: 振り返り | L44: =sumifs($X:$X,$S:$S,$L$40,$U:$U,J44) -> 0 | M44: =K44-L44 -> 0 | N44: =K22+N22+K33+N33+K44 -> 0 | O44: =L22+O22+L33+O33+L44 -> 0 | P44: =N44-O44 -> 0
L45: =sumifs($X:$X,$S:$S,$L$40,$U:$U,J45) -> 0 | M45: =K45-L45 -> 0 | N45: =K23+N23+K34+N34+K45 -> 0 | O45: =L23+O23+L34+O34+L45 -> 0 | P45: =N45-O45 -> 0
L46: =sumifs($X:$X,$S:$S,$L$40,$U:$U,J46) -> 0 | M46: =K46-L46 -> 0 | N46: =K24+N24+K35+N35+K46 -> 0 | O46: =L24+O24+L35+O35+L46 -> 0 | P46: =N46-O46 -> 0
L47: =sumifs($X:$X,$S:$S,$L$40,$U:$U,J47) -> 0 | M47: =K47-L47 -> 0 | N47: =K25+N25+K36+N36+K47 -> 0 | O47: =L25+O25+L36+O36+L47 -> 0 | P47: =N47-O47 -> 0
L48: =sumifs($X:$X,$S:$S,$L$40,$U:$U,J48) -> 0 | M48: =K48-L48 -> 0 | N48: =K26+N26+K37+N37+K48 -> 0 | O48: =L26+O26+L37+O37+L48 -> 0 | P48: =N48-O48 -> 0
J49: ALL | K49: =SUM(K42:K48) -> 0 | L49: =SUM(L42:L48) -> 0 | M49: =K49-L49 -> 0 | N49: =SUM(N42:N48) -> 0 | O49: =SUM(O42:O48) -> 0 | P49: =N49-O49 -> 0

Sheet 7月
B1: 7 | D1: ← 年・月を変更するとカレンダーが自動更新されます | J1: ※グレーのセルは自動反映します（入力不要）
B2: 2025 | J2: =DATE(B2,B1,1) -> 45839 | R2: 変動費 明細
B4: 収入 | F4: 先取り貯金・投資 | J4: 月 | K4: 火 | L4: 水 | M4: 木 | N4: 金 | O4: 土 | P4: 日 | R4: 日付 | S4: 週 | T4: 支払方法 | U4: 費目 | V4: 詳細 | X4: 金額 | Y4: 満足度
B5: 費目 | C5: 入金口座 | D5: 金額 | F5: 費目 | G5: 支払方法 | H5: 金額 | J5: =$J$2-weekday($J$2)+2 -> 45838 | K5: =J5+1 -> 45839 | L5: =K5+1 -> 45840 | M5: =L5+1 -> 45841 | N5: =M5+1 -> 45842 | O5: =N5+1 -> 45843 | P5: =O5+1 -> 45844 | R5: 45839
J6: =sumifs($X:$X,$R:$R,J5) -> 0 | K6: =sumifs($X:$X,$R:$R,K5) -> 0 | L6: =sumifs($X:$X,$R:$R,L5) -> 0 | M6: =sumifs($X:$X,$R:$R,M5) -> 0 | N6: =sumifs($X:$X,$R:$R,N5) -> 0 | O6: =sumifs($X:$X,$R:$R,O5) -> 0 | P6: =sumifs($X:$X,$R:$R,P5) -> 0
J7: =J5+7 -> 45845 | K7: =K5+7 -> 45846 | L7: =L5+7 -> 45847 | M7: =M5+7 -> 45848 | N7: =N5+7 -> 45849 | O7: =O5+7 -> 45850 | P7: =P5+7 -> 45851
J8: =sumifs($X:$X,$R:$R,J7) -> 0 | K8: =sumifs($X:$X,$R:$R,K7) -> 0 | L8: =sumifs($X:$X,$R:$R,L7) -> 0 | M8: =sumifs($X:$X,$R:$R,M7) -> 0 | N8: =sumifs($X:$X,$R:$R,N7) -> 0 | O8: =sumifs($X:$X,$R:$R,O7) -> 0 | P8: =sumifs($X:$X,$R:$R,P7) -> 0
J9: =J7+7 -> 45852 | K9: =K7+7 -> 45853 | L9: =L7+7 -> 45854 | M9: =M7+7 -> 45855 | N9: =N7+7 -> 45856 | O9: =O7+7 -> 45857 | P9: =P7+7 -> 45858
J10: =sumifs($X:$X,$R:$R,J9) -> 0 | K10: =sumifs($X:$X,$R:$R,K9) -> 0 | L10: =sumifs($X:$X,$R:$R,L9) -> 0 | M10: =sumifs($X:$X,$R:$R,M9) -> 0 | N10: =sumifs($X:$X,$R:$R,N9) -> 0 | O10: =sumifs($X:$X,$R:$R,O9) -> 0 | P10: =sumifs($X:$X,$R:$R,P9) -> 0
J11: =J9+7 -> 45859 | K11: =K9+7 -> 45860 | L11: =L9+7 -> 45861 | M11: =M9+7 -> 45862 | N11: =N9+7 -> 45863 | O11: =O9+7 -> 45864 | P11: =P9+7 -> 45865
J12: =sumifs($X:$X,$R:$R,J11) -> 0 | K12: =sumifs($X:$X,$R:$R,K11) -> 0 | L12: =sumifs($X:$X,$R:$R,L11) -> 0 | M12: =sumifs($X:$X,$R:$R,M11) -> 0 | N12: =sumifs($X:$X,$R:$R,N11) -> 0 | O12: =sumifs($X:$X,$R:$R,O11) -> 0 | P12: =sumifs($X:$X,$R:$R,P11) -> 0
J13: =J11+7 -> 45866 | K13: =K11+7 -> 45867 | L13: =L11+7 -> 45868 | M13: =M11+7 -> 45869 | N13: =N11+7 -> 45870 | O13: =O11+7 -> 45871 | P13: =P11+7 -> 45872
B14: 合計 | D14: =SUM(D6:D13) -> 0 | F14: 合計 | H14: =SUM(H6:H13) -> 0 | J14: =sumifs($X:$X,$R:$R,J13) -> 0 | K14: =sumifs($X:$X,$R:$R,K13) -> 0 | L14: =sumifs($X:$X,$R:$R,L13) -> 0 | M14: =sumifs($X:$X,$R:$R,M13) -> 0 | N14: =sumifs($X:$X,$R:$R,N13) -> 0 | O14: =sumifs($X:$X,$R:$R,O13) -> 0 | P14: =sumifs($X:$X,$R:$R,P13) -> 0
B16: 支出 | F16: 支出 | J16: 週予算 管理
B17: 固定費 | F17: 変動費
B18: 費目 | C18: 支払方法 | D18: 金額 | F18: 費目 | G18: 予算 | H18: 金額 | J18: 項目 | L18: 1week | O18: 2week
H19: =sumifs($X:$X,$U:$U,F19) -> 0 | K19: 予算 | L19: 金額 | M19: 差分 | N19: 予算 | O19: 金額 | P19: 差分
H20: =sumifs($X:$X,$U:$U,F20) -> 0 | L20: =sumifs($X:$X,$S:$S,$L$18,$U:$U,J20) -> 0 | M20: =K20-L20 -> 0 | O20: =sumifs($X:$X,$S:$S,$O$18,$U:$U,J20) -> 0 | P20: =N20-O20 -> 0
H21: =sumifs($X:$X,$U:$U,F21) -> 0 | L21: =sumifs($X:$X,$S:$S,$L$18,$U:$U,J21) -> 0 | M21: =K21-L21 -> 0 | O21: =sumifs($X:$X,$S:$S,$O$18,$U:$U,J21) -> 0 | P21: =N21-O21 -> 0
H22: =sumifs($X:$X,$U:$U,F22) -> 0 | L22: =sumifs($X:$X,$S:$S,$L$18,$U:$U,J22) -> 0 | M22: =K22-L22 -> 0 | O22: =sumifs($X:$X,$S:$S,$O$18,$U:$U,J22) -> 0 | P22: =N22-O22 -> 0
H23: =sumifs($X:$X,$U:$U,F23) -> 0 | L23: =sumifs($X:$X,$S:$S,$L$18,$U:$U,J23) -> 0 | M23: =K23-L23 -> 0 | O23: =sumifs($X:$X,$S:$S,$O$18,$U:$U,J23) -> 0 | P23: =N23-O23 -> 0
H24: =sumifs($X:$X,$U:$U,F24) -> 0 | L24: =sumifs($X:$X,$S:$S,$L$18,$U:$U,J24) -> 0 | M24: =K24-L24 -> 0 | O24: =sumifs($X:$X,$S:$S,$O$18,$U:$U,J24) -> 0 | P24: =N24-O24 -> 0
H25: =sumifs($X:$X,$U:$U,F25) -> 0 | L25: =sumifs($X:$X,$S:$S,$L$18,$U:$U,J25) -> 0 | M25: =K25-L25 -> 0 | O25: =sumifs($X:$X,$S:$S,$O$18,$U:$U,J25) -> 0 | P25: =N25-O25 -> 0
H26: =sumifs($X:$X,$U:$U,F26) -> 0 | L26: =sumifs($X:$X,$S:$S,$L$18,$U:$U,J26) -> 0 | M26: =K26-L26 -> 0 | O26: =sumifs($X:$X,$S:$S,$O$18,$U:$U,J26) -> 0 | P26: =N26-O26 -> 0
H27: =sumifs($X:$X,$U:$U,F27) -> 0 | J27: ALL | K27: =SUM(K20:K26) -> 0 | L27: =SUM(L20:L26) -> 0 | M27: =K27-L27 -> 0 | N27: =SUM(N20:N26) -> 0 | O27: =SUM(O20:O26) -> 0 | P27: =N27-O27 -> 0
H28: =sumifs($X:$X,$U:$U,F28) -> 0
H29: =sumifs($X:$X,$U:$U,F29) -> 0 | J29: 項目 | L29: 3week | O29: 4week
H30: =sumifs($X:$X,$U:$U,F30) -> 0 | K30: 予算 | L30: 金額 | M30: 差分 | N30: 予算 | O30: 金額 | P30: 差分
B31: 合計 | D31: =SUM(D19:D30) -> 0 | F31: 合計 | G31: =SUM(G19:G30) -> 0 | H31: =SUM(H19:H30) -> 0 | L31: =sumifs($X:$X,$S:$S,$L$29,$U:$U,J31) -> 0 | M31: =K31-L31 -> 0 | O31: =sumifs($X:$X,$S:$S,$O$29,$U:$U,J31) -> 0 | P31: =N31-O31 -> 0
L32: =sumifs($X:$X,$S:$S,$L$29,$U:$U,J32) -> 0 | M32: =K32-L32 -> 0 | O32: =sumifs($X:$X,$S:$S,$O$29,$U:$U,J32) -> 0 | P32: =N32-O32 -> 0
B33: 特別費 | F33: 今月の収支 | H33: 金額 | L33: =sumifs($X:$X,$S:$S,$L$29,$U:$U,J33) -> 0 | M33: =K33-L33 -> 0 | O33: =sumifs($X:$X,$S:$S,$O$29,$U:$U,J33) -> 0 | P33: =N33-O33 -> 0
B34: 費目 | C34: 支払方法 | D34: 金額 | F34: 収入（a） | H34: =D14 -> 0 | L34: =sumifs($X:$X,$S:$S,$L$29,$U:$U,J34) -> 0 | M34: =K34-L34 -> 0 | O34: =sumifs($X:$X,$S:$S,$O$29,$U:$U,J34) -> 0 | P34: =N34-O34 -> 0
F35: 先取り貯金・投資（b） | H35: =H14 -> 0 | L35: =sumifs($X:$X,$S:$S,$L$29,$U:$U,J35) -> 0 | M35: =K35-L35 -> 0 | O35: =sumifs($X:$X,$S:$S,$O$29,$U:$U,J35) -> 0 | P35: =N35-O35 -> 0
F36: 支出（c） | H36: =D31+H31 -> 0 | L36: =sumifs($X:$X,$S:$S,$L$29,$U:$U,J36) -> 0 | M36: =K36-L36 -> 0 | O36: =sumifs($X:$X,$S:$S,$O$29,$U:$U,J36) -> 0 | P36: =N36-O36 -> 0
F37: 余り貯金（d）※a-b-c | H37: =H34-H35-H36 -> 0 | L37: =sumifs($X:$X,$S:$S,$L$29,$U:$U,J37) -> 0 | M37: =K37-L37 -> 0 | O37: =sumifs($X:$X,$S:$S,$O$29,$U:$U,J37) -> 0 | P37: =N37-O37 -> 0
F38: 貯蓄合計（e）※b+d | H38: =H35+H37 -> 0 | J38: ALL | K38: =SUM(K31:K37) -> 0 | L38: =SUM(L31:L37) -> 0 | M38: =K38-L38 -> 0 | N38: =SUM(N31:N37) -> 0 | O38: =SUM(O31:O37) -> 0 | P38: =N38-O38 -> 0
F40: 支出率（c/a)×100 | G40: 貯蓄率 （e/a)×100 | J40: 項目 | L40: 5week | O40: ALL
F41: =H36/H34 -> #DIV/0! | G41: =H38/H34 -> #DIV/0! | K41: 予算 | L41: 金額 | M41: 差分 | N41: 予算 | O41: 金額 | P41: 差分
B42: 合計 | D42: =SUM(D35:D41) -> 0 | L42: =sumifs($X:$X,$S:$S,$L$40,$U:$U,J42) -> 0 | M42: =K42-L42 -> 0 | N42: =K20+N20+K31+N31+K42 -> 0 | O42: =L20+O20+L31+O31+L42 -> 0 | P42: =N42-O42 -> 0
D43: ※収支の計算外 | F43: ※目標：80%以下 | H43: ※目標：20%以上 | L43: =sumifs($X:$X,$S:$S,$L$40,$U:$U,J43) -> 0 | M43: =K43-L43 -> 0 | N43: =K21+N21+K32+N32+K43 -> 0 | O43: =L21+O21+L32+O32+L43 -> 0 | P43: =N43-O43 -> 0
B44: 振り返り | L44: =sumifs($X:$X,$S:$S,$L$40,$U:$U,J44) -> 0 | M44: =K44-L44 -> 0 | N44: =K22+N22+K33+N33+K44 -> 0 | O44: =L22+O22+L33+O33+L44 -> 0 | P44: =N44-O44 -> 0
L45: =sumifs($X:$X,$S:$S,$L$40,$U:$U,J45) -> 0 | M45: =K45-L45 -> 0 | N45: =K23+N23+K34+N34+K45 -> 0 | O45: =L23+O23+L34+O34+L45 -> 0 | P45: =N45-O45 -> 0
L46: =sumifs($X:$X,$S:$S,$L$40,$U:$U,J46) -> 0 | M46: =K46-L46 -> 0 | N46: =K24+N24+K35+N35+K46 -> 0 | O46: =L24+O24+L35+O35+L46 -> 0 | P46: =N46-O46 -> 0
L47: =sumifs($X:$X,$S:$S,$L$40,$U:$U,J47) -> 0 | M47: =K47-L47 -> 0 | N47: =K25+N25+K36+N36+K47 -> 0 | O47: =L25+O25+L36+O36+L47 -> 0 | P47: =N47-O47 -> 0
L48: =sumifs($X:$X,$S:$S,$L$40,$U:$U,J48) -> 0 | M48: =K48-L48 -> 0 | N48: =K26+N26+K37+N37+K48 -> 0 | O48: =L26+O26+L37+O37+L48 -> 0 | P48: =N48-O48 -> 0
J49: ALL | K49: =SUM(K42:K48) -> 0 | L49: =SUM(L42:L48) -> 0 | M49: =K49-L49 -> 0 | N49: =SUM(N42:N48) -> 0 | O49: =SUM(O42:O48) -> 0 | P49: =N49-O49 -> 0

Sheet 8月
B1: 8 | D1: ← 年・月を変更するとカレンダーが自動更新されます | J1: ※グレーのセルは自動反映します（入力不要）
B2: 2025 | J2: =DATE(B2,B1,1) -> 45870 | R2: 変動費 明細
B4: 収入 | F4: 先取り貯金・投資 | J4: 月 | K4: 火 | L4: 水 | M4: 木 | N4: 金 | O4: 土 | P4: 日 | R4: 日付 | S4: 週 | T4: 支払方法 | U4: 費目 | V4: 詳細 | X4: 金額 | Y4: 満足度
B5: 費目 | C5: 入金口座 | D5: 金額 | F5: 費目 | G5: 支払方法 | H5: 金額 | J5: =$J$2-weekday($J$2)+2 -> 45866 | K5: =J5+1 -> 45867 | L5: =K5+1 -> 45868 | M5: =L5+1 -> 45869 | N5: =M5+1 -> 45870 | O5: =N5+1 -> 45871 | P5: =O5+1 -> 45872 | R5: 45870
J6: =sumifs($X:$X,$R:$R,J5) -> 0 | K6: =sumifs($X:$X,$R:$R,K5) -> 0 | L6: =sumifs($X:$X,$R:$R,L5) -> 0 | M6: =sumifs($X:$X,$R:$R,M5) -> 0 | N6: =sumifs($X:$X,$R:$R,N5) -> 0 | O6: =sumifs($X:$X,$R:$R,O5) -> 0 | P6: =sumifs($X:$X,$R:$R,P5) -> 0
J7: =J5+7 -> 45873 | K7: =K5+7 -> 45874 | L7: =L5+7 -> 45875 | M7: =M5+7 -> 45876 | N7: =N5+7 -> 45877 | O7: =O5+7 -> 45878 | P7: =P5+7 -> 45879
J8: =sumifs($X:$X,$R:$R,J7) -> 0 | K8: =sumifs($X:$X,$R:$R,K7) -> 0 | L8: =sumifs($X:$X,$R:$R,L7) -> 0 | M8: =sumifs($X:$X,$R:$R,M7) -> 0 | N8: =sumifs($X:$X,$R:$R,N7) -> 0 | O8: =sumifs($X:$X,$R:$R,O7) -> 0 | P8: =sumifs($X:$X,$R:$R,P7) -> 0
J9: =J7+7 -> 45880 | K9: =K7+7 -> 45881 | L9: =L7+7 -> 45882 | M9: =M7+7 -> 45883 | N9: =N7+7 -> 45884 | O9: =O7+7 -> 45885 | P9: =P7+7 -> 45886
J10: =sumifs($X:$X,$R:$R,J9) -> 0 | K10: =sumifs($X:$X,$R:$R,K9) -> 0 | L10: =sumifs($X:$X,$R:$R,L9) -> 0 | M10: =sumifs($X:$X,$R:$R,M9) -> 0 | N10: =sumifs($X:$X,$R:$R,N9) -> 0 | O10: =sumifs($X:$X,$R:$R,O9) -> 0 | P10: =sumifs($X:$X,$R:$R,P9) -> 0
J11: =J9+7 -> 45887 | K11: =K9+7 -> 45888 | L11: =L9+7 -> 45889 | M11: =M9+7 -> 45890 | N11: =N9+7 -> 45891 | O11: =O9+7 -> 45892 | P11: =P9+7 -> 45893
J12: =sumifs($X:$X,$R:$R,J11) -> 0 | K12: =sumifs($X:$X,$R:$R,K11) -> 0 | L12: =sumifs($X:$X,$R:$R,L11) -> 0 | M12: =sumifs($X:$X,$R:$R,M11) -> 0 | N12: =sumifs($X:$X,$R:$R,N11) -> 0 | O12: =sumifs($X:$X,$R:$R,O11) -> 0 | P12: =sumifs($X:$X,$R:$R,P11) -> 0
J13: =J11+7 -> 45894 | K13: =K11+7 -> 45895 | L13: =L11+7 -> 45896 | M13: =M11+7 -> 45897 | N13: =N11+7 -> 45898 | O13: =O11+7 -> 45899 | P13: =P11+7 -> 45900
B14: 合計 | D14: =SUM(D6:D13) -> 0 | F14: 合計 | H14: =SUM(H6:H13) -> 0 | J14: =sumifs($X:$X,$R:$R,J13) -> 0 | K14: =sumifs($X:$X,$R:$R,K13) -> 0 | L14: =sumifs($X:$X,$R:$R,L13) -> 0 | M14: =sumifs($X:$X,$R:$R,M13) -> 0 | N14: =sumifs($X:$X,$R:$R,N13) -> 0 | O14: =sumifs($X:$X,$R:$R,O13) -> 0 | P14: =sumifs($X:$X,$R:$R,P13) -> 0
B16: 支出 | F16: 支出 | J16: 週予算 管理
B17: 固定費 | F17: 変動費
B18: 費目 | C18: 支払方法 | D18: 金額 | F18: 費目 | G18: 予算 | H18: 金額 | J18: 項目 | L18: 1week | O18: 2week
H19: =sumifs($X:$X,$U:$U,F19) -> 0 | K19: 予算 | L19: 金額 | M19: 差分 | N19: 予算 | O19: 金額 | P19: 差分
H20: =sumifs($X:$X,$U:$U,F20) -> 0 | L20: =sumifs($X:$X,$S:$S,$L$18,$U:$U,J20) -> 0 | M20: =K20-L20 -> 0 | O20: =sumifs($X:$X,$S:$S,$O$18,$U:$U,J20) -> 0 | P20: =N20-O20 -> 0
H21: =sumifs($X:$X,$U:$U,F21) -> 0 | L21: =sumifs($X:$X,$S:$S,$L$18,$U:$U,J21) -> 0 | M21: =K21-L21 -> 0 | O21: =sumifs($X:$X,$S:$S,$O$18,$U:$U,J21) -> 0 | P21: =N21-O21 -> 0
H22: =sumifs($X:$X,$U:$U,F22) -> 0 | L22: =sumifs($X:$X,$S:$S,$L$18,$U:$U,J22) -> 0 | M22: =K22-L22 -> 0 | O22: =sumifs($X:$X,$S:$S,$O$18,$U:$U,J22) -> 0 | P22: =N22-O22 -> 0
H23: =sumifs($X:$X,$U:$U,F23) -> 0 | L23: =sumifs($X:$X,$S:$S,$L$18,$U:$U,J23) -> 0 | M23: =K23-L23 -> 0 | O23: =sumifs($X:$X,$S:$S,$O$18,$U:$U,J23) -> 0 | P23: =N23-O23 -> 0
H24: =sumifs($X:$X,$U:$U,F24) -> 0 | L24: =sumifs($X:$X,$S:$S,$L$18,$U:$U,J24) -> 0 | M24: =K24-L24 -> 0 | O24: =sumifs($X:$X,$S:$S,$O$18,$U:$U,J24) -> 0 | P24: =N24-O24 -> 0
H25: =sumifs($X:$X,$U:$U,F25) -> 0 | L25: =sumifs($X:$X,$S:$S,$L$18,$U:$U,J25) -> 0 | M25: =K25-L25 -> 0 | O25: =sumifs($X:$X,$S:$S,$O$18,$U:$U,J25) -> 0 | P25: =N25-O25 -> 0
H26: =sumifs($X:$X,$U:$U,F26) -> 0 | L26: =sumifs($X:$X,$S:$S,$L$18,$U:$U,J26) -> 0 | M26: =K26-L26 -> 0 | O26: =sumifs($X:$X,$S:$S,$O$18,$U:$U,J26) -> 0 | P26: =N26-O26 -> 0
H27: =sumifs($X:$X,$U:$U,F27) -> 0 | J27: ALL | K27: =SUM(K20:K26) -> 0 | L27: =SUM(L20:L26) -> 0 | M27: =K27-L27 -> 0 | N27: =SUM(N20:N26) -> 0 | O27: =SUM(O20:O26) -> 0 | P27: =N27-O27 -> 0
H28: =sumifs($X:$X,$U:$U,F28) -> 0
H29: =sumifs($X:$X,$U:$U,F29) -> 0 | J29: 項目 | L29: 3week | O29: 4week
H30: =sumifs($X:$X,$U:$U,F30) -> 0 | K30: 予算 | L30: 金額 | M30: 差分 | N30: 予算 | O30: 金額 | P30: 差分
B31: 合計 | D31: =SUM(D19:D30) -> 0 | F31: 合計 | G31: =SUM(G19:G30) -> 0 | H31: =SUM(H19:H30) -> 0 | L31: =sumifs($X:$X,$S:$S,$L$29,$U:$U,J31) -> 0 | M31: =K31-L31 -> 0 | O31: =sumifs($X:$X,$S:$S,$O$29,$U:$U,J31) -> 0 | P31: =N31-O31 -> 0
L32: =sumifs($X:$X,$S:$S,$L$29,$U:$U,J32) -> 0 | M32: =K32-L32 -> 0 | O32: =sumifs($X:$X,$S:$S,$O$29,$U:$U,J32) -> 0 | P32: =N32-O32 -> 0
B33: 特別費 | F33: 今月の収支 | H33: 金額 | L33: =sumifs($X:$X,$S:$S,$L$29,$U:$U,J33) -> 0 | M33: =K33-L33 -> 0 | O33: =sumifs($X:$X,$S:$S,$O$29,$U:$U,J33) -> 0 | P33: =N33-O33 -> 0
B34: 費目 | C34: 支払方法 | D34: 金額 | F34: 収入（a） | H34: =D14 -> 0 | L34: =sumifs($X:$X,$S:$S,$L$29,$U:$U,J34) -> 0 | M34: =K34-L34 -> 0 | O34: =sumifs($X:$X,$S:$S,$O$29,$U:$U,J34) -> 0 | P34: =N34-O34 -> 0
F35: 先取り貯金・投資（b） | H35: =H14 -> 0 | L35: =sumifs($X:$X,$S:$S,$L$29,$U:$U,J35) -> 0 | M35: =K35-L35 -> 0 | O35: =sumifs($X:$X,$S:$S,$O$29,$U:$U,J35) -> 0 | P35: =N35-O35 -> 0
F36: 支出（c） | H36: =D31+H31 -> 0 | L36: =sumifs($X:$X,$S:$S,$L$29,$U:$U,J36) -> 0 | M36: =K36-L36 -> 0 | O36: =sumifs($X:$X,$S:$S,$O$29,$U:$U,J36) -> 0 | P36: =N36-O36 -> 0
F37: 余り貯金（d）※a-b-c | H37: =H34-H35-H36 -> 0 | L37: =sumifs($X:$X,$S:$S,$L$29,$U:$U,J37) -> 0 | M37: =K37-L37 -> 0 | O37: =sumifs($X:$X,$S:$S,$O$29,$U:$U,J37) -> 0 | P37: =N37-O37 -> 0
F38: 貯蓄合計（e）※b+d | H38: =H35+H37 -> 0 | J38: ALL | K38: =SUM(K31:K37) -> 0 | L38: =SUM(L31:L37) -> 0 | M38: =K38-L38 -> 0 | N38: =SUM(N31:N37) -> 0 | O38: =SUM(O31:O37) -> 0 | P38: =N38-O38 -> 0
F40: 支出率（c/a)×100 | G40: 貯蓄率 （e/a)×100 | J40: 項目 | L40: 5week | O40: ALL
F41: =H36/H34 -> #DIV/0! | G41: =H38/H34 -> #DIV/0! | K41: 予算 | L41: 金額 | M41: 差分 | N41: 予算 | O41: 金額 | P41: 差分
B42: 合計 | D42: =SUM(D35:D41) -> 0 | L42: =sumifs($X:$X,$S:$S,$L$40,$U:$U,J42) -> 0 | M42: =K42-L42 -> 0 | N42: =K20+N20+K31+N31+K42 -> 0 | O42: =L20+O20+L31+O31+L42 -> 0 | P42: =N42-O42 -> 0
D43: ※収支の計算外 | F43: ※目標：80%以下 | H43: ※目標：20%以上 | L43: =sumifs($X:$X,$S:$S,$L$40,$U:$U,J43) -> 0 | M43: =K43-L43 -> 0 | N43: =K21+N21+K32+N32+K43 -> 0 | O43: =L21+O21+L32+O32+L43 -> 0 | P43: =N43-O43 -> 0
B44: 振り返り | L44: =sumifs($X:$X,$S:$S,$L$40,$U:$U,J44) -> 0 | M44: =K44-L44 -> 0 | N44: =K22+N22+K33+N33+K44 -> 0 | O44: =L22+O22+L33+O33+L44 -> 0 | P44: =N44-O44 -> 0
L45: =sumifs($X:$X,$S:$S,$L$40,$U:$U,J45) -> 0 | M45: =K45-L45 -> 0 | N45: =K23+N23+K34+N34+K45 -> 0 | O45: =L23+O23+L34+O34+L45 -> 0 | P45: =N45-O45 -> 0
L46: =sumifs($X:$X,$S:$S,$L$40,$U:$U,J46) -> 0 | M46: =K46-L46 -> 0 | N46: =K24+N24+K35+N35+K46 -> 0 | O46: =L24+O24+L35+O35+L46 -> 0 | P46: =N46-O46 -> 0
L47: =sumifs($X:$X,$S:$S,$L$40,$U:$U,J47) -> 0 | M47: =K47-L47 -> 0 | N47: =K25+N25+K36+N36+K47 -> 0 | O47: =L25+O25+L36+O36+L47 -> 0 | P47: =N47-O47 -> 0
L48: =sumifs($X:$X,$S:$S,$L$40,$U:$U,J48) -> 0 | M48: =K48-L48 -> 0 | N48: =K26+N26+K37+N37+K48 -> 0 | O48: =L26+O26+L37+O37+L48 -> 0 | P48: =N48-O48 -> 0
J49: ALL | K49: =SUM(K42:K48) -> 0 | L49: =SUM(L42:L48) -> 0 | M49: =K49-L49 -> 0 | N49: =SUM(N42:N48) -> 0 | O49: =SUM(O42:O48) -> 0 | P49: =N49-O49 -> 0

Sheet 9月
B1: 9 | D1: ← 年・月を変更するとカレンダーが自動更新されます | J1: ※グレーのセルは自動反映します（入力不要）
B2: 2025 | J2: =DATE(B2,B1,1) -> 45901 | R2: 変動費 明細
B4: 収入 | F4: 先取り貯金・投資 | J4: 月 | K4: 火 | L4: 水 | M4: 木 | N4: 金 | O4: 土 | P4: 日 | R4: 日付 | S4: 週 | T4: 支払方法 | U4: 費目 | V4: 詳細 | X4: 金額 | Y4: 満足度
B5: 費目 | C5: 入金口座 | D5: 金額 | F5: 費目 | G5: 支払方法 | H5: 金額 | J5: =$J$2-weekday($J$2)+2 -> 45901 | K5: =J5+1 -> 45902 | L5: =K5+1 -> 45903 | M5: =L5+1 -> 45904 | N5: =M5+1 -> 45905 | O5: =N5+1 -> 45906 | P5: =O5+1 -> 45907 | R5: 45903
J6: =sumifs($X:$X,$R:$R,J5) -> 0 | K6: =sumifs($X:$X,$R:$R,K5) -> 0 | L6: =sumifs($X:$X,$R:$R,L5) -> 0 | M6: =sumifs($X:$X,$R:$R,M5) -> 0 | N6: =sumifs($X:$X,$R:$R,N5) -> 0 | O6: =sumifs($X:$X,$R:$R,O5) -> 0 | P6: =sumifs($X:$X,$R:$R,P5) -> 0
J7: =J5+7 -> 45908 | K7: =K5+7 -> 45909 | L7: =L5+7 -> 45910 | M7: =M5+7 -> 45911 | N7: =N5+7 -> 45912 | O7: =O5+7 -> 45913 | P7: =P5+7 -> 45914
J8: =sumifs($X:$X,$R:$R,J7) -> 0 | K8: =sumifs($X:$X,$R:$R,K7) -> 0 | L8: =sumifs($X:$X,$R:$R,L7) -> 0 | M8: =sumifs($X:$X,$R:$R,M7) -> 0 | N8: =sumifs($X:$X,$R:$R,N7) -> 0 | O8: =sumifs($X:$X,$R:$R,O7) -> 0 | P8: =sumifs($X:$X,$R:$R,P7) -> 0
J9: =J7+7 -> 45915 | K9: =K7+7 -> 45916 | L9: =L7+7 -> 45917 | M9: =M7+7 -> 45918 | N9: =N7+7 -> 45919 | O9: =O7+7 -> 45920 | P9: =P7+7 -> 45921
J10: =sumifs($X:$X,$R:$R,J9) -> 0 | K10: =sumifs($X:$X,$R:$R,K9) -> 0 | L10: =sumifs($X:$X,$R:$R,L9) -> 0 | M10: =sumifs($X:$X,$R:$R,M9) -> 0 | N10: =sumifs($X:$X,$R:$R,N9) -> 0 | O10: =sumifs($X:$X,$R:$R,O9) -> 0 | P10: =sumifs($X:$X,$R:$R,P9) -> 0
J11: =J9+7 -> 45922 | K11: =K9+7 -> 45923 | L11: =L9+7 -> 45924 | M11: =M9+7 -> 45925 | N11: =N9+7 -> 45926 | O11: =O9+7 -> 45927 | P11: =P9+7 -> 45928
J12: =sumifs($X:$X,$R:$R,J11) -> 0 | K12: =sumifs($X:$X,$R:$R,K11) -> 0 | L12: =sumifs($X:$X,$R:$R,L11) -> 0 | M12: =sumifs($X:$X,$R:$R,M11) -> 0 | N12: =sumifs($X:$X,$R:$R,N11) -> 0 | O12: =sumifs($X:$X,$R:$R,O11) -> 0 | P12: =sumifs($X:$X,$R:$R,P11) -> 0
J13: =J11+7 -> 45929 | K13: =K11+7 -> 45930 | L13: =L11+7 -> 45931 | M13: =M11+7 -> 45932 | N13: =N11+7 -> 45933 | O13: =O11+7 -> 45934 | P13: =P11+7 -> 45935
B14: 合計 | D14: =SUM(D6:D13) -> 0 | F14: 合計 | H14: =SUM(H6:H13) -> 0 | J14: =sumifs($X:$X,$R:$R,J13) -> 0 | K14: =sumifs($X:$X,$R:$R,K13) -> 0 | L14: =sumifs($X:$X,$R:$R,L13) -> 0 | M14: =sumifs($X:$X,$R:$R,M13) -> 0 | N14: =sumifs($X:$X,$R:$R,N13) -> 0 | O14: =sumifs($X:$X,$R:$R,O13) -> 0 | P14: =sumifs($X:$X,$R:$R,P13) -> 0
B16: 支出 | F16: 支出 | J16: 週予算 管理
B17: 固定費 | F17: 変動費
B18: 費目 | C18: 支払方法 | D18: 金額 | F18: 費目 | G18: 予算 | H18: 金額 | J18: 項目 | L18: 1week | O18: 2week
H19: =sumifs($X:$X,$U:$U,F19) -> 0 | K19: 予算 | L19: 金額 | M19: 差分 | N19: 予算 | O19: 金額 | P19: 差分
H20: =sumifs($X:$X,$U:$U,F20) -> 0 | L20: =sumifs($X:$X,$S:$S,$L$18,$U:$U,J20) -> 0 | M20: =K20-L20 -> 0 | O20: =sumifs($X:$X,$S:$S,$O$18,$U:$U,J20) -> 0 | P20: =N20-O20 -> 0
H21: =sumifs($X:$X,$U:$U,F21) -> 0 | L21: =sumifs($X:$X,$S:$S,$L$18,$U:$U,J21) -> 0 | M21: =K21-L21 -> 0 | O21: =sumifs($X:$X,$S:$S,$O$18,$U:$U,J21) -> 0 | P21: =N21-O21 -> 0
H22: =sumifs($X:$X,$U:$U,F22) -> 0 | L22: =sumifs($X:$X,$S:$S,$L$18,$U:$U,J22) -> 0 | M22: =K22-L22 -> 0 | O22: =sumifs($X:$X,$S:$S,$O$18,$U:$U,J22) -> 0 | P22: =N22-O22 -> 0
H23: =sumifs($X:$X,$U:$U,F23) -> 0 | L23: =sumifs($X:$X,$S:$S,$L$18,$U:$U,J23) -> 0 | M23: =K23-L23 -> 0 | O23: =sumifs($X:$X,$S:$S,$O$18,$U:$U,J23) -> 0 | P23: =N23-O23 -> 0
H24: =sumifs($X:$X,$U:$U,F24) -> 0 | L24: =sumifs($X:$X,$S:$S,$L$18,$U:$U,J24) -> 0 | M24: =K24-L24 -> 0 | O24: =sumifs($X:$X,$S:$S,$O$18,$U:$U,J24) -> 0 | P24: =N24-O24 -> 0
H25: =sumifs($X:$X,$U:$U,F25) -> 0 | L25: =sumifs($X:$X,$S:$S,$L$18,$U:$U,J25) -> 0 | M25: =K25-L25 -> 0 | O25: =sumifs($X:$X,$S:$S,$O$18,$U:$U,J25) -> 0 | P25: =N25-O25 -> 0
H26: =sumifs($X:$X,$U:$U,F26) -> 0 | L26: =sumifs($X:$X,$S:$S,$L$18,$U:$U,J26) -> 0 | M26: =K26-L26 -> 0 | O26: =sumifs($X:$X,$S:$S,$O$18,$U:$U,J26) -> 0 | P26: =N26-O26 -> 0
H27: =sumifs($X:$X,$U:$U,F27) -> 0 | J27: ALL | K27: =SUM(K20:K26) -> 0 | L27: =SUM(L20:L26) -> 0 | M27: =K27-L27 -> 0 | N27: =SUM(N20:N26) -> 0 | O27: =SUM(O20:O26) -> 0 | P27: =N27-O27 -> 0
H28: =sumifs($X:$X,$U:$U,F28) -> 0
H29: =sumifs($X:$X,$U:$U,F29) -> 0 | J29: 項目 | L29: 3week | O29: 4week
H30: =sumifs($X:$X,$U:$U,F30) -> 0 | K30: 予算 | L30: 金額 | M30: 差分 | N30: 予算 | O30: 金額 | P30: 差分
B31: 合計 | D31: =SUM(D19:D30) -> 0 | F31: 合計 | G31: =SUM(G19:G30) -> 0 | H31: =SUM(H19:H30) -> 0 | L31: =sumifs($X:$X,$S:$S,$L$29,$U:$U,J31) -> 0 | M31: =K31-L31 -> 0 | O31: =sumifs($X:$X,$S:$S,$O$29,$U:$U,J31) -> 0 | P31: =N31-O31 -> 0
L32: =sumifs($X:$X,$S:$S,$L$29,$U:$U,J32) -> 0 | M32: =K32-L32 -> 0 | O32: =sumifs($X:$X,$S:$S,$O$29,$U:$U,J32) -> 0 | P32: =N32-O32 -> 0
B33: 特別費 | F33: 今月の収支 | H33: 金額 | L33: =sumifs($X:$X,$S:$S,$L$29,$U:$U,J33) -> 0 | M33: =K33-L33 -> 0 | O33: =sumifs($X:$X,$S:$S,$O$29,$U:$U,J33) -> 0 | P33: =N33-O33 -> 0
B34: 費目 | C34: 支払方法 | D34: 金額 | F34: 収入（a） | H34: =D14 -> 0 | L34: =sumifs($X:$X,$S:$S,$L$29,$U:$U,J34) -> 0 | M34: =K34-L34 -> 0 | O34: =sumifs($X:$X,$S:$S,$O$29,$U:$U,J34) -> 0 | P34: =N34-O34 -> 0
F35: 先取り貯金・投資（b） | H35: =H14 -> 0 | L35: =sumifs($X:$X,$S:$S,$L$29,$U:$U,J35) -> 0 | M35: =K35-L35 -> 0 | O35: =sumifs($X:$X,$S:$S,$O$29,$U:$U,J35) -> 0 | P35: =N35-O35 -> 0
F36: 支出（c） | H36: =D31+H31 -> 0 | L36: =sumifs($X:$X,$S:$S,$L$29,$U:$U,J36) -> 0 | M36: =K36-L36 -> 0 | O36: =sumifs($X:$X,$S:$S,$O$29,$U:$U,J36) -> 0 | P36: =N36-O36 -> 0
F37: 余り貯金（d）※a-b-c | H37: =H34-H35-H36 -> 0 | L37: =sumifs($X:$X,$S:$S,$L$29,$U:$U,J37) -> 0 | M37: =K37-L37 -> 0 | O37: =sumifs($X:$X,$S:$S,$O$29,$U:$U,J37) -> 0 | P37: =N37-O37 -> 0
F38: 貯蓄合計（e）※b+d | H38: =H35+H37 -> 0 | J38: ALL | K38: =SUM(K31:K37) -> 0 | L38: =SUM(L31:L37) -> 0 | M38: =K38-L38 -> 0 | N38: =SUM(N31:N37) -> 0 | O38: =SUM(O31:O37) -> 0 | P38: =N38-O38 -> 0
F40: 支出率（c/a)×100 | G40: 貯蓄率 （e/a)×100 | J40: 項目 | L40: 5week | O40: ALL
F41: =H36/H34 -> #DIV/0! | G41: =H38/H34 -> #DIV/0! | K41: 予算 | L41: 金額 | M41: 差分 | N41: 予算 | O41: 金額 | P41: 差分
B42: 合計 | D42: =SUM(D35:D41) -> 0 | L42: =sumifs($X:$X,$S:$S,$L$40,$U:$U,J42) -> 0 | M42: =K42-L42 -> 0 | N42: =K20+N20+K31+N31+K42 -> 0 | O42: =L20+O20+L31+O31+L42 -> 0 | P42: =N42-O42 -> 0
D43: ※収支の計算外 | F43: ※目標：80%以下 | H43: ※目標：20%以上 | L43: =sumifs($X:$X,$S:$S,$L$40,$U:$U,J43) -> 0 | M43: =K43-L43 -> 0 | N43: =K21+N21+K32+N32+K43 -> 0 | O43: =L21+O21+L32+O32+L43 -> 0 | P43: =N43-O43 -> 0
B44: 振り返り | L44: =sumifs($X:$X,$S:$S,$L$40,$U:$U,J44) -> 0 | M44: =K44-L44 -> 0 | N44: =K22+N22+K33+N33+K44 -> 0 | O44: =L22+O22+L33+O33+L44 -> 0 | P44: =N44-O44 -> 0
L45: =sumifs($X:$X,$S:$S,$L$40,$U:$U,J45) -> 0 | M45: =K45-L45 -> 0 | N45: =K23+N23+K34+N34+K45 -> 0 | O45: =L23+O23+L34+O34+L45 -> 0 | P45: =N45-O45 -> 0
L46: =sumifs($X:$X,$S:$S,$L$40,$U:$U,J46) -> 0 | M46: =K46-L46 -> 0 | N46: =K24+N24+K35+N35+K46 -> 0 | O46: =L24+O24+L35+O35+L46 -> 0 | P46: =N46-O46 -> 0
L47: =sumifs($X:$X,$S:$S,$L$40,$U:$U,J47) -> 0 | M47: =K47-L47 -> 0 | N47: =K25+N25+K36+N36+K47 -> 0 | O47: =L25+O25+L36+O36+L47 -> 0 | P47: =N47-O47 -> 0
L48: =sumifs($X:$X,$S:$S,$L$40,$U:$U,J48) -> 0 | M48: =K48-L48 -> 0 | N48: =K26+N26+K37+N37+K48 -> 0 | O48: =L26+O26+L37+O37+L48 -> 0 | P48: =N48-O48 -> 0
J49: ALL | K49: =SUM(K42:K48) -> 0 | L49: =SUM(L42:L48) -> 0 | M49: =K49-L49 -> 0 | N49: =SUM(N42:N48) -> 0 | O49: =SUM(O42:O48) -> 0 | P49: =N49-O49 -> 0

Sheet 10月
B1: 10 | D1: ← 年・月を変更するとカレンダーが自動更新されます | J1: ※グレーのセルは自動反映します（入力不要）
B2: 2025 | J2: =DATE(B2,B1,1) -> 45931 | R2: 変動費 明細
B4: 収入 | F4: 先取り貯金・投資 | J4: 月 | K4: 火 | L4: 水 | M4: 木 | N4: 金 | O4: 土 | P4: 日 | R4: 日付 | S4: 週 | T4: 支払方法 | U4: 費目 | V4: 詳細 | X4: 金額 | Y4: 満足度
B5: 費目 | C5: 入金口座 | D5: 金額 | F5: 費目 | G5: 支払方法 | H5: 金額 | J5: =$J$2-weekday($J$2)+2 -> 45929 | K5: =J5+1 -> 45930 | L5: =K5+1 -> 45931 | M5: =L5+1 -> 45932 | N5: =M5+1 -> 45933 | O5: =N5+1 -> 45934 | P5: =O5+1 -> 45935 | R5: 45931
J6: =sumifs($X:$X,$R:$R,J5) -> 0 | K6: =sumifs($X:$X,$R:$R,K5) -> 0 | L6: =sumifs($X:$X,$R:$R,L5) -> 0 | M6: =sumifs($X:$X,$R:$R,M5) -> 0 | N6: =sumifs($X:$X,$R:$R,N5) -> 0 | O6: =sumifs($X:$X,$R:$R,O5) -> 0 | P6: =sumifs($X:$X,$R:$R,P5) -> 0
J7: =J5+7 -> 45936 | K7: =K5+7 -> 45937 | L7: =L5+7 -> 45938 | M7: =M5+7 -> 45939 | N7: =N5+7 -> 45940 | O7: =O5+7 -> 45941 | P7: =P5+7 -> 45942
J8: =sumifs($X:$X,$R:$R,J7) -> 0 | K8: =sumifs($X:$X,$R:$R,K7) -> 0 | L8: =sumifs($X:$X,$R:$R,L7) -> 0 | M8: =sumifs($X:$X,$R:$R,M7) -> 0 | N8: =sumifs($X:$X,$R:$R,N7) -> 0 | O8: =sumifs($X:$X,$R:$R,O7) -> 0 | P8: =sumifs($X:$X,$R:$R,P7) -> 0
J9: =J7+7 -> 45943 | K9: =K7+7 -> 45944 | L9: =L7+7 -> 45945 | M9: =M7+7 -> 45946 | N9: =N7+7 -> 45947 | O9: =O7+7 -> 45948 | P9: =P7+7 -> 45949
J10: =sumifs($X:$X,$R:$R,J9) -> 0 | K10: =sumifs($X:$X,$R:$R,K9) -> 0 | L10: =sumifs($X:$X,$R:$R,L9) -> 0 | M10: =sumifs($X:$X,$R:$R,M9) -> 0 | N10: =sumifs($X:$X,$R:$R,N9) -> 0 | O10: =sumifs($X:$X,$R:$R,O9) -> 0 | P10: =sumifs($X:$X,$R:$R,P9) -> 0
J11: =J9+7 -> 45950 | K11: =K9+7 -> 45951 | L11: =L9+7 -> 45952 | M11: =M9+7 -> 45953 | N11: =N9+7 -> 45954 | O11: =O9+7 -> 45955 | P11: =P9+7 -> 45956
J12: =sumifs($X:$X,$R:$R,J11) -> 0 | K12: =sumifs($X:$X,$R:$R,K11) -> 0 | L12: =sumifs($X:$X,$R:$R,L11) -> 0 | M12: =sumifs($X:$X,$R:$R,M11) -> 0 | N12: =sumifs($X:$X,$R:$R,N11) -> 0 | O12: =sumifs($X:$X,$R:$R,O11) -> 0 | P12: =sumifs($X:$X,$R:$R,P11) -> 0
J13: =J11+7 -> 45957 | K13: =K11+7 -> 45958 | L13: =L11+7 -> 45959 | M13: =M11+7 -> 45960 | N13: =N11+7 -> 45961 | O13: =O11+7 -> 45962 | P13: =P11+7 -> 45963
B14: 合計 | D14: =SUM(D6:D13) -> 0 | F14: 合計 | H14: =SUM(H6:H13) -> 0 | J14: =sumifs($X:$X,$R:$R,J13) -> 0 | K14: =sumifs($X:$X,$R:$R,K13) -> 0 | L14: =sumifs($X:$X,$R:$R,L13) -> 0 | M14: =sumifs($X:$X,$R:$R,M13) -> 0 | N14: =sumifs($X:$X,$R:$R,N13) -> 0 | O14: =sumifs($X:$X,$R:$R,O13) -> 0 | P14: =sumifs($X:$X,$R:$R,P13) -> 0
B16: 支出 | F16: 支出 | J16: 週予算 管理
B17: 固定費 | F17: 変動費
B18: 費目 | C18: 支払方法 | D18: 金額 | F18: 費目 | G18: 予算 | H18: 金額 | J18: 項目 | L18: 1week | O18: 2week
H19: =sumifs($X:$X,$U:$U,F19) -> 0 | K19: 予算 | L19: 金額 | M19: 差分 | N19: 予算 | O19: 金額 | P19: 差分
H20: =sumifs($X:$X,$U:$U,F20) -> 0 | L20: =sumifs($X:$X,$S:$S,$L$18,$U:$U,J20) -> 0 | M20: =K20-L20 -> 0 | O20: =sumifs($X:$X,$S:$S,$O$18,$U:$U,J20) -> 0 | P20: =N20-O20 -> 0
H21: =sumifs($X:$X,$U:$U,F21) -> 0 | L21: =sumifs($X:$X,$S:$S,$L$18,$U:$U,J21) -> 0 | M21: =K21-L21 -> 0 | O21: =sumifs($X:$X,$S:$S,$O$18,$U:$U,J21) -> 0 | P21: =N21-O21 -> 0
H22: =sumifs($X:$X,$U:$U,F22) -> 0 | L22: =sumifs($X:$X,$S:$S,$L$18,$U:$U,J22) -> 0 | M22: =K22-L22 -> 0 | O22: =sumifs($X:$X,$S:$S,$O$18,$U:$U,J22) -> 0 | P22: =N22-O22 -> 0
H23: =sumifs($X:$X,$U:$U,F23) -> 0 | L23: =sumifs($X:$X,$S:$S,$L$18,$U:$U,J23) -> 0 | M23: =K23-L23 -> 0 | O23: =sumifs($X:$X,$S:$S,$O$18,$U:$U,J23) -> 0 | P23: =N23-O23 -> 0
H24: =sumifs($X:$X,$U:$U,F24) -> 0 | L24: =sumifs($X:$X,$S:$S,$L$18,$U:$U,J24) -> 0 | M24: =K24-L24 -> 0 | O24: =sumifs($X:$X,$S:$S,$O$18,$U:$U,J24) -> 0 | P24: =N24-O24 -> 0
H25: =sumifs($X:$X,$U:$U,F25) -> 0 | L25: =sumifs($X:$X,$S:$S,$L$18,$U:$U,J25) -> 0 | M25: =K25-L25 -> 0 | O25: =sumifs($X:$X,$S:$S,$O$18,$U:$U,J25) -> 0 | P25: =N25-O25 -> 0
H26: =sumifs($X:$X,$U:$U,F26) -> 0 | L26: =sumifs($X:$X,$S:$S,$L$18,$U:$U,J26) -> 0 | M26: =K26-L26 -> 0 | O26: =sumifs($X:$X,$S:$S,$O$18,$U:$U,J26) -> 0 | P26: =N26-O26 -> 0
H27: =sumifs($X:$X,$U:$U,F27) -> 0 | J27: ALL | K27: =SUM(K20:K26) -> 0 | L27: =SUM(L20:L26) -> 0 | M27: =K27-L27 -> 0 | N27: =SUM(N20:N26) -> 0 | O27: =SUM(O20:O26) -> 0 | P27: =N27-O27 -> 0
H28: =sumifs($X:$X,$U:$U,F28) -> 0
H29: =sumifs($X:$X,$U:$U,F29) -> 0 | J29: 項目 | L29: 3week | O29: 4week
H30: =sumifs($X:$X,$U:$U,F30) -> 0 | K30: 予算 | L30: 金額 | M30: 差分 | N30: 予算 | O30: 金額 | P30: 差分
B31: 合計 | D31: =SUM(D19:D30) -> 0 | F31: 合計 | G31: =SUM(G19:G30) -> 0 | H31: =SUM(H19:H30) -> 0 | L31: =sumifs($X:$X,$S:$S,$L$29,$U:$U,J31) -> 0 | M31: =K31-L31 -> 0 | O31: =sumifs($X:$X,$S:$S,$O$29,$U:$U,J31) -> 0 | P31: =N31-O31 -> 0
L32: =sumifs($X:$X,$S:$S,$L$29,$U:$U,J32) -> 0 | M32: =K32-L32 -> 0 | O32: =sumifs($X:$X,$S:$S,$O$29,$U:$U,J32) -> 0 | P32: =N32-O32 -> 0
B33: 特別費 | F33: 今月の収支 | H33: 金額 | L33: =sumifs($X:$X,$S:$S,$L$29,$U:$U,J33) -> 0 | M33: =K33-L33 -> 0 | O33: =sumifs($X:$X,$S:$S,$O$29,$U:$U,J33) -> 0 | P33: =N33-O33 -> 0
B34: 費目 | C34: 支払方法 | D34: 金額 | F34: 収入（a） | H34: =D14 -> 0 | L34: =sumifs($X:$X,$S:$S,$L$29,$U:$U,J34) -> 0 | M34: =K34-L34 -> 0 | O34: =sumifs($X:$X,$S:$S,$O$29,$U:$U,J34) -> 0 | P34: =N34-O34 -> 0
F35: 先取り貯金・投資（b） | H35: =H14 -> 0 | L35: =sumifs($X:$X,$S:$S,$L$29,$U:$U,J35) -> 0 | M35: =K35-L35 -> 0 | O35: =sumifs($X:$X,$S:$S,$O$29,$U:$U,J35) -> 0 | P35: =N35-O35 -> 0
F36: 支出（c） | H36: =D31+H31 -> 0 | L36: =sumifs($X:$X,$S:$S,$L$29,$U:$U,J36) -> 0 | M36: =K36-L36 -> 0 | O36: =sumifs($X:$X,$S:$S,$O$29,$U:$U,J36) -> 0 | P36: =N36-O36 -> 0
F37: 余り貯金（d）※a-b-c | H37: =H34-H35-H36 -> 0 | L37: =sumifs($X:$X,$S:$S,$L$29,$U:$U,J37) -> 0 | M37: =K37-L37 -> 0 | O37: =sumifs($X:$X,$S:$S,$O$29,$U:$U,J37) -> 0 | P37: =N37-O37 -> 0
F38: 貯蓄合計（e）※b+d | H38: =H35+H37 -> 0 | J38: ALL | K38: =SUM(K31:K37) -> 0 | L38: =SUM(L31:L37) -> 0 | M38: =K38-L38 -> 0 | N38: =SUM(N31:N37) -> 0 | O38: =SUM(O31:O37) -> 0 | P38: =N38-O38 -> 0
F40: 支出率（c/a)×100 | G40: 貯蓄率 （e/a)×100 | J40: 項目 | L40: 5week | O40: ALL
F41: =H36/H34 -> #DIV/0! | G41: =H38/H34 -> #DIV/0! | K41: 予算 | L41: 金額 | M41: 差分 | N41: 予算 | O41: 金額 | P41: 差分
B42: 合計 | D42: =SUM(D35:D41) -> 0 | L42: =sumifs($X:$X,$S:$S,$L$40,$U:$U,J42) -> 0 | M42: =K42-L42 -> 0 | N42: =K20+N20+K31+N31+K42 -> 0 | O42: =L20+O20+L31+O31+L42 -> 0 | P42: =N42-O42 -> 0
D43: ※収支の計算外 | F43: ※目標：80%以下 | H43: ※目標：20%以上 | L43: =sumifs($X:$X,$S:$S,$L$40,$U:$U,J43) -> 0 | M43: =K43-L43 -> 0 | N43: =K21+N21+K32+N32+K43 -> 0 | O43: =L21+O21+L32+O32+L43 -> 0 | P43: =N43-O43 -> 0
B44: 振り返り | L44: =sumifs($X:$X,$S:$S,$L$40,$U:$U,J44) -> 0 | M44: =K44-L44 -> 0 | N44: =K22+N22+K33+N33+K44 -> 0 | O44: =L22+O22+L33+O33+L44 -> 0 | P44: =N44-O44 -> 0
L45: =sumifs($X:$X,$S:$S,$L$40,$U:$U,J45) -> 0 | M45: =K45-L45 -> 0 | N45: =K23+N23+K34+N34+K45 -> 0 | O45: =L23+O23+L34+O34+L45 -> 0 | P45: =N45-O45 -> 0
L46: =sumifs($X:$X,$S:$S,$L$40,$U:$U,J46) -> 0 | M46: =K46-L46 -> 0 | N46: =K24+N24+K35+N35+K46 -> 0 | O46: =L24+O24+L35+O35+L46 -> 0 | P46: =N46-O46 -> 0
L47: =sumifs($X:$X,$S:$S,$L$40,$U:$U,J47) -> 0 | M47: =K47-L47 -> 0 | N47: =K25+N25+K36+N36+K47 -> 0 | O47: =L25+O25+L36+O36+L47 -> 0 | P47: =N47-O47 -> 0
L48: =sumifs($X:$X,$S:$S,$L$40,$U:$U,J48) -> 0 | M48: =K48-L48 -> 0 | N48: =K26+N26+K37+N37+K48 -> 0 | O48: =L26+O26+L37+O37+L48 -> 0 | P48: =N48-O48 -> 0
J49: ALL | K49: =SUM(K42:K48) -> 0 | L49: =SUM(L42:L48) -> 0 | M49: =K49-L49 -> 0 | N49: =SUM(N42:N48) -> 0 | O49: =SUM(O42:O48) -> 0 | P49: =N49-O49 -> 0

Sheet 11月
B1: 11 | D1: ← 年・月を変更するとカレンダーが自動更新されます | J1: ※グレーのセルは自動反映します（入力不要）
B2: 2025 | J2: =DATE(B2,B1,1) -> 45962 | R2: 変動費 明細
B4: 収入 | F4: 先取り貯金・投資 | J4: 月 | K4: 火 | L4: 水 | M4: 木 | N4: 金 | O4: 土 | P4: 日 | R4: 日付 | S4: 週 | T4: 支払方法 | U4: 費目 | V4: 詳細 | X4: 金額 | Y4: 満足度
B5: 費目 | C5: 入金口座 | D5: 金額 | F5: 費目 | G5: 支払方法 | H5: 金額 | J5: =$J$2-weekday($J$2)+2 -> 45957 | K5: =J5+1 -> 45958 | L5: =K5+1 -> 45959 | M5: =L5+1 -> 45960 | N5: =M5+1 -> 45961 | O5: =N5+1 -> 45962 | P5: =O5+1 -> 45963 | R5: 45962
J6: =sumifs($X:$X,$R:$R,J5) -> 0 | K6: =sumifs($X:$X,$R:$R,K5) -> 0 | L6: =sumifs($X:$X,$R:$R,L5) -> 0 | M6: =sumifs($X:$X,$R:$R,M5) -> 0 | N6: =sumifs($X:$X,$R:$R,N5) -> 0 | O6: =sumifs($X:$X,$R:$R,O5) -> 0 | P6: =sumifs($X:$X,$R:$R,P5) -> 0
J7: =J5+7 -> 45964 | K7: =K5+7 -> 45965 | L7: =L5+7 -> 45966 | M7: =M5+7 -> 45967 | N7: =N5+7 -> 45968 | O7: =O5+7 -> 45969 | P7: =P5+7 -> 45970
J8: =sumifs($X:$X,$R:$R,J7) -> 0 | K8: =sumifs($X:$X,$R:$R,K7) -> 0 | L8: =sumifs($X:$X,$R:$R,L7) -> 0 | M8: =sumifs($X:$X,$R:$R,M7) -> 0 | N8: =sumifs($X:$X,$R:$R,N7) -> 0 | O8: =sumifs($X:$X,$R:$R,O7) -> 0 | P8: =sumifs($X:$X,$R:$R,P7) -> 0
J9: =J7+7 -> 45971 | K9: =K7+7 -> 45972 | L9: =L7+7 -> 45973 | M9: =M7+7 -> 45974 | N9: =N7+7 -> 45975 | O9: =O7+7 -> 45976 | P9: =P7+7 -> 45977
J10: =sumifs($X:$X,$R:$R,J9) -> 0 | K10: =sumifs($X:$X,$R:$R,K9) -> 0 | L10: =sumifs($X:$X,$R:$R,L9) -> 0 | M10: =sumifs($X:$X,$R:$R,M9) -> 0 | N10: =sumifs($X:$X,$R:$R,N9) -> 0 | O10: =sumifs($X:$X,$R:$R,O9) -> 0 | P10: =sumifs($X:$X,$R:$R,P9) -> 0
J11: =J9+7 -> 45978 | K11: =K9+7 -> 45979 | L11: =L9+7 -> 45980 | M11: =M9+7 -> 45981 | N11: =N9+7 -> 45982 | O11: =O9+7 -> 45983 | P11: =P9+7 -> 45984
J12: =sumifs($X:$X,$R:$R,J11) -> 0 | K12: =sumifs($X:$X,$R:$R,K11) -> 0 | L12: =sumifs($X:$X,$R:$R,L11) -> 0 | M12: =sumifs($X:$X,$R:$R,M11) -> 0 | N12: =sumifs($X:$X,$R:$R,N11) -> 0 | O12: =sumifs($X:$X,$R:$R,O11) -> 0 | P12: =sumifs($X:$X,$R:$R,P11) -> 0
J13: =J11+7 -> 45985 | K13: =K11+7 -> 45986 | L13: =L11+7 -> 45987 | M13: =M11+7 -> 45988 | N13: =N11+7 -> 45989 | O13: =O11+7 -> 45990 | P13: =P11+7 -> 45991
B14: 合計 | D14: =SUM(D6:D13) -> 0 | F14: 合計 | H14: =SUM(H6:H13) -> 0 | J14: =sumifs($X:$X,$R:$R,J13) -> 0 | K14: =sumifs($X:$X,$R:$R,K13) -> 0 | L14: =sumifs($X:$X,$R:$R,L13) -> 0 | M14: =sumifs($X:$X,$R:$R,M13) -> 0 | N14: =sumifs($X:$X,$R:$R,N13) -> 0 | O14: =sumifs($X:$X,$R:$R,O13) -> 0 | P14: =sumifs($X:$X,$R:$R,P13) -> 0
B16: 支出 | F16: 支出 | J16: 週予算 管理
B17: 固定費 | F17: 変動費
B18: 費目 | C18: 支払方法 | D18: 金額 | F18: 費目 | G18: 予算 | H18: 金額 | J18: 項目 | L18: 1week | O18: 2week
H19: =sumifs($X:$X,$U:$U,F19) -> 0 | K19: 予算 | L19: 金額 | M19: 差分 | N19: 予算 | O19: 金額 | P19: 差分
H20: =sumifs($X:$X,$U:$U,F20) -> 0 | L20: =sumifs($X:$X,$S:$S,$L$18,$U:$U,J20) -> 0 | M20: =K20-L20 -> 0 | O20: =sumifs($X:$X,$S:$S,$O$18,$U:$U,J20) -> 0 | P20: =N20-O20 -> 0
H21: =sumifs($X:$X,$U:$U,F21) -> 0 | L21: =sumifs($X:$X,$S:$S,$L$18,$U:$U,J21) -> 0 | M21: =K21-L21 -> 0 | O21: =sumifs($X:$X,$S:$S,$O$18,$U:$U,J21) -> 0 | P21: =N21-O21 -> 0
H22: =sumifs($X:$X,$U:$U,F22) -> 0 | L22: =sumifs($X:$X,$S:$S,$L$18,$U:$U,J22) -> 0 | M22: =K22-L22 -> 0 | O22: =sumifs($X:$X,$S:$S,$O$18,$U:$U,J22) -> 0 | P22: =N22-O22 -> 0
H23: =sumifs($X:$X,$U:$U,F23) -> 0 | L23: =sumifs($X:$X,$S:$S,$L$18,$U:$U,J23) -> 0 | M23: =K23-L23 -> 0 | O23: =sumifs($X:$X,$S:$S,$O$18,$U:$U,J23) -> 0 | P23: =N23-O23 -> 0
H24: =sumifs($X:$X,$U:$U,F24) -> 0 | L24: =sumifs($X:$X,$S:$S,$L$18,$U:$U,J24) -> 0 | M24: =K24-L24 -> 0 | O24: =sumifs($X:$X,$S:$S,$O$18,$U:$U,J24) -> 0 | P24: =N24-O24 -> 0
H25: =sumifs($X:$X,$U:$U,F25) -> 0 | L25: =sumifs($X:$X,$S:$S,$L$18,$U:$U,J25) -> 0 | M25: =K25-L25 -> 0 | O25: =sumifs($X:$X,$S:$S,$O$18,$U:$U,J25) -> 0 | P25: =N25-O25 -> 0
H26: =sumifs($X:$X,$U:$U,F26) -> 0 | L26: =sumifs($X:$X,$S:$S,$L$18,$U:$U,J26) -> 0 | M26: =K26-L26 -> 0 | O26: =sumifs($X:$X,$S:$S,$O$18,$U:$U,J26) -> 0 | P26: =N26-O26 -> 0
H27: =sumifs($X:$X,$U:$U,F27) -> 0 | J27: ALL | K27: =SUM(K20:K26) -> 0 | L27: =SUM(L20:L26) -> 0 | M27: =K27-L27 -> 0 | N27: =SUM(N20:N26) -> 0 | O27: =SUM(O20:O26) -> 0 | P27: =N27-O27 -> 0
H28: =sumifs($X:$X,$U:$U,F28) -> 0
H29: =sumifs($X:$X,$U:$U,F29) -> 0 | J29: 項目 | L29: 3week | O29: 4week
H30: =sumifs($X:$X,$U:$U,F30) -> 0 | K30: 予算 | L30: 金額 | M30: 差分 | N30: 予算 | O30: 金額 | P30: 差分
B31: 合計 | D31: =SUM(D19:D30) -> 0 | F31: 合計 | G31: =SUM(G19:G30) -> 0 | H31: =SUM(H19:H30) -> 0 | L31: =sumifs($X:$X,$S:$S,$L$29,$U:$U,J31) -> 0 | M31: =K31-L31 -> 0 | O31: =sumifs($X:$X,$S:$S,$O$29,$U:$U,J31) -> 0 | P31: =N31-O31 -> 0
L32: =sumifs($X:$X,$S:$S,$L$29,$U:$U,J32) -> 0 | M32: =K32-L32 -> 0 | O32: =sumifs($X:$X,$S:$S,$O$29,$U:$U,J32) -> 0 | P32: =N32-O32 -> 0
B33: 特別費 | F33: 今月の収支 | H33: 金額 | L33: =sumifs($X:$X,$S:$S,$L$29,$U:$U,J33) -> 0 | M33: =K33-L33 -> 0 | O33: =sumifs($X:$X,$S:$S,$O$29,$U:$U,J33) -> 0 | P33: =N33-O33 -> 0
B34: 費目 | C34: 支払方法 | D34: 金額 | F34: 収入（a） | H34: =D14 -> 0 | L34: =sumifs($X:$X,$S:$S,$L$29,$U:$U,J34) -> 0 | M34: =K34-L34 -> 0 | O34: =sumifs($X:$X,$S:$S,$O$29,$U:$U,J34) -> 0 | P34: =N34-O34 -> 0
F35: 先取り貯金・投資（b） | H35: =H14 -> 0 | L35: =sumifs($X:$X,$S:$S,$L$29,$U:$U,J35) -> 0 | M35: =K35-L35 -> 0 | O35: =sumifs($X:$X,$S:$S,$O$29,$U:$U,J35) -> 0 | P35: =N35-O35 -> 0
F36: 支出（c） | H36: =D31+H31 -> 0 | L36: =sumifs($X:$X,$S:$S,$L$29,$U:$U,J36) -> 0 | M36: =K36-L36 -> 0 | O36: =sumifs($X:$X,$S:$S,$O$29,$U:$U,J36) -> 0 | P36: =N36-O36 -> 0
F37: 余り貯金（d）※a-b-c | H37: =H34-H35-H36 -> 0 | L37: =sumifs($X:$X,$S:$S,$L$29,$U:$U,J37) -> 0 | M37: =K37-L37 -> 0 | O37: =sumifs($X:$X,$S:$S,$O$29,$U:$U,J37) -> 0 | P37: =N37-O37 -> 0
F38: 貯蓄合計（e）※b+d | H38: =H35+H37 -> 0 | J38: ALL | K38: =SUM(K31:K37) -> 0 | L38: =SUM(L31:L37) -> 0 | M38: =K38-L38 -> 0 | N38: =SUM(N31:N37) -> 0 | O38: =SUM(O31:O37) -> 0 | P38: =N38-O38 -> 0
F40: 支出率（c/a)×100 | G40: 貯蓄率 （e/a)×100 | J40: 項目 | L40: 5week | O40: ALL
F41: =H36/H34 -> #DIV/0! | G41: =H38/H34 -> #DIV/0! | K41: 予算 | L41: 金額 | M41: 差分 | N41: 予算 | O41: 金額 | P41: 差分
B42: 合計 | D42: =SUM(D35:D41) -> 0 | L42: =sumifs($X:$X,$S:$S,$L$40,$U:$U,J42) -> 0 | M42: =K42-L42 -> 0 | N42: =K20+N20+K31+N31+K42 -> 0 | O42: =L20+O20+L31+O31+L42 -> 0 | P42: =N42-O42 -> 0
D43: ※収支の計算外 | F43: ※目標：80%以下 | H43: ※目標：20%以上 | L43: =sumifs($X:$X,$S:$S,$L$40,$U:$U,J43) -> 0 | M43: =K43-L43 -> 0 | N43: =K21+N21+K32+N32+K43 -> 0 | O43: =L21+O21+L32+O32+L43 -> 0 | P43: =N43-O43 -> 0
B44: 振り返り | L44: =sumifs($X:$X,$S:$S,$L$40,$U:$U,J44) -> 0 | M44: =K44-L44 -> 0 | N44: =K22+N22+K33+N33+K44 -> 0 | O44: =L22+O22+L33+O33+L44 -> 0 | P44: =N44-O44 -> 0
L45: =sumifs($X:$X,$S:$S,$L$40,$U:$U,J45) -> 0 | M45: =K45-L45 -> 0 | N45: =K23+N23+K34+N34+K45 -> 0 | O45: =L23+O23+L34+O34+L45 -> 0 | P45: =N45-O45 -> 0
L46: =sumifs($X:$X,$S:$S,$L$40,$U:$U,J46) -> 0 | M46: =K46-L46 -> 0 | N46: =K24+N24+K35+N35+K46 -> 0 | O46: =L24+O24+L35+O35+L46 -> 0 | P46: =N46-O46 -> 0
L47: =sumifs($X:$X,$S:$S,$L$40,$U:$U,J47) -> 0 | M47: =K47-L47 -> 0 | N47: =K25+N25+K36+N36+K47 -> 0 | O47: =L25+O25+L36+O36+L47 -> 0 | P47: =N47-O47 -> 0
L48: =sumifs($X:$X,$S:$S,$L$40,$U:$U,J48) -> 0 | M48: =K48-L48 -> 0 | N48: =K26+N26+K37+N37+K48 -> 0 | O48: =L26+O26+L37+O37+L48 -> 0 | P48: =N48-O48 -> 0
J49: ALL | K49: =SUM(K42:K48) -> 0 | L49: =SUM(L42:L48) -> 0 | M49: =K49-L49 -> 0 | N49: =SUM(N42:N48) -> 0 | O49: =SUM(O42:O48) -> 0 | P49: =N49-O49 -> 0

Sheet 12月
B1: 12 | D1: ← 年・月を変更するとカレンダーが自動更新されます | J1: ※グレーのセルは自動反映します（入力不要）
B2: 2025 | J2: =DATE(B2,B1,1) -> 45992 | R2: 変動費 明細
B4: 収入 | F4: 先取り貯金・投資 | J4: 月 | K4: 火 | L4: 水 | M4: 木 | N4: 金 | O4: 土 | P4: 日 | R4: 日付 | S4: 週 | T4: 支払方法 | U4: 費目 | V4: 詳細 | X4: 金額 | Y4: 満足度
B5: 費目 | C5: 入金口座 | D5: 金額 | F5: 費目 | G5: 支払方法 | H5: 金額 | J5: =$J$2-weekday($J$2)+2 -> 45992 | K5: =J5+1 -> 45993 | L5: =K5+1 -> 45994 | M5: =L5+1 -> 45995 | N5: =M5+1 -> 45996 | O5: =N5+1 -> 45997 | P5: =O5+1 -> 45998 | R5: 45992
J6: =sumifs($X:$X,$R:$R,J5) -> 0 | K6: =sumifs($X:$X,$R:$R,K5) -> 0 | L6: =sumifs($X:$X,$R:$R,L5) -> 0 | M6: =sumifs($X:$X,$R:$R,M5) -> 0 | N6: =sumifs($X:$X,$R:$R,N5) -> 0 | O6: =sumifs($X:$X,$R:$R,O5) -> 0 | P6: =sumifs($X:$X,$R:$R,P5) -> 0
J7: =J5+7 -> 45999 | K7: =K5+7 -> 46000 | L7: =L5+7 -> 46001 | M7: =M5+7 -> 46002 | N7: =N5+7 -> 46003 | O7: =O5+7 -> 46004 | P7: =P5+7 -> 46005
J8: =sumifs($X:$X,$R:$R,J7) -> 0 | K8: =sumifs($X:$X,$R:$R,K7) -> 0 | L8: =sumifs($X:$X,$R:$R,L7) -> 0 | M8: =sumifs($X:$X,$R:$R,M7) -> 0 | N8: =sumifs($X:$X,$R:$R,N7) -> 0 | O8: =sumifs($X:$X,$R:$R,O7) -> 0 | P8: =sumifs($X:$X,$R:$R,P7) -> 0
J9: =J7+7 -> 46006 | K9: =K7+7 -> 46007 | L9: =L7+7 -> 46008 | M9: =M7+7 -> 46009 | N9: =N7+7 -> 46010 | O9: =O7+7 -> 46011 | P9: =P7+7 -> 46012
J10: =sumifs($X:$X,$R:$R,J9) -> 0 | K10: =sumifs($X:$X,$R:$R,K9) -> 0 | L10: =sumifs($X:$X,$R:$R,L9) -> 0 | M10: =sumifs($X:$X,$R:$R,M9) -> 0 | N10: =sumifs($X:$X,$R:$R,N9) -> 0 | O10: =sumifs($X:$X,$R:$R,O9) -> 0 | P10: =sumifs($X:$X,$R:$R,P9) -> 0
J11: =J9+7 -> 46013 | K11: =K9+7 -> 46014 | L11: =L9+7 -> 46015 | M11: =M9+7 -> 46016 | N11: =N9+7 -> 46017 | O11: =O9+7 -> 46018 | P11: =P9+7 -> 46019
J12: =sumifs($X:$X,$R:$R,J11) -> 0 | K12: =sumifs($X:$X,$R:$R,K11) -> 0 | L12: =sumifs($X:$X,$R:$R,L11) -> 0 | M12: =sumifs($X:$X,$R:$R,M11) -> 0 | N12: =sumifs($X:$X,$R:$R,N11) -> 0 | O12: =sumifs($X:$X,$R:$R,O11) -> 0 | P12: =sumifs($X:$X,$R:$R,P11) -> 0
J13: =J11+7 -> 46020 | K13: =K11+7 -> 46021 | L13: =L11+7 -> 46022 | M13: =M11+7 -> 46023 | N13: =N11+7 -> 46024 | O13: =O11+7 -> 46025 | P13: =P11+7 -> 46026
B14: 合計 | D14: =SUM(D6:D13) -> 0 | F14: 合計 | H14: =SUM(H6:H13) -> 0 | J14: =sumifs($X:$X,$R:$R,J13) -> 0 | K14: =sumifs($X:$X,$R:$R,K13) -> 0 | L14: =sumifs($X:$X,$R:$R,L13) -> 0 | M14: =sumifs($X:$X,$R:$R,M13) -> 0 | N14: =sumifs($X:$X,$R:$R,N13) -> 0 | O14: =sumifs($X:$X,$R:$R,O13) -> 0 | P14: =sumifs($X:$X,$R:$R,P13) -> 0
B16: 支出 | F16: 支出 | J16: 週予算 管理
B17: 固定費 | F17: 変動費
B18: 費目 | C18: 支払方法 | D18: 金額 | F18: 費目 | G18: 予算 | H18: 金額 | J18: 項目 | L18: 1week | O18: 2week
H19: =sumifs($X:$X,$U:$U,F19) -> 0 | K19: 予算 | L19: 金額 | M19: 差分 | N19: 予算 | O19: 金額 | P19: 差分
H20: =sumifs($X:$X,$U:$U,F20) -> 0 | L20: =sumifs($X:$X,$S:$S,$L$18,$U:$U,J20) -> 0 | M20: =K20-L20 -> 0 | O20: =sumifs($X:$X,$S:$S,$O$18,$U:$U,J20) -> 0 | P20: =N20-O20 -> 0
H21: =sumifs($X:$X,$U:$U,F21) -> 0 | L21: =sumifs($X:$X,$S:$S,$L$18,$U:$U,J21) -> 0 | M21: =K21-L21 -> 0 | O21: =sumifs($X:$X,$S:$S,$O$18,$U:$U,J21) -> 0 | P21: =N21-O21 -> 0
H22: =sumifs($X:$X,$U:$U,F22) -> 0 | L22: =sumifs($X:$X,$S:$S,$L$18,$U:$U,J22) -> 0 | M22: =K22-L22 -> 0 | O22: =sumifs($X:$X,$S:$S,$O$18,$U:$U,J22) -> 0 | P22: =N22-O22 -> 0
H23: =sumifs($X:$X,$U:$U,F23) -> 0 | L23: =sumifs($X:$X,$S:$S,$L$18,$U:$U,J23) -> 0 | M23: =K23-L23 -> 0 | O23: =sumifs($X:$X,$S:$S,$O$18,$U:$U,J23) -> 0 | P23: =N23-O23 -> 0
H24: =sumifs($X:$X,$U:$U,F24) -> 0 | L24: =sumifs($X:$X,$S:$S,$L$18,$U:$U,J24) -> 0 | M24: =K24-L24 -> 0 | O24: =sumifs($X:$X,$S:$S,$O$18,$U:$U,J24) -> 0 | P24: =N24-O24 -> 0
H25: =sumifs($X:$X,$U:$U,F25) -> 0 | L25: =sumifs($X:$X,$S:$S,$L$18,$U:$U,J25) -> 0 | M25: =K25-L25 -> 0 | O25: =sumifs($X:$X,$S:$S,$O$18,$U:$U,J25) -> 0 | P25: =N25-O25 -> 0
H26: =sumifs($X:$X,$U:$U,F26) -> 0 | L26: =sumifs($X:$X,$S:$S,$L$18,$U:$U,J26) -> 0 | M26: =K26-L26 -> 0 | O26: =sumifs($X:$X,$S:$S,$O$18,$U:$U,J26) -> 0 | P26: =N26-O26 -> 0
H27: =sumifs($X:$X,$U:$U,F27) -> 0 | J27: ALL | K27: =SUM(K20:K26) -> 0 | L27: =SUM(L20:L26) -> 0 | M27: =K27-L27 -> 0 | N27: =SUM(N20:N26) -> 0 | O27: =SUM(O20:O26) -> 0 | P27: =N27-O27 -> 0
H28: =sumifs($X:$X,$U:$U,F28) -> 0
H29: =sumifs($X:$X,$U:$U,F29) -> 0 | J29: 項目 | L29: 3week | O29: 4week
H30: =sumifs($X:$X,$U:$U,F30) -> 0 | K30: 予算 | L30: 金額 | M30: 差分 | N30: 予算 | O30: 金額 | P30: 差分
B31: 合計 | D31: =SUM(D19:D30) -> 0 | F31: 合計 | G31: =SUM(G19:G30) -> 0 | H31: =SUM(H19:H30) -> 0 | L31: =sumifs($X:$X,$S:$S,$L$29,$U:$U,J31) -> 0 | M31: =K31-L31 -> 0 | O31: =sumifs($X:$X,$S:$S,$O$29,$U:$U,J31) -> 0 | P31: =N31-O31 -> 0
L32: =sumifs($X:$X,$S:$S,$L$29,$U:$U,J32) -> 0 | M32: =K32-L32 -> 0 | O32: =sumifs($X:$X,$S:$S,$O$29,$U:$U,J32) -> 0 | P32: =N32-O32 -> 0
B33: 特別費 | F33: 今月の収支 | H33: 金額 | L33: =sumifs($X:$X,$S:$S,$L$29,$U:$U,J33) -> 0 | M33: =K33-L33 -> 0 | O33: =sumifs($X:$X,$S:$S,$O$29,$U:$U,J33) -> 0 | P33: =N33-O33 -> 0
B34: 費目 | C34: 支払方法 | D34: 金額 | F34: 収入（a） | H34: =D14 -> 0 | L34: =sumifs($X:$X,$S:$S,$L$29,$U:$U,J34) -> 0 | M34: =K34-L34 -> 0 | O34: =sumifs($X:$X,$S:$S,$O$29,$U:$U,J34) -> 0 | P34: =N34-O34 -> 0
F35: 先取り貯金・投資（b） | H35: =H14 -> 0 | L35: =sumifs($X:$X,$S:$S,$L$29,$U:$U,J35) -> 0 | M35: =K35-L35 -> 0 | O35: =sumifs($X:$X,$S:$S,$O$29,$U:$U,J35) -> 0 | P35: =N35-O35 -> 0
F36: 支出（c） | H36: =D31+H31 -> 0 | L36: =sumifs($X:$X,$S:$S,$L$29,$U:$U,J36) -> 0 | M36: =K36-L36 -> 0 | O36: =sumifs($X:$X,$S:$S,$O$29,$U:$U,J36) -> 0 | P36: =N36-O36 -> 0
F37: 余り貯金（d）※a-b-c | H37: =H34-H35-H36 -> 0 | L37: =sumifs($X:$X,$S:$S,$L$29,$U:$U,J37) -> 0 | M37: =K37-L37 -> 0 | O37: =sumifs($X:$X,$S:$S,$O$29,$U:$U,J37) -> 0 | P37: =N37-O37 -> 0
F38: 貯蓄合計（e）※b+d | H38: =H35+H37 -> 0 | J38: ALL | K38: =SUM(K31:K37) -> 0 | L38: =SUM(L31:L37) -> 0 | M38: =K38-L38 -> 0 | N38: =SUM(N31:N37) -> 0 | O38: =SUM(O31:O37) -> 0 | P38: =N38-O38 -> 0
F40: 支出率（c/a)×100 | G40: 貯蓄率 （e/a)×100 | J40: 項目 | L40: 5week | O40: ALL
F41: =H36/H34 -> #DIV/0! | G41: =H38/H34 -> #DIV/0! | K41: 予算 | L41: 金額 | M41: 差分 | N41: 予算 | O41: 金額 | P41: 差分
B42: 合計 | D42: =SUM(D35:D41) -> 0 | L42: =sumifs($X:$X,$S:$S,$L$40,$U:$U,J42) -> 0 | M42: =K42-L42 -> 0 | N42: =K20+N20+K31+N31+K42 -> 0 | O42: =L20+O20+L31+O31+L42 -> 0 | P42: =N42-O42 -> 0
D43: ※収支の計算外 | F43: ※目標：80%以下 | H43: ※目標：20%以上 | L43: =sumifs($X:$X,$S:$S,$L$40,$U:$U,J43) -> 0 | M43: =K43-L43 -> 0 | N43: =K21+N21+K32+N32+K43 -> 0 | O43: =L21+O21+L32+O32+L43 -> 0 | P43: =N43-O43 -> 0
B44: 振り返り | L44: =sumifs($X:$X,$S:$S,$L$40,$U:$U,J44) -> 0 | M44: =K44-L44 -> 0 | N44: =K22+N22+K33+N33+K44 -> 0 | O44: =L22+O22+L33+O33+L44 -> 0 | P44: =N44-O44 -> 0
L45: =sumifs($X:$X,$S:$S,$L$40,$U:$U,J45) -> 0 | M45: =K45-L45 -> 0 | N45: =K23+N23+K34+N34+K45 -> 0 | O45: =L23+O23+L34+O34+L45 -> 0 | P45: =N45-O45 -> 0
L46: =sumifs($X:$X,$S:$S,$L$40,$U:$U,J46) -> 0 | M46: =K46-L46 -> 0 | N46: =K24+N24+K35+N35+K46 -> 0 | O46: =L24+O24+L35+O35+L46 -> 0 | P46: =N46-O46 -> 0
L47: =sumifs($X:$X,$S:$S,$L$40,$U:$U,J47) -> 0 | M47: =K47-L47 -> 0 | N47: =K25+N25+K36+N36+K47 -> 0 | O47: =L25+O25+L36+O36+L47 -> 0 | P47: =N47-O47 -> 0
L48: =sumifs($X:$X,$S:$S,$L$40,$U:$U,J48) -> 0 | M48: =K48-L48 -> 0 | N48: =K26+N26+K37+N37+K48 -> 0 | O48: =L26+O26+L37+O37+L48 -> 0 | P48: =N48-O48 -> 0
J49: ALL | K49: =SUM(K42:K48) -> 0 | L49: =SUM(L42:L48) -> 0 | M49: =K49-L49 -> 0 | N49: =SUM(N42:N48) -> 0 | O49: =SUM(O42:O48) -> 0 | P49: =N49-O49 -> 0

Sheet 年間推移シート
A1: 年間推移シート | D1: ※費目を選択すれば自動で反映されます
A3: 2025年 | C3: 費目 | D3: Memo | E3: 1月 | F3: 2月 | G3: 3月 | H3: 4月 | I3: 5月 | J3: 6月 | K3: 7月 | L3: 8月 | M3: 9月 | N3: 10月 | O3: 11月 | P3: 12月 | Q3: 平均 | R3: 年間合計 | T3: {={"年間合計";ByRow(E13:P63, Lambda(row, Sum(row)))}} -> 年間合計
A4: 収入 | C4: 💰 パパ給与 | E4: =SUMIF('1月'!$B$6:$B$13,$C4,'1月'!$D$6:$D$13) -> 250000 | F4: =SUMIF('2月'!$B$6:$B$13,$C4,'2月'!$D$6:$D$13) -> 0 | G4: =SUMIF('3月'!$B$6:$B$13,$C4,'3月'!$D$6:$D$13) -> 0 | H4: =SUMIF('4月'!$B$6:$B$13,$C4,'4月'!$D$6:$D$13) -> 0 | I4: =SUMIF('5月'!$B$6:$B$13,$C4,'5月'!$D$6:$D$13) -> 0 | J4: =SUMIF('6月'!$B$6:$B$13,$C4,'6月'!$D$6:$D$13) -> 0 | K4: =SUMIF('7月'!$B$6:$B$13,$C4,'7月'!$D$6:$D$13) -> 0 | L4: =SUMIF('8月'!$B$6:$B$13,$C4,'8月'!$D$6:$D$13) -> 0 | M4: =SUMIF('9月'!$B$6:$B$13,$C4,'9月'!$D$6:$D$13) -> 0 | N4: =SUMIF('10月'!$B$6:$B$13,$C4,'10月'!$D$6:$D$13) -> 0 | O4: =SUMIF('11月'!$B$6:$B$13,$C4,'11月'!$D$6:$D$13) -> 0 | P4: =SUMIF('12月'!$B$6:$B$13,$C4,'12月'!$D$6:$D$13) -> 0 | Q4: =AVERAGE(E4:P4) -> 20833.333 | R4: =SUM(E4:P4) -> 250000 | T4: 100000
C5: 💰 ママ給与 | E5: =SUMIF('1月'!$B$6:$B$13,$C5,'1月'!$D$6:$D$13) -> 150000 | F5: =SUMIF('2月'!$B$6:$B$13,$C5,'2月'!$D$6:$D$13) -> 0 | G5: =SUMIF('3月'!$B$6:$B$13,$C5,'3月'!$D$6:$D$13) -> 0 | H5: =SUMIF('4月'!$B$6:$B$13,$C5,'4月'!$D$6:$D$13) -> 0 | I5: =SUMIF('5月'!$B$6:$B$13,$C5,'5月'!$D$6:$D$13) -> 0 | J5: =SUMIF('6月'!$B$6:$B$13,$C5,'6月'!$D$6:$D$13) -> 0 | K5: =SUMIF('7月'!$B$6:$B$13,$C5,'7月'!$D$6:$D$13) -> 0 | L5: =SUMIF('8月'!$B$6:$B$13,$C5,'8月'!$D$6:$D$13) -> 0 | M5: =SUMIF('9月'!$B$6:$B$13,$C5,'9月'!$D$6:$D$13) -> 0 | N5: =SUMIF('10月'!$B$6:$B$13,$C5,'10月'!$D$6:$D$13) -> 0 | O5: =SUMIF('11月'!$B$6:$B$13,$C5,'11月'!$D$6:$D$13) -> 0 | P5: =SUMIF('12月'!$B$6:$B$13,$C5,'12月'!$D$6:$D$13) -> 0 | Q5: =AVERAGE(E5:P5) -> 12500 | R5: =SUM(E5:P5) -> 150000 | T5: 8000
C6: 💰 配当金 | E6: =SUMIF('1月'!$B$6:$B$13,$C6,'1月'!$D$6:$D$13) -> 0 | F6: =SUMIF('2月'!$B$6:$B$13,$C6,'2月'!$D$6:$D$13) -> 0 | G6: =SUMIF('3月'!$B$6:$B$13,$C6,'3月'!$D$6:$D$13) -> 0 | H6: =SUMIF('4月'!$B$6:$B$13,$C6,'4月'!$D$6:$D$13) -> 0 | I6: =SUMIF('5月'!$B$6:$B$13,$C6,'5月'!$D$6:$D$13) -> 0 | J6: =SUMIF('6月'!$B$6:$B$13,$C6,'6月'!$D$6:$D$13) -> 0 | K6: =SUMIF('7月'!$B$6:$B$13,$C6,'7月'!$D$6:$D$13) -> 0 | L6: =SUMIF('8月'!$B$6:$B$13,$C6,'8月'!$D$6:$D$13) -> 0 | M6: =SUMIF('9月'!$B$6:$B$13,$C6,'9月'!$D$6:$D$13) -> 0 | N6: =SUMIF('10月'!$B$6:$B$13,$C6,'10月'!$D$6:$D$13) -> 0 | O6: =SUMIF('11月'!$B$6:$B$13,$C6,'11月'!$D$6:$D$13) -> 0 | P6: =SUMIF('12月'!$B$6:$B$13,$C6,'12月'!$D$6:$D$13) -> 0 | Q6: =AVERAGE(E6:P6) -> 0 | R6: =SUM(E6:P6) -> 0 | T6: 5000
C7: 💰 賞与 | E7: =SUMIF('1月'!$B$6:$B$13,$C7,'1月'!$D$6:$D$13) -> 0 | F7: =SUMIF('2月'!$B$6:$B$13,$C7,'2月'!$D$6:$D$13) -> 0 | G7: =SUMIF('3月'!$B$6:$B$13,$C7,'3月'!$D$6:$D$13) -> 0 | H7: =SUMIF('4月'!$B$6:$B$13,$C7,'4月'!$D$6:$D$13) -> 0 | I7: =SUMIF('5月'!$B$6:$B$13,$C7,'5月'!$D$6:$D$13) -> 0 | J7: =SUMIF('6月'!$B$6:$B$13,$C7,'6月'!$D$6:$D$13) -> 0 | K7: =SUMIF('7月'!$B$6:$B$13,$C7,'7月'!$D$6:$D$13) -> 0 | L7: =SUMIF('8月'!$B$6:$B$13,$C7,'8月'!$D$6:$D$13) -> 0 | M7: =SUMIF('9月'!$B$6:$B$13,$C7,'9月'!$D$6:$D$13) -> 0 | N7: =SUMIF('10月'!$B$6:$B$13,$C7,'10月'!$D$6:$D$13) -> 0 | O7: =SUMIF('11月'!$B$6:$B$13,$C7,'11月'!$D$6:$D$13) -> 0 | P7: =SUMIF('12月'!$B$6:$B$13,$C7,'12月'!$D$6:$D$13) -> 0 | Q7: =AVERAGE(E7:P7) -> 0 | R7: =SUM(E7:P7) -> 0 | T7: 2000
C8: 💰 児童手当 | E8: =SUMIF('1月'!$B$6:$B$13,$C8,'1月'!$D$6:$D$13) -> 0 | F8: =SUMIF('2月'!$B$6:$B$13,$C8,'2月'!$D$6:$D$13) -> 0 | G8: =SUMIF('3月'!$B$6:$B$13,$C8,'3月'!$D$6:$D$13) -> 0 | H8: =SUMIF('4月'!$B$6:$B$13,$C8,'4月'!$D$6:$D$13) -> 0 | I8: =SUMIF('5月'!$B$6:$B$13,$C8,'5月'!$D$6:$D$13) -> 0 | J8: =SUMIF('6月'!$B$6:$B$13,$C8,'6月'!$D$6:$D$13) -> 0 | K8: =SUMIF('7月'!$B$6:$B$13,$C8,'7月'!$D$6:$D$13) -> 0 | L8: =SUMIF('8月'!$B$6:$B$13,$C8,'8月'!$D$6:$D$13) -> 0 | M8: =SUMIF('9月'!$B$6:$B$13,$C8,'9月'!$D$6:$D$13) -> 0 | N8: =SUMIF('10月'!$B$6:$B$13,$C8,'10月'!$D$6:$D$13) -> 0 | O8: =SUMIF('11月'!$B$6:$B$13,$C8,'11月'!$D$6:$D$13) -> 0 | P8: =SUMIF('12月'!$B$6:$B$13,$C8,'12月'!$D$6:$D$13) -> 0 | Q8: =AVERAGE(E8:P8) -> 0 | R8: =SUM(E8:P8) -> 0 | T8: 30000
C9: 💰 副業 | E9: =SUMIF('1月'!$B$6:$B$13,$C9,'1月'!$D$6:$D$13) -> 0 | F9: =SUMIF('2月'!$B$6:$B$13,$C9,'2月'!$D$6:$D$13) -> 0 | G9: =SUMIF('3月'!$B$6:$B$13,$C9,'3月'!$D$6:$D$13) -> 0 | H9: =SUMIF('4月'!$B$6:$B$13,$C9,'4月'!$D$6:$D$13) -> 0 | I9: =SUMIF('5月'!$B$6:$B$13,$C9,'5月'!$D$6:$D$13) -> 0 | J9: =SUMIF('6月'!$B$6:$B$13,$C9,'6月'!$D$6:$D$13) -> 0 | K9: =SUMIF('7月'!$B$6:$B$13,$C9,'7月'!$D$6:$D$13) -> 0 | L9: =SUMIF('8月'!$B$6:$B$13,$C9,'8月'!$D$6:$D$13) -> 0 | M9: =SUMIF('9月'!$B$6:$B$13,$C9,'9月'!$D$6:$D$13) -> 0 | N9: =SUMIF('10月'!$B$6:$B$13,$C9,'10月'!$D$6:$D$13) -> 0 | O9: =SUMIF('11月'!$B$6:$B$13,$C9,'11月'!$D$6:$D$13) -> 0 | P9: =SUMIF('12月'!$B$6:$B$13,$C9,'12月'!$D$6:$D$13) -> 0 | Q9: =AVERAGE(E9:P9) -> 0 | R9: =SUM(E9:P9) -> 0 | T9: 5000
E10: =SUMIF('1月'!$B$6:$B$13,$C10,'1月'!$D$6:$D$13) -> 0 | F10: =SUMIF('2月'!$B$6:$B$13,$C10,'2月'!$D$6:$D$13) -> 0 | G10: =SUMIF('3月'!$B$6:$B$13,$C10,'3月'!$D$6:$D$13) -> 0 | H10: =SUMIF('4月'!$B$6:$B$13,$C10,'4月'!$D$6:$D$13) -> 0 | I10: =SUMIF('5月'!$B$6:$B$13,$C10,'5月'!$D$6:$D$13) -> 0 | J10: =SUMIF('6月'!$B$6:$B$13,$C10,'6月'!$D$6:$D$13) -> 0 | K10: =SUMIF('7月'!$B$6:$B$13,$C10,'7月'!$D$6:$D$13) -> 0 | L10: =SUMIF('8月'!$B$6:$B$13,$C10,'8月'!$D$6:$D$13) -> 0 | M10: =SUMIF('9月'!$B$6:$B$13,$C10,'9月'!$D$6:$D$13) -> 0 | N10: =SUMIF('10月'!$B$6:$B$13,$C10,'10月'!$D$6:$D$13) -> 0 | O10: =SUMIF('11月'!$B$6:$B$13,$C10,'11月'!$D$6:$D$13) -> 0 | P10: =SUMIF('12月'!$B$6:$B$13,$C10,'12月'!$D$6:$D$13) -> 0 | Q10: =AVERAGE(E10:P10) -> 0 | R10: =SUM(E10:P10) -> 0 | T10: 2000
E11: =SUMIF('1月'!$B$6:$B$13,$C11,'1月'!$D$6:$D$13) -> 0 | F11: =SUMIF('2月'!$B$6:$B$13,$C11,'2月'!$D$6:$D$13) -> 0 | G11: =SUMIF('3月'!$B$6:$B$13,$C11,'3月'!$D$6:$D$13) -> 0 | H11: =SUMIF('4月'!$B$6:$B$13,$C11,'4月'!$D$6:$D$13) -> 0 | I11: =SUMIF('5月'!$B$6:$B$13,$C11,'5月'!$D$6:$D$13) -> 0 | J11: =SUMIF('6月'!$B$6:$B$13,$C11,'6月'!$D$6:$D$13) -> 0 | K11: =SUMIF('7月'!$B$6:$B$13,$C11,'7月'!$D$6:$D$13) -> 0 | L11: =SUMIF('8月'!$B$6:$B$13,$C11,'8月'!$D$6:$D$13) -> 0 | M11: =SUMIF('9月'!$B$6:$B$13,$C11,'9月'!$D$6:$D$13) -> 0 | N11: =SUMIF('10月'!$B$6:$B$13,$C11,'10月'!$D$6:$D$13) -> 0 | O11: =SUMIF('11月'!$B$6:$B$13,$C11,'11月'!$D$6:$D$13) -> 0 | P11: =SUMIF('12月'!$B$6:$B$13,$C11,'12月'!$D$6:$D$13) -> 0 | Q11: =AVERAGE(E11:P11) -> 0 | R11: =SUM(E11:P11) -> 0 | T11: 5000
C12: 収入合計 | E12: =SUM(E4:E11) -> 400000 | F12: =SUM(F4:F11) -> 0 | G12: =SUM(G4:G11) -> 0 | H12: =SUM(H4:H11) -> 0 | I12: =SUM(I4:I11) -> 0 | J12: =SUM(J4:J11) -> 0 | K12: =SUM(K4:K11) -> 0 | L12: =SUM(L4:L11) -> 0 | ... P12: =SUM(P4:P11) -> 0 | Q12: =AVERAGE(E12:P12) -> 33333.333 | R12: =SUM(E12:P12) -> 400000 | T12: 0
A13: 支出 | B13: 固定費 | C13: 🏠 住宅 | E13: =SUMIF('1月'!$B$19:$B$30,$C13,'1月'!$D$19:$D$30) -> 100000 | F13: =SUMIF('2月'!$B$19:$B$30,$C13,'2月'!$D$19:$D$30) -> 0 | G13: =SUMIF('3月'!$B$19:$B$30,$C13,'3月'!$D$19:$D$30) -> 0 | H13: =SUMIF('4月'!$B$19:$B$30,$C13,'4月'!$D$19:$D$30) -> 0 | I13: =SUMIF('5月'!$B$19:$B$30,$C13,'5月'!$D$19:$D$30) -> 0 | J13: =SUMIF('6月'!$B$19:$B$30,$C13,'6月'!$D$19:$D$30) -> 0 | K13: =SUMIF('7月'!$B$19:$B$30,$C13,'7月'!$D$19:$D$30) -> 0 | L13: =SUMIF('8月'!$B$19:$B$30,$C13,'8月'!$D$19:$D$30) -> 0 | M13: =SUMIF('9月'!$B$19:$B$30,$C13,'9月'!$D$19:$D$30) -> 0 | N13: =SUMIF('10月'!$B$19:$B$30,$C13,'10月'!$D$19:$D$30) -> 0 | O13: =SUMIF('11月'!$B$19:$B$30,$C13,'11月'!$D$19:$D$30) -> 0 | P13: =SUMIF('12月'!$B$19:$B$30,$C13,'12月'!$D$19:$D$30) -> 0 | Q13: =AVERAGE(E13:P13) -> 8333.3333 | R13: =SUM(E13:P13) -> 100000 | T13: 0
C14: 💡 電気 | E14: =SUMIF('1月'!$B$19:$B$30,$C14,'1月'!$D$19:$D$30) -> 8000 | F14: =SUMIF('2月'!$B$19:$B$30,$C14,'2月'!$D$19:$D$30) -> 0 | G14: =SUMIF('3月'!$B$19:$B$30,$C14,'3月'!$D$19:$D$30) -> 0 | H14: =SUMIF('4月'!$B$19:$B$30,$C14,'4月'!$D$19:$D$30) -> 0 | I14: =SUMIF('5月'!$B$19:$B$30,$C14,'5月'!$D$19:$D$30) -> 0 | J14: =SUMIF('6月'!$B$19:$B$30,$C14,'6月'!$D$19:$D$30) -> 0 | K14: =SUMIF('7月'!$B$19:$B$30,$C14,'7月'!$D$19:$D$30) -> 0 | L14: =SUMIF('8月'!$B$19:$B$30,$C14,'8月'!$D$19:$D$30) -> 0 | M14: =SUMIF('9月'!$B$19:$B$30,$C14,'9月'!$D$19:$D$30) -> 0 | N14: =SUMIF('10月'!$B$19:$B$30,$C14,'10月'!$D$19:$D$30) -> 0 | O14: =SUMIF('11月'!$B$19:$B$30,$C14,'11月'!$D$19:$D$30) -> 0 | P14: =SUMIF('12月'!$B$19:$B$30,$C14,'12月'!$D$19:$D$30) -> 0 | Q14: =AVERAGE(E14:P14) -> 666.66667 | R14: =SUM(E14:P14) -> 8000 | T14: 0
C15: 🔥 ガス | E15: =SUMIF('1月'!$B$19:$B$30,$C15,'1月'!$D$19:$D$30) -> 5000 | F15: =SUMIF('2月'!$B$19:$B$30,$C15,'2月'!$D$19:$D$30) -> 0 | G15: =SUMIF('3月'!$B$19:$B$30,$C15,'3月'!$D$19:$D$30) -> 0 | H15: =SUMIF('4月'!$B$19:$B$30,$C15,'4月'!$D$19:$D$30) -> 0 | I15: =SUMIF('5月'!$B$19:$B$30,$C15,'5月'!$D$19:$D$30) -> 0 | J15: =SUMIF('6月'!$B$19:$B$30,$C15,'6月'!$D$19:$D$30) -> 0 | K15: =SUMIF('7月'!$B$19:$B$30,$C15,'7月'!$D$19:$D$30) -> 0 | L15: =SUMIF('8月'!$B$19:$B$30,$C15,'8月'!$D$19:$D$30) -> 0 | M15: =SUMIF('9月'!$B$19:$B$30,$C15,'9月'!$D$19:$D$30) -> 0 | N15: =SUMIF('10月'!$B$19:$B$30,$C15,'10月'!$D$19:$D$30) -> 0 | O15: =SUMIF('11月'!$B$19:$B$30,$C15,'11月'!$D$19:$D$30) -> 0 | P15: =SUMIF('12月'!$B$19:$B$30,$C15,'12月'!$D$19:$D$30) -> 0 | Q15: =AVERAGE(E15:P15) -> 416.66667 | R15: =SUM(E15:P15) -> 5000 | T15: 0
C16: 🚰 水道 | E16: =SUMIF('1月'!$B$19:$B$30,$C16,'1月'!$D$19:$D$30) -> 2000 | F16: =SUMIF('2月'!$B$19:$B$30,$C16,'2月'!$D$19:$D$30) -> 0 | G16: =SUMIF('3月'!$B$19:$B$30,$C16,'3月'!$D$19:$D$30) -> 0 | H16: =SUMIF('4月'!$B$19:$B$30,$C16,'4月'!$D$19:$D$30) -> 0 | I16: =SUMIF('5月'!$B$19:$B$30,$C16,'5月'!$D$19:$D$30) -> 0 | J16: =SUMIF('6月'!$B$19:$B$30,$C16,'6月'!$D$19:$D$30) -> 0 | K16: =SUMIF('7月'!$B$19:$B$30,$C16,'7月'!$D$19:$D$30) -> 0 | L16: =SUMIF('8月'!$B$19:$B$30,$C16,'8月'!$D$19:$D$30) -> 0 | M16: =SUMIF('9月'!$B$19:$B$30,$C16,'9月'!$D$19:$D$30) -> 0 | N16: =SUMIF('10月'!$B$19:$B$30,$C16,'10月'!$D$19:$D$30) -> 0 | O16: =SUMIF('11月'!$B$19:$B$30,$C16,'11月'!$D$19:$D$30) -> 0 | P16: =SUMIF('12月'!$B$19:$B$30,$C16,'12月'!$D$19:$D$30) -> 0 | Q16: =AVERAGE(E16:P16) -> 166.66667 | R16: =SUM(E16:P16) -> 2000 | T16: 157000
C17: 🎓 教養・教育 | E17: =SUMIF('1月'!$B$19:$B$30,$C17,'1月'!$D$19:$D$30) -> 30000 | F17: =SUMIF('2月'!$B$19:$B$30,$C17,'2月'!$D$19:$D$30) -> 0 | G17: =SUMIF('3月'!$B$19:$B$30,$C17,'3月'!$D$19:$D$30) -> 0 | H17: =SUMIF('4月'!$B$19:$B$30,$C17,'4月'!$D$19:$D$30) -> 0 | I17: =SUMIF('5月'!$B$19:$B$30,$C17,'5月'!$D$19:$D$30) -> 0 | J17: =SUMIF('6月'!$B$19:$B$30,$C17,'6月'!$D$19:$D$30) -> 0 | K17: =SUMIF('7月'!$B$19:$B$30,$C17,'7月'!$D$19:$D$30) -> 0 | L17: =SUMIF('8月'!$B$19:$B$30,$C17,'8月'!$D$19:$D$30) -> 0 | M17: =SUMIF('9月'!$B$19:$B$30,$C17,'9月'!$D$19:$D$30) -> 0 | N17: =SUMIF('10月'!$B$19:$B$30,$C17,'10月'!$D$19:$D$30) -> 0 | O17: =SUMIF('11月'!$B$19:$B$30,$C17,'11月'!$D$19:$D$30) -> 0 | P17: =SUMIF('12月'!$B$19:$B$30,$C17,'12月'!$D$19:$D$30) -> 0 | Q17: =AVERAGE(E17:P17) -> 2500 | R17: =SUM(E17:P17) -> 30000 | T17: 1000
C18: 📱 通信費 | E18: =SUMIF('1月'!$B$19:$B$30,$C18,'1月'!$D$19:$D$30) -> 5000 | F18: =SUMIF('2月'!$B$19:$B$30,$C18,'2月'!$D$19:$D$30) -> 0 | G18: =SUMIF('3月'!$B$19:$B$30,$C18,'3月'!$D$19:$D$30) -> 0 | H18: =SUMIF('4月'!$B$19:$B$30,$C18,'4月'!$D$19:$D$30) -> 0 | I18: =SUMIF('5月'!$B$19:$B$30,$C18,'5月'!$D$19:$D$30) -> 0 | J18: =SUMIF('6月'!$B$19:$B$30,$C18,'6月'!$D$19:$D$30) -> 0 | K18: =SUMIF('7月'!$B$19:$B$30,$C18,'7月'!$D$19:$D$30) -> 0 | L18: =SUMIF('8月'!$B$19:$B$30,$C18,'8月'!$D$19:$D$30) -> 0 | M18: =SUMIF('9月'!$B$19:$B$30,$C18,'9月'!$D$19:$D$30) -> 0 | N18: =SUMIF('10月'!$B$19:$B$30,$C18,'10月'!$D$19:$D$30) -> 0 | O18: =SUMIF('11月'!$B$19:$B$30,$C18,'11月'!$D$19:$D$30) -> 0 | P18: =SUMIF('12月'!$B$19:$B$30,$C18,'12月'!$D$19:$D$30) -> 0 | Q18: =AVERAGE(E18:P18) -> 416.66667 | R18: =SUM(E18:P18) -> 5000 | T18: 0
C19: 📽️ サブスク | E19: =SUMIF('1月'!$B$19:$B$30,$C19,'1月'!$D$19:$D$30) -> 2000 | F19: =SUMIF('2月'!$B$19:$B$30,$C19,'2月'!$D$19:$D$30) -> 0 | G19: =SUMIF('3月'!$B$19:$B$30,$C19,'3月'!$D$19:$D$30) -> 0 | H19: =SUMIF('4月'!$B$19:$B$30,$C19,'4月'!$D$19:$D$30) -> 0 | I19: =SUMIF('5月'!$B$19:$B$30,$C19,'5月'!$D$19:$D$30) -> 0 | J19: =SUMIF('6月'!$B$19:$B$30,$C19,'6月'!$D$19:$D$30) -> 0 | K19: =SUMIF('7月'!$B$19:$B$30,$C19,'7月'!$D$19:$D$30) -> 0 | L19: =SUMIF('8月'!$B$19:$B$30,$C19,'8月'!$D$19:$D$30) -> 0 | M19: =SUMIF('9月'!$B$19:$B$30,$C19,'9月'!$D$19:$D$30) -> 0 | N19: =SUMIF('10月'!$B$19:$B$30,$C19,'10月'!$D$19:$D$30) -> 0 | O19: =SUMIF('11月'!$B$19:$B$30,$C19,'11月'!$D$19:$D$30) -> 0 | P19: =SUMIF('12月'!$B$19:$B$30,$C19,'12月'!$D$19:$D$30) -> 0 | Q19: =AVERAGE(E19:P19) -> 166.66667 | R19: =SUM(E19:P19) -> 2000 | T19: 0
C20: 📃 保険 | E20: =SUMIF('1月'!$B$19:$B$30,$C20,'1月'!$D$19:$D$30) -> 5000 | F20: =SUMIF('2月'!$B$19:$B$30,$C20,'2月'!$D$19:$D$30) -> 0 | G20: =SUMIF('3月'!$B$19:$B$30,$C20,'3月'!$D$19:$D$30) -> 0 | H20: =SUMIF('4月'!$B$19:$B$30,$C20,'4月'!$D$19:$D$30) -> 0 | I20: =SUMIF('5月'!$B$19:$B$30,$C20,'5月'!$D$19:$D$30) -> 0 | J20: =SUMIF('6月'!$B$19:$B$30,$C20,'6月'!$D$19:$D$30) -> 0 | K20: =SUMIF('7月'!$B$19:$B$30,$C20,'7月'!$D$19:$D$30) -> 0 | L20: =SUMIF('8月'!$B$19:$B$30,$C20,'8月'!$D$19:$D$30) -> 0 | M20: =SUMIF('9月'!$B$19:$B$30,$C20,'9月'!$D$19:$D$30) -> 0 | N20: =SUMIF('10月'!$B$19:$B$30,$C20,'10月'!$D$19:$D$30) -> 0 | O20: =SUMIF('11月'!$B$19:$B$30,$C20,'11月'!$D$19:$D$30) -> 0 | P20: =SUMIF('12月'!$B$19:$B$30,$C20,'12月'!$D$19:$D$30) -> 0 | Q20: =AVERAGE(E20:P20) -> 416.66667 | R20: =SUM(E20:P20) -> 5000 | T20: 0
E21: =SUMIF('1月'!$B$19:$B$30,$C21,'1月'!$D$19:$D$30) -> 0 | F21: =SUMIF('2月'!$B$19:$B$30,$C21,'2月'!$D$19:$D$30) -> 0 | G21: =SUMIF('3月'!$B$19:$B$30,$C21,'3月'!$D$19:$D$30) -> 0 | H21: =SUMIF('4月'!$B$19:$B$30,$C21,'4月'!$D$19:$D$30) -> 0 | I21: =SUMIF('5月'!$B$19:$B$30,$C21,'5月'!$D$19:$D$30) -> 0 | J21: =SUMIF('6月'!$B$19:$B$30,$C21,'6月'!$D$19:$D$30) -> 0 | K21: =SUMIF('7月'!$B$19:$B$30,$C21,'7月'!$D$19:$D$30) -> 0 | L21: =SUMIF('8月'!$B$19:$B$30,$C21,'8月'!$D$19:$D$30) -> 0 | M21: =SUMIF('9月'!$B$19:$B$30,$C21,'9月'!$D$19:$D$30) -> 0 | N21: =SUMIF('10月'!$B$19:$B$30,$C21,'10月'!$D$19:$D$30) -> 0 | O21: =SUMIF('11月'!$B$19:$B$30,$C21,'11月'!$D$19:$D$30) -> 0 | P21: =SUMIF('12月'!$B$19:$B$30,$C21,'12月'!$D$19:$D$30) -> 0 | Q21: =AVERAGE(E21:P21) -> 0 | R21: =SUM(E21:P21) -> 0 | T21: 0
E22: =SUMIF('1月'!$B$19:$B$30,$C22,'1月'!$D$19:$D$30) -> 0 | F22: =SUMIF('2月'!$B$19:$B$30,$C22,'2月'!$D$19:$D$30) -> 0 | G22: =SUMIF('3月'!$B$19:$B$30,$C22,'3月'!$D$19:$D$30) -> 0 | H22: =SUMIF('4月'!$B$19:$B$30,$C22,'4月'!$D$19:$D$30) -> 0 | I22: =SUMIF('5月'!$B$19:$B$30,$C22,'5月'!$D$19:$D$30) -> 0 | J22: =SUMIF('6月'!$B$19:$B$30,$C22,'6月'!$D$19:$D$30) -> 0 | K22: =SUMIF('7月'!$B$19:$B$30,$C22,'7月'!$D$19:$D$30) -> 0 | L22: =SUMIF('8月'!$B$19:$B$30,$C22,'8月'!$D$19:$D$30) -> 0 | M22: =SUMIF('9月'!$B$19:$B$30,$C22,'9月'!$D$19:$D$30) -> 0 | N22: =SUMIF('10月'!$B$19:$B$30,$C22,'10月'!$D$19:$D$30) -> 0 | O22: =SUMIF('11月'!$B$19:$B$30,$C22,'11月'!$D$19:$D$30) -> 0 | P22: =SUMIF('12月'!$B$19:$B$30,$C22,'12月'!$D$19:$D$30) -> 0 | Q22: =AVERAGE(E22:P22) -> 0 | R22: =SUM(E22:P22) -> 0 | T22: 0
E23: =SUMIF('1月'!$B$19:$B$30,$C23,'1月'!$D$19:$D$30) -> 0 | F23: =SUMIF('2月'!$B$19:$B$30,$C23,'2月'!$D$19:$D$30) -> 0 | G23: =SUMIF('3月'!$B$19:$B$30,$C23,'3月'!$D$19:$D$30) -> 0 | H23: =SUMIF('4月'!$B$19:$B$30,$C23,'4月'!$D$19:$D$30) -> 0 | I23: =SUMIF('5月'!$B$19:$B$30,$C23,'5月'!$D$19:$D$30) -> 0 | J23: =SUMIF('6月'!$B$19:$B$30,$C23,'6月'!$D$19:$D$30) -> 0 | K23: =SUMIF('7月'!$B$19:$B$30,$C23,'7月'!$D$19:$D$30) -> 0 | L23: =SUMIF('8月'!$B$19:$B$30,$C23,'8月'!$D$19:$D$30) -> 0 | M23: =SUMIF('9月'!$B$19:$B$30,$C23,'9月'!$D$19:$D$30) -> 0 | N23: =SUMIF('10月'!$B$19:$B$30,$C23,'10月'!$D$19:$D$30) -> 0 | O23: =SUMIF('11月'!$B$19:$B$30,$C23,'11月'!$D$19:$D$30) -> 0 | P23: =SUMIF('12月'!$B$19:$B$30,$C23,'12月'!$D$19:$D$30) -> 0 | Q23: =AVERAGE(E23:P23) -> 0 | R23: =SUM(E23:P23) -> 0 | T23: 0
E24: =SUMIF('1月'!$B$19:$B$30,$C24,'1月'!$D$19:$D$30) -> 0 | F24: =SUMIF('2月'!$B$19:$B$30,$C24,'2月'!$D$19:$D$30) -> 0 | G24: =SUMIF('3月'!$B$19:$B$30,$C24,'3月'!$D$19:$D$30) -> 0 | H24: =SUMIF('4月'!$B$19:$B$30,$C24,'4月'!$D$19:$D$30) -> 0 | I24: =SUMIF('5月'!$B$19:$B$30,$C24,'5月'!$D$19:$D$30) -> 0 | J24: =SUMIF('6月'!$B$19:$B$30,$C24,'6月'!$D$19:$D$30) -> 0 | K24: =SUMIF('7月'!$B$19:$B$30,$C24,'7月'!$D$19:$D$30) -> 0 | L24: =SUMIF('8月'!$B$19:$B$30,$C24,'8月'!$D$19:$D$30) -> 0 | M24: =SUMIF('9月'!$B$19:$B$30,$C24,'9月'!$D$19:$D$30) -> 0 | N24: =SUMIF('10月'!$B$19:$B$30,$C24,'10月'!$D$19:$D$30) -> 0 | O24: =SUMIF('11月'!$B$19:$B$30,$C24,'11月'!$D$19:$D$30) -> 0 | P24: =SUMIF('12月'!$B$19:$B$30,$C24,'12月'!$D$19:$D$30) -> 0 | Q24: =AVERAGE(E24:P24) -> 0 | R24: =SUM(E24:P24) -> 0 | T24: 0
C25: 固定費合計 | E25: =SUM(E13:E24) -> 157000 | F25: =SUM(F13:F24) -> 0 | G25: =SUM(G13:G24) -> 0 | H25: =SUM(H13:H24) -> 0 | I25: =SUM(I13:I24) -> 0 | J25: =SUM(J13:J24) -> 0 | K25: =SUM(K13:K24) -> 0 | L25: =SUM(L13:L24) -> 0 | ... P25: =SUM(P13:P24) -> 0 | Q25: =AVERAGE(E25:P25) -> 13083.333 | R25: =SUM(E25:P25) -> 157000 | T25: 0
B26: 変動費 | C26: 🍙 食費 | E26: =SUMIF('1月'!$F$19:$F$30,$C26,'1月'!$H$19:$H$30) -> 1000 | F26: =SUMIF('2月'!$F$19:$F$30,$C26,'2月'!$H$19:$H$30) -> 0 | G26: =SUMIF('3月'!$F$19:$F$30,$C26,'3月'!$H$19:$H$30) -> 0 | H26: =SUMIF('4月'!$F$19:$F$30,$C26,'4月'!$H$19:$H$30) -> 0 | I26: =SUMIF('5月'!$F$19:$F$30,$C26,'5月'!$H$19:$H$30) -> 0 | J26: =SUMIF('6月'!$F$19:$F$30,$C26,'6月'!$H$19:$H$30) -> 0 | K26: =SUMIF('7月'!$F$19:$F$30,$C26,'7月'!$H$19:$H$30) -> 0 | L26: =SUMIF('8月'!$F$19:$F$30,$C26,'8月'!$H$19:$H$30) -> 0 | M26: =SUMIF('9月'!$F$19:$F$30,$C26,'9月'!$H$19:$H$30) -> 0 | N26: =SUMIF('10月'!$F$19:$F$30,$C26,'10月'!$H$19:$H$30) -> 0 | O26: =SUMIF('11月'!$F$19:$F$30,$C26,'11月'!$H$19:$H$30) -> 0 | P26: =SUMIF('12月'!$F$19:$F$30,$C26,'12月'!$H$19:$H$30) -> 0 | Q26: =AVERAGE(E26:P26) -> 83.333333 | R26: =SUM(E26:P26) -> 1000 | T26: 0
C27: 🧴 日用品 | E27: =SUMIF('1月'!$F$19:$F$30,$C27,'1月'!$H$19:$H$30) -> 0 | F27: =SUMIF('2月'!$F$19:$F$30,$C27,'2月'!$H$19:$H$30) -> 0 | G27: =SUMIF('3月'!$F$19:$F$30,$C27,'3月'!$H$19:$H$30) -> 0 | H27: =SUMIF('4月'!$F$19:$F$30,$C27,'4月'!$H$19:$H$30) -> 0 | I27: =SUMIF('5月'!$F$19:$F$30,$C27,'5月'!$H$19:$H$30) -> 0 | J27: =SUMIF('6月'!$F$19:$F$30,$C27,'6月'!$H$19:$H$30) -> 0 | K27: =SUMIF('7月'!$F$19:$F$30,$C27,'7月'!$H$19:$H$30) -> 0 | L27: =SUMIF('8月'!$F$19:$F$30,$C27,'8月'!$H$19:$H$30) -> 0 | M27: =SUMIF('9月'!$F$19:$F$30,$C27,'9月'!$H$19:$H$30) -> 0 | N27: =SUMIF('10月'!$F$19:$F$30,$C27,'10月'!$H$19:$H$30) -> 0 | O27: =SUMIF('11月'!$F$19:$F$30,$C27,'11月'!$H$19:$H$30) -> 0 | P27: =SUMIF('12月'!$F$19:$F$30,$C27,'12月'!$H$19:$H$30) -> 0 | Q27: =AVERAGE(E27:P27) -> 0 | R27: =SUM(E27:P27) -> 0 | T27: 0
C28: 📒 雑費 | E28: =SUMIF('1月'!$F$19:$F$30,$C28,'1月'!$H$19:$H$30) -> 0 | F28: =SUMIF('2月'!$F$19:$F$30,$C28,'2月'!$H$19:$H$30) -> 0 | G28: =SUMIF('3月'!$F$19:$F$30,$C28,'3月'!$H$19:$H$30) -> 0 | H28: =SUMIF('4月'!$F$19:$F$30,$C28,'4月'!$H$19:$H$30) -> 0 | I28: =SUMIF('5月'!$F$19:$F$30,$C28,'5月'!$H$19:$H$30) -> 0 | J28: =SUMIF('6月'!$F$19:$F$30,$C28,'6月'!$H$19:$H$30) -> 0 | K28: =SUMIF('7月'!$F$19:$F$30,$C28,'7月'!$H$19:$H$30) -> 0 | L28: =SUMIF('8月'!$F$19:$F$30,$C28,'8月'!$H$19:$H$30) -> 0 | M28: =SUMIF('9月'!$F$19:$F$30,$C28,'9月'!$H$19:$H$30) -> 0 | N28: =SUMIF('10月'!$F$19:$F$30,$C28,'10月'!$H$19:$H$30) -> 0 | O28: =SUMIF('11月'!$F$19:$F$30,$C28,'11月'!$H$19:$H$30) -> 0 | P28: =SUMIF('12月'!$F$19:$F$30,$C28,'12月'!$H$19:$H$30) -> 0 | Q28: =AVERAGE(E28:P28) -> 0 | R28: =SUM(E28:P28) -> 0 | T28: 0
C29: ⛺️ 趣味・娯楽 | E29: =SUMIF('1月'!$F$19:$F$30,$C29,'1月'!$H$19:$H$30) -> 0 | F29: =SUMIF('2月'!$F$19:$F$30,$C29,'2月'!$H$19:$H$30) -> 0 | G29: =SUMIF('3月'!$F$19:$F$30,$C29,'3月'!$H$19:$H$30) -> 0 | H29: =SUMIF('4月'!$F$19:$F$30,$C29,'4月'!$H$19:$H$30) -> 0 | I29: =SUMIF('5月'!$F$19:$F$30,$C29,'5月'!$H$19:$H$30) -> 0 | J29: =SUMIF('6月'!$F$19:$F$30,$C29,'6月'!$H$19:$H$30) -> 0 | K29: =SUMIF('7月'!$F$19:$F$30,$C29,'7月'!$H$19:$H$30) -> 0 | L29: =SUMIF('8月'!$F$19:$F$30,$C29,'8月'!$H$19:$H$30) -> 0 | M29: =SUMIF('9月'!$F$19:$F$30,$C29,'9月'!$H$19:$H$30) -> 0 | N29: =SUMIF('10月'!$F$19:$F$30,$C29,'10月'!$H$19:$H$30) -> 0 | O29: =SUMIF('11月'!$F$19:$F$30,$C29,'11月'!$H$19:$H$30) -> 0 | P29: =SUMIF('12月'!$F$19:$F$30,$C29,'12月'!$H$19:$H$30) -> 0 | Q29: =AVERAGE(E29:P29) -> 0 | R29: =SUM(E29:P29) -> 0 | T29: 1000
C30: 👚 衣服・美容 | E30: =SUMIF('1月'!$F$19:$F$30,$C30,'1月'!$H$19:$H$30) -> 0 | F30: =SUMIF('2月'!$F$19:$F$30,$C30,'2月'!$H$19:$H$30) -> 0 | G30: =SUMIF('3月'!$F$19:$F$30,$C30,'3月'!$H$19:$H$30) -> 0 | H30: =SUMIF('4月'!$F$19:$F$30,$C30,'4月'!$H$19:$H$30) -> 0 | I30: =SUMIF('5月'!$F$19:$F$30,$C30,'5月'!$H$19:$H$30) -> 0 | J30: =SUMIF('6月'!$F$19:$F$30,$C30,'6月'!$H$19:$H$30) -> 0 | K30: =SUMIF('7月'!$F$19:$F$30,$C30,'7月'!$H$19:$H$30) -> 0 | L30: =SUMIF('8月'!$F$19:$F$30,$C30,'8月'!$H$19:$H$30) -> 0 | M30: =SUMIF('9月'!$F$19:$F$30,$C30,'9月'!$H$19:$H$30) -> 0 | N30: =SUMIF('10月'!$F$19:$F$30,$C30,'10月'!$H$19:$H$30) -> 0 | O30: =SUMIF('11月'!$F$19:$F$30,$C30,'11月'!$H$19:$H$30) -> 0 | P30: =SUMIF('12月'!$F$19:$F$30,$C30,'12月'!$H$19:$H$30) -> 0 | Q30: =AVERAGE(E30:P30) -> 0 | R30: =SUM(E30:P30) -> 0 | T30: 158000
C31: 🏥 健康・医療 | E31: =SUMIF('1月'!$F$19:$F$30,$C31,'1月'!$H$19:$H$30) -> 0 | F31: =SUMIF('2月'!$F$19:$F$30,$C31,'2月'!$H$19:$H$30) -> 0 | G31: =SUMIF('3月'!$F$19:$F$30,$C31,'3月'!$H$19:$H$30) -> 0 | H31: =SUMIF('4月'!$F$19:$F$30,$C31,'4月'!$H$19:$H$30) -> 0 | I31: =SUMIF('5月'!$F$19:$F$30,$C31,'5月'!$H$19:$H$30) -> 0 | J31: =SUMIF('6月'!$F$19:$F$30,$C31,'6月'!$H$19:$H$30) -> 0 | K31: =SUMIF('7月'!$F$19:$F$30,$C31,'7月'!$H$19:$H$30) -> 0 | L31: =SUMIF('8月'!$F$19:$F$30,$C31,'8月'!$H$19:$H$30) -> 0 | M31: =SUMIF('9月'!$F$19:$F$30,$C31,'9月'!$H$19:$H$30) -> 0 | N31: =SUMIF('10月'!$F$19:$F$30,$C31,'10月'!$H$19:$H$30) -> 0 | O31: =SUMIF('11月'!$F$19:$F$30,$C31,'11月'!$H$19:$H$30) -> 0 | P31: =SUMIF('12月'!$F$19:$F$30,$C31,'12月'!$H$19:$H$30) -> 0 | Q31: =AVERAGE(E31:P31) -> 0 | R31: =SUM(E31:P31) -> 0 | T31: 0.395
C32: 🍼 子ども | E32: =SUMIF('1月'!$F$19:$F$30,$C32,'1月'!$H$19:$H$30) -> 0 | F32: =SUMIF('2月'!$F$19:$F$30,$C32,'2月'!$H$19:$H$30) -> 0 | G32: =SUMIF('3月'!$F$19:$F$30,$C32,'3月'!$H$19:$H$30) -> 0 | H32: =SUMIF('4月'!$F$19:$F$30,$C32,'4月'!$H$19:$H$30) -> 0 | I32: =SUMIF('5月'!$F$19:$F$30,$C32,'5月'!$H$19:$H$30) -> 0 | J32: =SUMIF('6月'!$F$19:$F$30,$C32,'6月'!$H$19:$H$30) -> 0 | K32: =SUMIF('7月'!$F$19:$F$30,$C32,'7月'!$H$19:$H$30) -> 0 | L32: =SUMIF('8月'!$F$19:$F$30,$C32,'8月'!$H$19:$H$30) -> 0 | M32: =SUMIF('9月'!$F$19:$F$30,$C32,'9月'!$H$19:$H$30) -> 0 | N32: =SUMIF('10月'!$F$19:$F$30,$C32,'10月'!$H$19:$H$30) -> 0 | O32: =SUMIF('11月'!$F$19:$F$30,$C32,'11月'!$H$19:$H$30) -> 0 | P32: =SUMIF('12月'!$F$19:$F$30,$C32,'12月'!$H$19:$H$30) -> 0 | Q32: =AVERAGE(E32:P32) -> 0 | R32: =SUM(E32:P32) -> 0 | T32: 0
C33: 🍷 交際費 | E33: =SUMIF('1月'!$F$19:$F$30,$C33,'1月'!$H$19:$H$30) -> 0 | F33: =SUMIF('2月'!$F$19:$F$30,$C33,'2月'!$H$19:$H$30) -> 0 | G33: =SUMIF('3月'!$F$19:$F$30,$C33,'3月'!$H$19:$H$30) -> 0 | H33: =SUMIF('4月'!$F$19:$F$30,$C33,'4月'!$H$19:$H$30) -> 0 | I33: =SUMIF('5月'!$F$19:$F$30,$C33,'5月'!$H$19:$H$30) -> 0 | J33: =SUMIF('6月'!$F$19:$F$30,$C33,'6月'!$H$19:$H$30) -> 0 | K33: =SUMIF('7月'!$F$19:$F$30,$C33,'7月'!$H$19:$H$30) -> 0 | L33: =SUMIF('8月'!$F$19:$F$30,$C33,'8月'!$H$19:$H$30) -> 0 | M33: =SUMIF('9月'!$F$19:$F$30,$C33,'9月'!$H$19:$H$30) -> 0 | N33: =SUMIF('10月'!$F$19:$F$30,$C33,'10月'!$H$19:$H$30) -> 0 | O33: =SUMIF('11月'!$F$19:$F$30,$C33,'11月'!$H$19:$H$30) -> 0 | P33: =SUMIF('12月'!$F$19:$F$30,$C33,'12月'!$H$19:$H$30) -> 0 | Q33: =AVERAGE(E33:P33) -> 0 | R33: =SUM(E33:P33) -> 0 | T33: 12000
C34: 🚃 交通費 | E34: =SUMIF('1月'!$F$19:$F$30,$C34,'1月'!$H$19:$H$30) -> 0 | F34: =SUMIF('2月'!$F$19:$F$30,$C34,'2月'!$H$19:$H$30) -> 0 | G34: =SUMIF('3月'!$F$19:$F$30,$C34,'3月'!$H$19:$H$30) -> 0 | H34: =SUMIF('4月'!$F$19:$F$30,$C34,'4月'!$H$19:$H$30) -> 0 | I34: =SUMIF('5月'!$F$19:$F$30,$C34,'5月'!$H$19:$H$30) -> 0 | J34: =SUMIF('6月'!$F$19:$F$30,$C34,'6月'!$H$19:$H$30) -> 0 | K34: =SUMIF('7月'!$F$19:$F$30,$C34,'7月'!$H$19:$H$30) -> 0 | L34: =SUMIF('8月'!$F$19:$F$30,$C34,'8月'!$H$19:$H$30) -> 0 | M34: =SUMIF('9月'!$F$19:$F$30,$C34,'9月'!$H$19:$H$30) -> 0 | N34: =SUMIF('10月'!$F$19:$F$30,$C34,'10月'!$H$19:$H$30) -> 0 | O34: =SUMIF('11月'!$F$19:$F$30,$C34,'11月'!$H$19:$H$30) -> 0 | P34: =SUMIF('12月'!$F$19:$F$30,$C34,'12月'!$H$19:$H$30) -> 0 | Q34: =AVERAGE(E34:P34) -> 0 | R34: =SUM(E34:P34) -> 0 | T34: 0
E35: =SUMIF('1月'!$F$19:$F$30,$C35,'1月'!$H$19:$H$30) -> 0 | F35: =SUMIF('2月'!$F$19:$F$30,$C35,'2月'!$H$19:$H$30) -> 0 | G35: =SUMIF('3月'!$F$19:$F$30,$C35,'3月'!$H$19:$H$30) -> 0 | H35: =SUMIF('4月'!$F$19:$F$30,$C35,'4月'!$H$19:$H$30) -> 0 | I35: =SUMIF('5月'!$F$19:$F$30,$C35,'5月'!$H$19:$H$30) -> 0 | J35: =SUMIF('6月'!$F$19:$F$30,$C35,'6月'!$H$19:$H$30) -> 0 | K35: =SUMIF('7月'!$F$19:$F$30,$C35,'7月'!$H$19:$H$30) -> 0 | L35: =SUMIF('8月'!$F$19:$F$30,$C35,'8月'!$H$19:$H$30) -> 0 | M35: =SUMIF('9月'!$F$19:$F$30,$C35,'9月'!$H$19:$H$30) -> 0 | N35: =SUMIF('10月'!$F$19:$F$30,$C35,'10月'!$H$19:$H$30) -> 0 | O35: =SUMIF('11月'!$F$19:$F$30,$C35,'11月'!$H$19:$H$30) -> 0 | P35: =SUMIF('12月'!$F$19:$F$30,$C35,'12月'!$H$19:$H$30) -> 0 | Q35: =AVERAGE(E35:P35) -> 0 | R35: =SUM(E35:P35) -> 0 | T35: 0
E36: =SUMIF('1月'!$F$19:$F$30,$C36,'1月'!$H$19:$H$30) -> 0 | F36: =SUMIF('2月'!$F$19:$F$30,$C36,'2月'!$H$19:$H$30) -> 0 | G36: =SUMIF('3月'!$F$19:$F$30,$C36,'3月'!$H$19:$H$30) -> 0 | H36: =SUMIF('4月'!$F$19:$F$30,$C36,'4月'!$H$19:$H$30) -> 0 | I36: =SUMIF('5月'!$F$19:$F$30,$C36,'5月'!$H$19:$H$30) -> 0 | J36: =SUMIF('6月'!$F$19:$F$30,$C36,'6月'!$H$19:$H$30) -> 0 | K36: =SUMIF('7月'!$F$19:$F$30,$C36,'7月'!$H$19:$H$30) -> 0 | L36: =SUMIF('8月'!$F$19:$F$30,$C36,'8月'!$H$19:$H$30) -> 0 | M36: =SUMIF('9月'!$F$19:$F$30,$C36,'9月'!$H$19:$H$30) -> 0 | N36: =SUMIF('10月'!$F$19:$F$30,$C36,'10月'!$H$19:$H$30) -> 0 | O36: =SUMIF('11月'!$F$19:$F$30,$C36,'11月'!$H$19:$H$30) -> 0 | P36: =SUMIF('12月'!$F$19:$F$30,$C36,'12月'!$H$19:$H$30) -> 0 | Q36: =AVERAGE(E36:P36) -> 0 | R36: =SUM(E36:P36) -> 0 | T36: 0
E37: =SUMIF('1月'!$F$19:$F$30,$C37,'1月'!$H$19:$H$30) -> 0 | F37: =SUMIF('2月'!$F$19:$F$30,$C37,'2月'!$H$19:$H$30) -> 0 | G37: =SUMIF('3月'!$F$19:$F$30,$C37,'3月'!$H$19:$H$30) -> 0 | H37: =SUMIF('4月'!$F$19:$F$30,$C37,'4月'!$H$19:$H$30) -> 0 | I37: =SUMIF('5月'!$F$19:$F$30,$C37,'5月'!$H$19:$H$30) -> 0 | J37: =SUMIF('6月'!$F$19:$F$30,$C37,'6月'!$H$19:$H$30) -> 0 | K37: =SUMIF('7月'!$F$19:$F$30,$C37,'7月'!$H$19:$H$30) -> 0 | L37: =SUMIF('8月'!$F$19:$F$30,$C37,'8月'!$H$19:$H$30) -> 0 | M37: =SUMIF('9月'!$F$19:$F$30,$C37,'9月'!$H$19:$H$30) -> 0 | N37: =SUMIF('10月'!$F$19:$F$30,$C37,'10月'!$H$19:$H$30) -> 0 | O37: =SUMIF('11月'!$F$19:$F$30,$C37,'11月'!$H$19:$H$30) -> 0 | P37: =SUMIF('12月'!$F$19:$F$30,$C37,'12月'!$H$19:$H$30) -> 0 | Q37: =AVERAGE(E37:P37) -> 0 | R37: =SUM(E37:P37) -> 0 | T37: 0
C38: 変動費合計 | E38: =SUM(E26:E37) -> 1000 | F38: =SUM(F26:F37) -> 0 | G38: =SUM(G26:G37) -> 0 | H38: =SUM(H26:H37) -> 0 | I38: =SUM(I26:I37) -> 0 | J38: =SUM(J26:J37) -> 0 | K38: =SUM(K26:K37) -> 0 | L38: =SUM(L26:L37) -> 0 | ... P38: =SUM(P26:P37) -> 0 | Q38: =AVERAGE(E38:P38) -> 83.333333 | R38: =SUM(E38:P38) -> 1000 | T38: 0
B39: 支出合計（特別費除く） | E39: =E25+E38 -> 158000 | F39: =F25+F38 -> 0 | G39: =G25+G38 -> 0 | H39: =H25+H38 -> 0 | I39: =I25+I38 -> 0 | J39: =J25+J38 -> 0 | K39: =K25+K38 -> 0 | L39: =L25+L38 -> 0 | ... P39: =P25+P38 -> 0 | Q39: =AVERAGE(E39:P39) -> 13166.667 | R39: =SUM(E39:P39) -> 158000 | T39: 0
B40: 支出率 | D40: 目標：80%以下 | E40: =IFERROR(E39/E12,"") -> 0.395 | F40: =IFERROR(F39/F12,"") | G40: =IFERROR(G39/G12,"") | H40: =IFERROR(H39/H12,"") | I40: =IFERROR(I39/I12,"") | J40: =IFERROR(J39/J12,"") | K40: =IFERROR(K39/K12,"") | L40: =IFERROR(L39/L12,"") | ... R40: =IFERROR(R39/R12,"") -> 0.395 | T40: 0
B41: 特別費 | C41: ✈️ 旅行 | E41: =SUMIF('1月'!$B$35:$B$41,$C41,'1月'!$D$35:$D$41) -> 0 | F41: =SUMIF('2月'!$B$35:$B$41,$C41,'2月'!$D$35:$D$41) -> 0 | G41: =SUMIF('3月'!$B$35:$B$41,$C41,'3月'!$D$35:$D$41) -> 0 | H41: =SUMIF('4月'!$B$35:$B$41,$C41,'4月'!$D$35:$D$41) -> 0 | I41: =SUMIF('5月'!$B$35:$B$41,$C41,'5月'!$D$35:$D$41) -> 0 | J41: =SUMIF('6月'!$B$35:$B$41,$C41,'6月'!$D$35:$D$41) -> 0 | K41: =SUMIF('7月'!$B$35:$B$41,$C41,'7月'!$D$35:$D$41) -> 0 | L41: =SUMIF('8月'!$B$35:$B$41,$C41,'8月'!$D$35:$D$41) -> 0 | M41: =SUMIF('9月'!$B$35:$B$41,$C41,'9月'!$D$35:$D$41) -> 0 | N41: =SUMIF('10月'!$B$35:$B$41,$C41,'10月'!$D$35:$D$41) -> 0 | O41: =SUMIF('11月'!$B$35:$B$41,$C41,'11月'!$D$35:$D$41) -> 0 | P41: =SUMIF('12月'!$B$35:$B$41,$C41,'12月'!$D$35:$D$41) -> 0 | Q41: =AVERAGE(E41:P41) -> 0 | R41: =SUM(E41:P41) -> 0 | T41: 0
C42: 🍴 食事 | E42: =SUMIF('1月'!$B$35:$B$41,$C42,'1月'!$D$35:$D$41) -> 12000 | F42: =SUMIF('2月'!$B$35:$B$41,$C42,'2月'!$D$35:$D$41) -> 0 | G42: =SUMIF('3月'!$B$35:$B$41,$C42,'3月'!$D$35:$D$41) -> 0 | H42: =SUMIF('4月'!$B$35:$B$41,$C42,'4月'!$D$35:$D$41) -> 0 | I42: =SUMIF('5月'!$B$35:$B$41,$C42,'5月'!$D$35:$D$41) -> 0 | J42: =SUMIF('6月'!$B$35:$B$41,$C42,'6月'!$D$35:$D$41) -> 0 | K42: =SUMIF('7月'!$B$35:$B$41,$C42,'7月'!$D$35:$D$41) -> 0 | L42: =SUMIF('8月'!$B$35:$B$41,$C42,'8月'!$D$35:$D$41) -> 0 | M42: =SUMIF('9月'!$B$35:$B$41,$C42,'9月'!$D$35:$D$41) -> 0 | N42: =SUMIF('10月'!$B$35:$B$41,$C42,'10月'!$D$35:$D$41) -> 0 | O42: =SUMIF('11月'!$B$35:$B$41,$C42,'11月'!$D$35:$D$41) -> 0 | P42: =SUMIF('12月'!$B$35:$B$41,$C42,'12月'!$D$35:$D$41) -> 0 | Q42: =AVERAGE(E42:P42) -> 1000 | R42: =SUM(E42:P42) -> 12000 | T42: 12000
C43: 🏠 更新料 | E43: =SUMIF('1月'!$B$35:$B$41,$C43,'1月'!$D$35:$D$41) -> 0 | F43: =SUMIF('2月'!$B$35:$B$41,$C43,'2月'!$D$35:$D$41) -> 0 | G43: =SUMIF('3月'!$B$35:$B$41,$C43,'3月'!$D$35:$D$41) -> 0 | H43: =SUMIF('4月'!$B$35:$B$41,$C43,'4月'!$D$35:$D$41) -> 0 | I43: =SUMIF('5月'!$B$35:$B$41,$C43,'5月'!$D$35:$D$41) -> 0 | J43: =SUMIF('6月'!$B$35:$B$41,$C43,'6月'!$D$35:$D$41) -> 0 | K43: =SUMIF('7月'!$B$35:$B$41,$C43,'7月'!$D$35:$D$41) -> 0 | L43: =SUMIF('8月'!$B$35:$B$41,$C43,'8月'!$D$35:$D$41) -> 0 | M43: =SUMIF('9月'!$B$35:$B$41,$C43,'9月'!$D$35:$D$41) -> 0 | N43: =SUMIF('10月'!$B$35:$B$41,$C43,'10月'!$D$35:$D$41) -> 0 | O43: =SUMIF('11月'!$B$35:$B$41,$C43,'11月'!$D$35:$D$41) -> 0 | P43: =SUMIF('12月'!$B$35:$B$41,$C43,'12月'!$D$35:$D$41) -> 0 | Q43: =AVERAGE(E43:P43) -> 0 | R43: =SUM(E43:P43) -> 0 | T43: 20000
C44: 🗒️ 保険 | E44: =SUMIF('1月'!$B$35:$B$41,$C44,'1月'!$D$35:$D$41) -> 0 | F44: =SUMIF('2月'!$B$35:$B$41,$C44,'2月'!$D$35:$D$41) -> 0 | G44: =SUMIF('3月'!$B$35:$B$41,$C44,'3月'!$D$35:$D$41) -> 0 | H44: =SUMIF('4月'!$B$35:$B$41,$C44,'4月'!$D$35:$D$41) -> 0 | I44: =SUMIF('5月'!$B$35:$B$41,$C44,'5月'!$D$35:$D$41) -> 0 | J44: =SUMIF('6月'!$B$35:$B$41,$C44,'6月'!$D$35:$D$41) -> 0 | K44: =SUMIF('7月'!$B$35:$B$41,$C44,'7月'!$D$35:$D$41) -> 0 | L44: =SUMIF('8月'!$B$35:$B$41,$C44,'8月'!$D$35:$D$41) -> 0 | M44: =SUMIF('9月'!$B$35:$B$41,$C44,'9月'!$D$35:$D$41) -> 0 | N44: =SUMIF('10月'!$B$35:$B$41,$C44,'10月'!$D$35:$D$41) -> 0 | O44: =SUMIF('11月'!$B$35:$B$41,$C44,'11月'!$D$35:$D$41) -> 0 | P44: =SUMIF('12月'!$B$35:$B$41,$C44,'12月'!$D$35:$D$41) -> 0 | Q44: =AVERAGE(E44:P44) -> 0 | R44: =SUM(E44:P44) -> 0 | T44: 30000
C45: 📠 家具・家電 | E45: =SUMIF('1月'!$B$35:$B$41,$C45,'1月'!$D$35:$D$41) -> 0 | F45: =SUMIF('2月'!$B$35:$B$41,$C45,'2月'!$D$35:$D$41) -> 0 | G45: =SUMIF('3月'!$B$35:$B$41,$C45,'3月'!$D$35:$D$41) -> 0 | H45: =SUMIF('4月'!$B$35:$B$41,$C45,'4月'!$D$35:$D$41) -> 0 | I45: =SUMIF('5月'!$B$35:$B$41,$C45,'5月'!$D$35:$D$41) -> 0 | J45: =SUMIF('6月'!$B$35:$B$41,$C45,'6月'!$D$35:$D$41) -> 0 | K45: =SUMIF('7月'!$B$35:$B$41,$C45,'7月'!$D$35:$D$41) -> 0 | L45: =SUMIF('8月'!$B$35:$B$41,$C45,'8月'!$D$35:$D$41) -> 0 | M45: =SUMIF('9月'!$B$35:$B$41,$C45,'9月'!$D$35:$D$41) -> 0 | N45: =SUMIF('10月'!$B$35:$B$41,$C45,'10月'!$D$35:$D$41) -> 0 | O45: =SUMIF('11月'!$B$35:$B$41,$C45,'11月'!$D$35:$D$41) -> 0 | P45: =SUMIF('12月'!$B$35:$B$41,$C45,'12月'!$D$35:$D$41) -> 0 | Q45: =AVERAGE(E45:P45) -> 0 | R45: =SUM(E45:P45) -> 0 | T45: 0
C46: ❓ その他 | E46: =SUMIF('1月'!$B$35:$B$41,$C46,'1月'!$D$35:$D$41) -> 0 | F46: =SUMIF('2月'!$B$35:$B$41,$C46,'2月'!$D$35:$D$41) -> 0 | G46: =SUMIF('3月'!$B$35:$B$41,$C46,'3月'!$D$35:$D$41) -> 0 | H46: =SUMIF('4月'!$B$35:$B$41,$C46,'4月'!$D$35:$D$41) -> 0 | I46: =SUMIF('5月'!$B$35:$B$41,$C46,'5月'!$D$35:$D$41) -> 0 | J46: =SUMIF('6月'!$B$35:$B$41,$C46,'6月'!$D$35:$D$41) -> 0 | K46: =SUMIF('7月'!$B$35:$B$41,$C46,'7月'!$D$35:$D$41) -> 0 | L46: =SUMIF('8月'!$B$35:$B$41,$C46,'8月'!$D$35:$D$41) -> 0 | M46: =SUMIF('9月'!$B$35:$B$41,$C46,'9月'!$D$35:$D$41) -> 0 | N46: =SUMIF('10月'!$B$35:$B$41,$C46,'10月'!$D$35:$D$41) -> 0 | O46: =SUMIF('11月'!$B$35:$B$41,$C46,'11月'!$D$35:$D$41) -> 0 | P46: =SUMIF('12月'!$B$35:$B$41,$C46,'12月'!$D$35:$D$41) -> 0 | Q46: =AVERAGE(E46:P46) -> 0 | R46: =SUM(E46:P46) -> 0 | T46: 30000
E47: =SUMIF('1月'!$B$35:$B$41,$C47,'1月'!$D$35:$D$41) -> 0 | F47: =SUMIF('2月'!$B$35:$B$41,$C47,'2月'!$D$35:$D$41) -> 0 | G47: =SUMIF('3月'!$B$35:$B$41,$C47,'3月'!$D$35:$D$41) -> 0 | H47: =SUMIF('4月'!$B$35:$B$41,$C47,'4月'!$D$35:$D$41) -> 0 | I47: =SUMIF('5月'!$B$35:$B$41,$C47,'5月'!$D$35:$D$41) -> 0 | J47: =SUMIF('6月'!$B$35:$B$41,$C47,'6月'!$D$35:$D$41) -> 0 | K47: =SUMIF('7月'!$B$35:$B$41,$C47,'7月'!$D$35:$D$41) -> 0 | L47: =SUMIF('8月'!$B$35:$B$41,$C47,'8月'!$D$35:$D$41) -> 0 | M47: =SUMIF('9月'!$B$35:$B$41,$C47,'9月'!$D$35:$D$41) -> 0 | N47: =SUMIF('10月'!$B$35:$B$41,$C47,'10月'!$D$35:$D$41) -> 0 | O47: =SUMIF('11月'!$B$35:$B$41,$C47,'11月'!$D$35:$D$41) -> 0 | P47: =SUMIF('12月'!$B$35:$B$41,$C47,'12月'!$D$35:$D$41) -> 0 | Q47: =AVERAGE(E47:P47) -> 0 | R47: =SUM(E47:P47) -> 0 | T47: 0
E48: =SUMIF('1月'!$B$35:$B$41,$C48,'1月'!$D$35:$D$41) -> 0 | F48: =SUMIF('2月'!$B$35:$B$41,$C48,'2月'!$D$35:$D$41) -> 0 | G48: =SUMIF('3月'!$B$35:$B$41,$C48,'3月'!$D$35:$D$41) -> 0 | H48: =SUMIF('4月'!$B$35:$B$41,$C48,'4月'!$D$35:$D$41) -> 0 | I48: =SUMIF('5月'!$B$35:$B$41,$C48,'5月'!$D$35:$D$41) -> 0 | J48: =SUMIF('6月'!$B$35:$B$41,$C48,'6月'!$D$35:$D$41) -> 0 | K48: =SUMIF('7月'!$B$35:$B$41,$C48,'7月'!$D$35:$D$41) -> 0 | L48: =SUMIF('8月'!$B$35:$B$41,$C48,'8月'!$D$35:$D$41) -> 0 | M48: =SUMIF('9月'!$B$35:$B$41,$C48,'9月'!$D$35:$D$41) -> 0 | N48: =SUMIF('10月'!$B$35:$B$41,$C48,'10月'!$D$35:$D$41) -> 0 | O48: =SUMIF('11月'!$B$35:$B$41,$C48,'11月'!$D$35:$D$41) -> 0 | P48: =SUMIF('12月'!$B$35:$B$41,$C48,'12月'!$D$35:$D$41) -> 0 | Q48: =AVERAGE(E48:P48) -> 0 | R48: =SUM(E48:P48) -> 0 | T48: 0
E49: =SUMIF('1月'!$B$35:$B$41,$C49,'1月'!$D$35:$D$41) -> 0 | F49: =SUMIF('2月'!$B$35:$B$41,$C49,'2月'!$D$35:$D$41) -> 0 | G49: =SUMIF('3月'!$B$35:$B$41,$C49,'3月'!$D$35:$D$41) -> 0 | H49: =SUMIF('4月'!$B$35:$B$41,$C49,'4月'!$D$35:$D$41) -> 0 | I49: =SUMIF('5月'!$B$35:$B$41,$C49,'5月'!$D$35:$D$41) -> 0 | J49: =SUMIF('6月'!$B$35:$B$41,$C49,'6月'!$D$35:$D$41) -> 0 | K49: =SUMIF('7月'!$B$35:$B$41,$C49,'7月'!$D$35:$D$41) -> 0 | L49: =SUMIF('8月'!$B$35:$B$41,$C49,'8月'!$D$35:$D$41) -> 0 | M49: =SUMIF('9月'!$B$35:$B$41,$C49,'9月'!$D$35:$D$41) -> 0 | N49: =SUMIF('10月'!$B$35:$B$41,$C49,'10月'!$D$35:$D$41) -> 0 | O49: =SUMIF('11月'!$B$35:$B$41,$C49,'11月'!$D$35:$D$41) -> 0 | P49: =SUMIF('12月'!$B$35:$B$41,$C49,'12月'!$D$35:$D$41) -> 0 | Q49: =AVERAGE(E49:P49) -> 0 | R49: =SUM(E49:P49) -> 0 | T49: 0
E50: =SUMIF('1月'!$B$35:$B$41,$C50,'1月'!$D$35:$D$41) -> 0 | F50: =SUMIF('2月'!$B$35:$B$41,$C50,'2月'!$D$35:$D$41) -> 0 | G50: =SUMIF('3月'!$B$35:$B$41,$C50,'3月'!$D$35:$D$41) -> 0 | H50: =SUMIF('4月'!$B$35:$B$41,$C50,'4月'!$D$35:$D$41) -> 0 | I50: =SUMIF('5月'!$B$35:$B$41,$C50,'5月'!$D$35:$D$41) -> 0 | J50: =SUMIF('6月'!$B$35:$B$41,$C50,'6月'!$D$35:$D$41) -> 0 | K50: =SUMIF('7月'!$B$35:$B$41,$C50,'7月'!$D$35:$D$41) -> 0 | L50: =SUMIF('8月'!$B$35:$B$41,$C50,'8月'!$D$35:$D$41) -> 0 | M50: =SUMIF('9月'!$B$35:$B$41,$C50,'9月'!$D$35:$D$41) -> 0 | N50: =SUMIF('10月'!$B$35:$B$41,$C50,'10月'!$D$35:$D$41) -> 0 | O50: =SUMIF('11月'!$B$35:$B$41,$C50,'11月'!$D$35:$D$41) -> 0 | P50: =SUMIF('12月'!$B$35:$B$41,$C50,'12月'!$D$35:$D$41) -> 0 | Q50: =AVERAGE(E50:P50) -> 0 | R50: =SUM(E50:P50) -> 0 | T50: 0
B51: 特別費合計（支出に含めない） | E51: =SUM(E41:E50) -> 12000 | F51: =SUM(F41:F50) -> 0 | G51: =SUM(G41:G50) -> 0 | H51: =SUM(H41:H50) -> 0 | I51: =SUM(I41:I50) -> 0 | J51: =SUM(J41:J50) -> 0 | K51: =SUM(K41:K50) -> 0 | L51: =SUM(L41:L50) -> 0 | ... P51: =SUM(P41:P50) -> 0 | Q51: =AVERAGE(E51:P51) -> 1000 | R51: =SUM(E51:P51) -> 12000 | T51: 80000
A52: 先取り貯金・投資 | C52: 💴 貯金 | E52: =SUMIF('1月'!$F$6:$F$13,$C52,'1月'!$H$6:$H$13) -> 20000 | F52: =SUMIF('2月'!$F$6:$F$13,$C52,'2月'!$H$6:$H$13) -> 0 | G52: =SUMIF('3月'!$F$6:$F$13,$C52,'3月'!$H$6:$H$13) -> 0 | H52: =SUMIF('4月'!$F$6:$F$13,$C52,'4月'!$H$6:$H$13) -> 0 | I52: =SUMIF('5月'!$F$6:$F$13,$C52,'5月'!$H$6:$H$13) -> 0 | J52: =SUMIF('6月'!$F$6:$F$13,$C52,'6月'!$H$6:$H$13) -> 0 | K52: =SUMIF('7月'!$F$6:$F$13,$C52,'7月'!$H$6:$H$13) -> 0 | L52: =SUMIF('8月'!$F$6:$F$13,$C52,'8月'!$H$6:$H$13) -> 0 | M52: =SUMIF('9月'!$F$6:$F$13,$C52,'9月'!$H$6:$H$13) -> 0 | N52: =SUMIF('10月'!$F$6:$F$13,$C52,'10月'!$H$6:$H$13) -> 0 | O52: =SUMIF('11月'!$F$6:$F$13,$C52,'11月'!$H$6:$H$13) -> 0 | P52: =SUMIF('12月'!$F$6:$F$13,$C52,'12月'!$H$6:$H$13) -> 0 | Q52: =AVERAGE(E52:P52) -> 1666.6667 | R52: =SUM(E52:P52) -> 20000 | T52: 162000
C53: 💴 NISA | E53: =SUMIF('1月'!$F$6:$F$13,$C53,'1月'!$H$6:$H$13) -> 30000 | F53: =SUMIF('2月'!$F$6:$F$13,$C53,'2月'!$H$6:$H$13) -> 0 | G53: =SUMIF('3月'!$F$6:$F$13,$C53,'3月'!$H$6:$H$13) -> 0 | H53: =SUMIF('4月'!$F$6:$F$13,$C53,'4月'!$H$6:$H$13) -> 0 | I53: =SUMIF('5月'!$F$6:$F$13,$C53,'5月'!$H$6:$H$13) -> 0 | J53: =SUMIF('6月'!$F$6:$F$13,$C53,'6月'!$H$6:$H$13) -> 0 | K53: =SUMIF('7月'!$F$6:$F$13,$C53,'7月'!$H$6:$H$13) -> 0 | L53: =SUMIF('8月'!$F$6:$F$13,$C53,'8月'!$H$6:$H$13) -> 0 | M53: =SUMIF('9月'!$F$6:$F$13,$C53,'9月'!$H$6:$H$13) -> 0 | N53: =SUMIF('10月'!$F$6:$F$13,$C53,'10月'!$H$6:$H$13) -> 0 | O53: =SUMIF('11月'!$F$6:$F$13,$C53,'11月'!$H$6:$H$13) -> 0 | P53: =SUMIF('12月'!$F$6:$F$13,$C53,'12月'!$H$6:$H$13) -> 0 | Q53: =AVERAGE(E53:P53) -> 2500 | R53: =SUM(E53:P53) -> 30000 | T53: 242000
C54: 💴 iDeCo | E54: =SUMIF('1月'!$F$6:$F$13,$C54,'1月'!$H$6:$H$13) -> 0 | F54: =SUMIF('2月'!$F$6:$F$13,$C54,'2月'!$H$6:$H$13) -> 0 | G54: =SUMIF('3月'!$F$6:$F$13,$C54,'3月'!$H$6:$H$13) -> 0 | H54: =SUMIF('4月'!$F$6:$F$13,$C54,'4月'!$H$6:$H$13) -> 0 | I54: =SUMIF('5月'!$F$6:$F$13,$C54,'5月'!$H$6:$H$13) -> 0 | J54: =SUMIF('6月'!$F$6:$F$13,$C54,'6月'!$H$6:$H$13) -> 0 | K54: =SUMIF('7月'!$F$6:$F$13,$C54,'7月'!$H$6:$H$13) -> 0 | L54: =SUMIF('8月'!$F$6:$F$13,$C54,'8月'!$H$6:$H$13) -> 0 | M54: =SUMIF('9月'!$F$6:$F$13,$C54,'9月'!$H$6:$H$13) -> 0 | N54: =SUMIF('10月'!$F$6:$F$13,$C54,'10月'!$H$6:$H$13) -> 0 | O54: =SUMIF('11月'!$F$6:$F$13,$C54,'11月'!$H$6:$H$13) -> 0 | P54: =SUMIF('12月'!$F$6:$F$13,$C54,'12月'!$H$6:$H$13) -> 0 | Q54: =AVERAGE(E54:P54) -> 0 | R54: =SUM(E54:P54) -> 0 | T54: 0.605
C55: 💴 特別費積み立て | E55: =SUMIF('1月'!$F$6:$F$13,$C55,'1月'!$H$6:$H$13) -> 30000 | F55: =SUMIF('2月'!$F$6:$F$13,$C55,'2月'!$H$6:$H$13) -> 0 | G55: =SUMIF('3月'!$F$6:$F$13,$C55,'3月'!$H$6:$H$13) -> 0 | H55: =SUMIF('4月'!$F$6:$F$13,$C55,'4月'!$H$6:$H$13) -> 0 | I55: =SUMIF('5月'!$F$6:$F$13,$C55,'5月'!$H$6:$H$13) -> 0 | J55: =SUMIF('6月'!$F$6:$F$13,$C55,'6月'!$H$6:$H$13) -> 0 | K55: =SUMIF('7月'!$F$6:$F$13,$C55,'7月'!$H$6:$H$13) -> 0 | L55: =SUMIF('8月'!$F$6:$F$13,$C55,'8月'!$H$6:$H$13) -> 0 | M55: =SUMIF('9月'!$F$6:$F$13,$C55,'9月'!$H$6:$H$13) -> 0 | N55: =SUMIF('10月'!$F$6:$F$13,$C55,'10月'!$H$6:$H$13) -> 0 | O55: =SUMIF('11月'!$F$6:$F$13,$C55,'11月'!$H$6:$H$13) -> 0 | P55: =SUMIF('12月'!$F$6:$F$13,$C55,'12月'!$H$6:$H$13) -> 0 | Q55: =AVERAGE(E55:P55) -> 2500 | R55: =SUM(E55:P55) -> 30000
C56: 💴 貯金（臨時） | E56: =SUMIF('1月'!$F$6:$F$13,$C56,'1月'!$H$6:$H$13) -> 0 | F56: =SUMIF('2月'!$F$6:$F$13,$C56,'2月'!$H$6:$H$13) -> 0 | G56: =SUMIF('3月'!$F$6:$F$13,$C56,'3月'!$H$6:$H$13) -> 0 | H56: =SUMIF('4月'!$F$6:$F$13,$C56,'4月'!$H$6:$H$13) -> 0 | I56: =SUMIF('5月'!$F$6:$F$13,$C56,'5月'!$H$6:$H$13) -> 0 | J56: =SUMIF('6月'!$F$6:$F$13,$C56,'6月'!$H$6:$H$13) -> 0 | K56: =SUMIF('7月'!$F$6:$F$13,$C56,'7月'!$H$6:$H$13) -> 0 | L56: =SUMIF('8月'!$F$6:$F$13,$C56,'8月'!$H$6:$H$13) -> 0 | M56: =SUMIF('9月'!$F$6:$F$13,$C56,'9月'!$H$6:$H$13) -> 0 | N56: =SUMIF('10月'!$F$6:$F$13,$C56,'10月'!$H$6:$H$13) -> 0 | O56: =SUMIF('11月'!$F$6:$F$13,$C56,'11月'!$H$6:$H$13) -> 0 | P56: =SUMIF('12月'!$F$6:$F$13,$C56,'12月'!$H$6:$H$13) -> 0 | Q56: =AVERAGE(E56:P56) -> 0 | R56: =SUM(E56:P56) -> 0
C57: 💴 NISA（臨時） | E57: =SUMIF('1月'!$F$6:$F$13,$C57,'1月'!$H$6:$H$13) -> 0 | F57: =SUMIF('2月'!$F$6:$F$13,$C57,'2月'!$H$6:$H$13) -> 0 | G57: =SUMIF('3月'!$F$6:$F$13,$C57,'3月'!$H$6:$H$13) -> 0 | H57: =SUMIF('4月'!$F$6:$F$13,$C57,'4月'!$H$6:$H$13) -> 0 | I57: =SUMIF('5月'!$F$6:$F$13,$C57,'5月'!$H$6:$H$13) -> 0 | J57: =SUMIF('6月'!$F$6:$F$13,$C57,'6月'!$H$6:$H$13) -> 0 | K57: =SUMIF('7月'!$F$6:$F$13,$C57,'7月'!$H$6:$H$13) -> 0 | L57: =SUMIF('8月'!$F$6:$F$13,$C57,'8月'!$H$6:$H$13) -> 0 | M57: =SUMIF('9月'!$F$6:$F$13,$C57,'9月'!$H$6:$H$13) -> 0 | N57: =SUMIF('10月'!$F$6:$F$13,$C57,'10月'!$H$6:$H$13) -> 0 | O57: =SUMIF('11月'!$F$6:$F$13,$C57,'11月'!$H$6:$H$13) -> 0 | P57: =SUMIF('12月'!$F$6:$F$13,$C57,'12月'!$H$6:$H$13) -> 0 | Q57: =AVERAGE(E57:P57) -> 0 | R57: =SUM(E57:P57) -> 0
C58: 💴 投資（臨時） | E58: =SUMIF('1月'!$F$6:$F$13,$C58,'1月'!$H$6:$H$13) -> 0 | F58: =SUMIF('2月'!$F$6:$F$13,$C58,'2月'!$H$6:$H$13) -> 0 | G58: =SUMIF('3月'!$F$6:$F$13,$C58,'3月'!$H$6:$H$13) -> 0 | H58: =SUMIF('4月'!$F$6:$F$13,$C58,'4月'!$H$6:$H$13) -> 0 | I58: =SUMIF('5月'!$F$6:$F$13,$C58,'5月'!$H$6:$H$13) -> 0 | J58: =SUMIF('6月'!$F$6:$F$13,$C58,'6月'!$H$6:$H$13) -> 0 | K58: =SUMIF('7月'!$F$6:$F$13,$C58,'7月'!$H$6:$H$13) -> 0 | L58: =SUMIF('8月'!$F$6:$F$13,$C58,'8月'!$H$6:$H$13) -> 0 | M58: =SUMIF('9月'!$F$6:$F$13,$C58,'9月'!$H$6:$H$13) -> 0 | N58: =SUMIF('10月'!$F$6:$F$13,$C58,'10月'!$H$6:$H$13) -> 0 | O58: =SUMIF('11月'!$F$6:$F$13,$C58,'11月'!$H$6:$H$13) -> 0 | P58: =SUMIF('12月'!$F$6:$F$13,$C58,'12月'!$H$6:$H$13) -> 0 | Q58: =AVERAGE(E58:P58) -> 0 | R58: =SUM(E58:P58) -> 0
C59: 💴 その他 | E59: =SUMIF('1月'!$F$6:$F$13,$C59,'1月'!$H$6:$H$13) -> 0 | F59: =SUMIF('2月'!$F$6:$F$13,$C59,'2月'!$H$6:$H$13) -> 0 | G59: =SUMIF('3月'!$F$6:$F$13,$C59,'3月'!$H$6:$H$13) -> 0 | H59: =SUMIF('4月'!$F$6:$F$13,$C59,'4月'!$H$6:$H$13) -> 0 | I59: =SUMIF('5月'!$F$6:$F$13,$C59,'5月'!$H$6:$H$13) -> 0 | J59: =SUMIF('6月'!$F$6:$F$13,$C59,'6月'!$H$6:$H$13) -> 0 | K59: =SUMIF('7月'!$F$6:$F$13,$C59,'7月'!$H$6:$H$13) -> 0 | L59: =SUMIF('8月'!$F$6:$F$13,$C59,'8月'!$H$6:$H$13) -> 0 | M59: =SUMIF('9月'!$F$6:$F$13,$C59,'9月'!$H$6:$H$13) -> 0 | N59: =SUMIF('10月'!$F$6:$F$13,$C59,'10月'!$H$6:$H$13) -> 0 | O59: =SUMIF('11月'!$F$6:$F$13,$C59,'11月'!$H$6:$H$13) -> 0 | P59: =SUMIF('12月'!$F$6:$F$13,$C59,'12月'!$H$6:$H$13) -> 0 | Q59: =AVERAGE(E59:P59) -> 0 | R59: =SUM(E59:P59) -> 0
C60: 先取り貯金・投資合計 | E60: =SUM(E52:E59) -> 80000 | F60: =SUM(F52:F59) -> 0 | G60: =SUM(G52:G59) -> 0 | H60: =SUM(H52:H59) -> 0 | I60: =SUM(I52:I59) -> 0 | J60: =SUM(J52:J59) -> 0 | K60: =SUM(K52:K59) -> 0 | L60: =SUM(L52:L59) -> 0 | ... P60: =SUM(P52:P59) -> 0 | Q60: =AVERAGE(E60:P60) -> 6666.6667 | R60: =SUM(E60:P60) -> 80000
A61: 収支 | C61: 余り貯金 （収入-先取り‐支出） | E61: =E12-E39-E60 -> 162000 | F61: =F12-F39-F60 -> 0 | G61: =G12-G39-G60 -> 0 | H61: =H12-H39-H60 -> 0 | I61: =I12-I39-I60 -> 0 | J61: =J12-J39-J60 -> 0 | K61: =K12-K39-K60 -> 0 | L61: =L12-L39-L60 -> 0 | ... P61: =P12-P39-P60 -> 0 | Q61: =AVERAGE(E61:P61) -> 13500 | R61: =SUM(E61:P61) -> 162000
C62: 貯蓄合計（先取り＋余り貯金） | E62: =E60+E61 -> 242000 | F62: =F60+F61 -> 0 | G62: =G60+G61 -> 0 | H62: =H60+H61 -> 0 | I62: =I60+I61 -> 0 | J62: =J60+J61 -> 0 | K62: =K60+K61 -> 0 | L62: =L60+L61 -> 0 | ... P62: =P60+P61 -> 0 | Q62: =AVERAGE(E62:P62) -> 20166.667 | R62: =SUM(E62:P62) -> 242000
C63: 貯蓄率（貯蓄合計/収入） | D63: 目標：20%以上 | E63: =IFERROR(E62/E12,"") -> 0.605 | F63: =IFERROR(F62/F12,"") | G63: =IFERROR(G62/G12,"") | H63: =IFERROR(H62/H12,"") | I63: =IFERROR(I62/I12,"") | J63: =IFERROR(J62/J12,"") | K63: =IFERROR(K62/K12,"") | L63: =IFERROR(L62/L12,"") | ... R63: =IFERROR(R62/R12,"") -> 0.605
A64: 1 | B64: 1 | E64: {=ByCol(E13:P63, Lambda(col, N(Sum(col)>0)))} -> 1 | F64: 0 | G64: 0 | H64: 0 | I64: 0 | J64: 0 | K64: 0 | L64: 0 | M64: 0 | N64: 0 | O64: 0 | P64: 0 | Q64: =Sum(E64:P64) -> 1

Sheet 収支可視化シート
B1: 収支可視化シート | E1: ※費目を選択すれば自動で反映されます ※1年分の家計簿を入力してから確認してください（年途中の場合は未来の家計簿を仮で作成してください）
B3: 月平均 | C3: ※毎月発生するもの
B5: 収入 | E5: 先取り貯金・投資
B6: 費目 | C6: 金額 | E6: 費目 | F6: 金額
B7: 💰 パパ給与 | C7: =SUMIF('年間推移シート'!$C$4:$C$11,B7,'年間推移シート'!$Q$4:$Q$11) -> 20833.333 | E7: 💴 貯金 | F7: =SUMIF('年間推移シート'!$C$52:$C$59,E7,'年間推移シート'!$Q$52:$Q$59) -> 1666.6667
B8: 💰 ママ給与 | C8: =SUMIF('年間推移シート'!$C$4:$C$11,B8,'年間推移シート'!$Q$4:$Q$11) -> 12500 | E8: 💴 特別費積み立て | F8: =SUMIF('年間推移シート'!$C$52:$C$59,E8,'年間推移シート'!$Q$52:$Q$59) -> 2500
C9: =SUMIF('年間推移シート'!$C$4:$C$11,B9,'年間推移シート'!$Q$4:$Q$11) -> 0 | E9: 💴 NISA | F9: =SUMIF('年間推移シート'!$C$52:$C$59,E9,'年間推移シート'!$Q$52:$Q$59) -> 2500
C10: =SUMIF('年間推移シート'!$C$4:$C$11,B10,'年間推移シート'!$Q$4:$Q$11) -> 0 | F10: =SUMIF('年間推移シート'!$C$52:$C$59,E10,'年間推移シート'!$Q$52:$Q$59) -> 0
C11: =SUMIF('年間推移シート'!$C$4:$C$11,B11,'年間推移シート'!$Q$4:$Q$11) -> 0 | F11: =SUMIF('年間推移シート'!$C$52:$C$59,E11,'年間推移シート'!$Q$52:$Q$59) -> 0
C12: =SUMIF('年間推移シート'!$C$4:$C$11,B12,'年間推移シート'!$Q$4:$Q$11) -> 0 | F12: =SUMIF('年間推移シート'!$C$52:$C$59,E12,'年間推移シート'!$Q$52:$Q$59) -> 0
C13: =SUMIF('年間推移シート'!$C$4:$C$11,B13,'年間推移シート'!$Q$4:$Q$11) -> 0 | F13: =SUMIF('年間推移シート'!$C$52:$C$59,E13,'年間推移シート'!$Q$52:$Q$59) -> 0
C14: =SUMIF('年間推移シート'!$C$4:$C$11,B14,'年間推移シート'!$Q$4:$Q$11) -> 0 | F14: =SUMIF('年間推移シート'!$C$52:$C$59,E14,'年間推移シート'!$Q$52:$Q$59) -> 0
B15: 合計 | C15: =SUM(C7:C14) -> 33333.333 | E15: 合計 | F15: =SUM(F7:F14) -> 6666.6667
B18: 支出 | E18: 支出
B19: 固定 | E19: 変動
B20: 費目 | C20: 金額 | E20: 費目 | F20: 金額
B21: 🏠 住宅 | C21: =SUMIF('年間推移シート'!$C$13:$C$24,B21,'年間推移シート'!$Q$13:$Q$24) -> 8333.3333 | E21: 🍙 食費 | F21: =SUMIF('年間推移シート'!$C$26:$C$37,E21,'年間推移シート'!$Q$26:$Q$37) -> 83.333333
B22: 💡 電気 | C22: =SUMIF('年間推移シート'!$C$13:$C$24,B22,'年間推移シート'!$Q$13:$Q$24) -> 666.66667 | E22: 🧴 日用品 | F22: =SUMIF('年間推移シート'!$C$26:$C$37,E22,'年間推移シート'!$Q$26:$Q$37) -> 0
B23: 🔥 ガス | C23: =SUMIF('年間推移シート'!$C$13:$C$24,B23,'年間推移シート'!$Q$13:$Q$24) -> 416.66667 | E23: 📒 雑費 | F23: =SUMIF('年間推移シート'!$C$26:$C$37,E23,'年間推移シート'!$Q$26:$Q$37) -> 0 | H23: 今月の収支 | I23: 金額
B24: 🚰 水道 | C24: =SUMIF('年間推移シート'!$C$13:$C$24,B24,'年間推移シート'!$Q$13:$Q$24) -> 166.66667 | E24: ⛺️ 趣味・娯楽 | F24: =SUMIF('年間推移シート'!$C$26:$C$37,E24,'年間推移シート'!$Q$26:$Q$37) -> 0 | H24: 収入（a） | I24: =C15 -> 33333.333
B25: 🎓 教養・教育 | C25: =SUMIF('年間推移シート'!$C$13:$C$24,B25,'年間推移シート'!$Q$13:$Q$24) -> 2500 | E25: 👚 衣服・美容 | F25: =SUMIF('年間推移シート'!$C$26:$C$37,E25,'年間推移シート'!$Q$26:$Q$37) -> 0 | H25: 先取り貯金・投資（b） | I25: =F15 -> 6666.6667
B26: 📱 通信費 | C26: =SUMIF('年間推移シート'!$C$13:$C$24,B26,'年間推移シート'!$Q$13:$Q$24) -> 416.66667 | E26: 🏥 健康・医療 | F26: =SUMIF('年間推移シート'!$C$26:$C$37,E26,'年間推移シート'!$Q$26:$Q$37) -> 0 | H26: 支出（c） | I26: =C33+F33 -> 13166.667
B27: 📽️ サブスク | C27: =SUMIF('年間推移シート'!$C$13:$C$24,B27,'年間推移シート'!$Q$13:$Q$24) -> 166.66667 | E27: 🍼 子ども | F27: =SUMIF('年間推移シート'!$C$26:$C$37,E27,'年間推移シート'!$Q$26:$Q$37) -> 0 | H27: 余り貯金（d）※a-b-c | I27: =I24-I25-I26 -> 13500
B28: 📃 保険 | C28: =SUMIF('年間推移シート'!$C$13:$C$24,B28,'年間推移シート'!$Q$13:$Q$24) -> 416.66667 | E28: 🍷 交際費 | F28: =SUMIF('年間推移シート'!$C$26:$C$37,E28,'年間推移シート'!$Q$26:$Q$37) -> 0 | H28: 貯蓄合計（e）※b+d | I28: =I25+I27 -> 20166.667
C29: =SUMIF('年間推移シート'!$C$13:$C$24,B29,'年間推移シート'!$Q$13:$Q$24) -> 0 | E29: 🚃 交通費 | F29: =SUMIF('年間推移シート'!$C$26:$C$37,E29,'年間推移シート'!$Q$26:$Q$37) -> 0
C30: =SUMIF('年間推移シート'!$C$13:$C$24,B30,'年間推移シート'!$Q$13:$Q$24) -> 0 | F30: =SUMIF('年間推移シート'!$C$26:$C$37,E30,'年間推移シート'!$Q$26:$Q$37) -> 0 | H30: 支出割合 （c/a)×100 | I30: 貯蓄率 （e/a)×100
C31: =SUMIF('年間推移シート'!$C$13:$C$24,B31,'年間推移シート'!$Q$13:$Q$24) -> 0 | F31: =SUMIF('年間推移シート'!$C$26:$C$37,E31,'年間推移シート'!$Q$26:$Q$37) -> 0 | H31: =I26/I24 -> 0.395 | I31: =I28/I24 -> 0.605
C32: =SUMIF('年間推移シート'!$C$13:$C$24,B32,'年間推移シート'!$Q$13:$Q$24) -> 0 | F32: =SUMIF('年間推移シート'!$C$26:$C$37,E32,'年間推移シート'!$Q$26:$Q$37) -> 0
B33: 合計 | C33: =SUM(C21:C32) -> 13083.333 | E33: 合計 | F33: =SUM(F21:F32) -> 83.333333 | H33: ↑手取りの80％以内が目安 | I33: ↑目標：20％以上
B36: 年計 | C36: ※臨時で発生するもの（特別費）
B38: 収入 | E38: 先取り貯金・投資
B39: 費目 | C39: 金額 | E39: 費目 | F39: 金額
B40: 💰 賞与 | C40: =SUMIF('年間推移シート'!$C$4:$C$11,B40,'年間推移シート'!$R$4:$R$11) -> 0 | E40: 💴 貯金（臨時） | F40: =SUMIF('年間推移シート'!$C$52:$C$59,E40,'年間推移シート'!$R$52:$R$59) -> 0
C41: =SUMIF('年間推移シート'!$C$4:$C$11,B41,'年間推移シート'!$R$4:$R$11) -> 0 | F41: =SUMIF('年間推移シート'!$C$52:$C$59,E41,'年間推移シート'!$R$52:$R$59) -> 0
C42: =SUMIF('年間推移シート'!$C$4:$C$11,B42,'年間推移シート'!$R$4:$R$11) -> 0 | F42: =SUMIF('年間推移シート'!$C$52:$C$59,E42,'年間推移シート'!$R$52:$R$59) -> 0
C43: =SUMIF('年間推移シート'!$C$4:$C$11,B43,'年間推移シート'!$R$4:$R$11) -> 0 | F43: =SUMIF('年間推移シート'!$C$52:$C$59,E43,'年間推移シート'!$R$52:$R$59) -> 0
C44: =SUMIF('年間推移シート'!$C$4:$C$11,B44,'年間推移シート'!$R$4:$R$11) -> 0 | F44: =SUMIF('年間推移シート'!$C$52:$C$59,E44,'年間推移シート'!$R$52:$R$59) -> 0
B45: 合計 | C45: =SUM(C40:C44) -> 0 | E45: 合計 | F45: =SUM(F40:F44) -> 0
B48: 支出
B49: 特別費
B50: 費目 | C50: 金額
B51: ✈️ 旅行 | C51: =SUMIF('年間推移シート'!$C$41:$C$50,B51,'年間推移シート'!$R$41:$R$50) -> 0
B52: 🍴 食事 | C52: =SUMIF('年間推移シート'!$C$41:$C$50,B52,'年間推移シート'!$R$41:$R$50) -> 12000
B53: 🏠 更新料 | C53: =SUMIF('年間推移シート'!$C$41:$C$50,B53,'年間推移シート'!$R$41:$R$50) -> 0
B54: 🗒️ 保険 | C54: =SUMIF('年間推移シート'!$C$41:$C$50,B54,'年間推移シート'!$R$41:$R$50) -> 0
B55: 📠 家具・家電 | C55: =SUMIF('年間推移シート'!$C$41:$C$50,B55,'年間推移シート'!$R$41:$R$50) -> 0
B56: ❓ その他 | C56: =SUMIF('年間推移シート'!$C$41:$C$50,B56,'年間推移シート'!$R$41:$R$50) -> 0 | H56: 年間の収支 | I56: 金額 | K56: 支出割合 （c/a)×100 | L56: 貯蓄率 （e/a)×100
C57: =SUMIF('年間推移シート'!$C$41:$C$50,B57,'年間推移シート'!$R$41:$R$50) -> 0 | H57: 収入（a） | I57: =C45 -> 0 | K57: =I59/I57 -> #DIV/0! | L57: =I61/I57 -> #DIV/0!
C58: =SUMIF('年間推移シート'!$C$41:$C$50,B58,'年間推移シート'!$R$41:$R$50) -> 0 | H58: 先取り貯金・投資（b） | I58: =F45 -> 0
C59: =SUMIF('年間推移シート'!$C$41:$C$50,B59,'年間推移シート'!$R$41:$R$50) -> 0 | H59: 支出（c） | I59: =C61 -> 12000
C60: =SUMIF('年間推移シート'!$C$41:$C$50,B60,'年間推移シート'!$R$41:$R$50) -> 0 | H60: 余り貯金（d）※a-b-c | I60: =I57-I58-I59 -> -12000
B61: 合計 | C61: =SUM(C51:C60) -> 12000 | H61: 貯蓄合計（e）※b+d | I61: =I58+I60 -> -12000
F64: {=ByCol(#REF!, Lambda(col, N(Sum(col)>0)))} -> #REF!

Sheet 特別費管理シート
B1: 特別費管理シート | E1: ※グレーのセルは自動反映します
C3: 前年からの繰越 | D3: 今年の積立金額 | G3: 予算合計 | H3: 金額 | I3: 特別費の残り
C4: 100000 | D4: ='積立管理シート'!D4 -> 30000 | G4: =D14+D23+D32+D41+D50+D59+H14+H23+H32+H41+H50+H59 -> 0 | H4: =E14+E23+E32+E41+E50+E59+I14+I23+I32+I41+I50+I59 -> 12000 | I4: =C4+D4-H4 -> 118000
B6: 1月 | C6: 内容 | D6: 予算 | E6: 金額 | F6: 7月 | G6: 内容 | H6: 予算 | I6: 金額
C7: ✈️ 旅行 | E7: =SUMIF('1月'!$B$35:$B$41,C7,'1月'!$D$35:$D$41) -> 0 | G7: ✈️ 旅行 | I7: =SUMIF('7月'!$B$35:$B$41,G7,'7月'!$D$35:$D$41) -> 0
C8: 🍴 食事 | E8: =SUMIF('1月'!$B$35:$B$41,C8,'1月'!$D$35:$D$41) -> 12000 | G8: 🍴 食事 | I8: =SUMIF('7月'!$B$35:$B$41,G8,'7月'!$D$35:$D$41) -> 0
C9: 🏠 更新料 | E9: =SUMIF('1月'!$B$35:$B$41,C9,'1月'!$D$35:$D$41) -> 0 | G9: 🏠 更新料 | I9: =SUMIF('7月'!$B$35:$B$41,G9,'7月'!$D$35:$D$41) -> 0
C10: 🗒️ 保険 | E10: =SUMIF('1月'!$B$35:$B$41,C10,'1月'!$D$35:$D$41) -> 0 | G10: 🗒️ 保険 | I10: =SUMIF('7月'!$B$35:$B$41,G10,'7月'!$D$35:$D$41) -> 0
C11: 📠 家具・家電 | E11: =SUMIF('1月'!$B$35:$B$41,C11,'1月'!$D$35:$D$41) -> 0 | G11: 📠 家具・家電 | I11: =SUMIF('7月'!$B$35:$B$41,G11,'7月'!$D$35:$D$41) -> 0
C12: 🤰🏻 妊活 | E12: =SUMIF('1月'!$B$35:$B$41,C12,'1月'!$D$35:$D$41) -> 0 | G12: 🤰🏻 妊活 | I12: =SUMIF('7月'!$B$35:$B$41,G12,'7月'!$D$35:$D$41) -> 0
C13: ❓ その他 | E13: =SUMIF('1月'!$B$35:$B$41,C13,'1月'!$D$35:$D$41) -> 0 | G13: ❓ その他 | I13: =SUMIF('7月'!$B$35:$B$41,G13,'7月'!$D$35:$D$41) -> 0
C14: 合計 | D14: =SUM(D7:D13) -> 0 | E14: =SUM(E7:E13) -> 12000 | G14: 合計 | H14: =SUM(H7:H13) -> 0 | I14: =SUM(I7:I13) -> 0
B15: 2月 | C15: 内容 | D15: 予算 | E15: 金額 | F15: 8月 | G15: 内容 | H15: 予算 | I15: 金額
C16: ✈️ 旅行 | E16: =SUMIF('2月'!$B$35:$B$41,C16,'2月'!$D$35:$D$41) -> 0 | G16: ✈️ 旅行 | I16: =SUMIF('8月'!$B$35:$B$41,G16,'8月'!$D$35:$D$41) -> 0
C17: 🍴 食事 | E17: =SUMIF('2月'!$B$35:$B$41,C17,'2月'!$D$35:$D$41) -> 0 | G17: 🍴 食事 | I17: =SUMIF('8月'!$B$35:$B$41,G17,'8月'!$D$35:$D$41) -> 0
C18: 🏠 更新料 | E18: =SUMIF('2月'!$B$35:$B$41,C18,'2月'!$D$35:$D$41) -> 0 | G18: 🏠 更新料 | I18: =SUMIF('8月'!$B$35:$B$41,G18,'8月'!$D$35:$D$41) -> 0
C19: 🗒️ 保険 | E19: =SUMIF('2月'!$B$35:$B$41,C19,'2月'!$D$35:$D$41) -> 0 | G19: 🗒️ 保険 | I19: =SUMIF('8月'!$B$35:$B$41,G19,'8月'!$D$35:$D$41) -> 0
C20: 📠 家具・家電 | E20: =SUMIF('2月'!$B$35:$B$41,C20,'2月'!$D$35:$D$41) -> 0 | G20: 📠 家具・家電 | I20: =SUMIF('8月'!$B$35:$B$41,G20,'8月'!$D$35:$D$41) -> 0
C21: 🤰🏻 妊活 | E21: =SUMIF('2月'!$B$35:$B$41,C21,'2月'!$D$35:$D$41) -> 0 | G21: 🤰🏻 妊活 | I21: =SUMIF('8月'!$B$35:$B$41,G21,'8月'!$D$35:$D$41) -> 0
C22: ❓ その他 | E22: =SUMIF('2月'!$B$35:$B$41,C22,'2月'!$D$35:$D$41) -> 0 | G22: ❓ その他 | I22: =SUMIF('8月'!$B$35:$B$41,G22,'8月'!$D$35:$D$41) -> 0
C23: 合計 | D23: =SUM(D16:D22) -> 0 | E23: =SUM(E16:E22) -> 0 | G23: 合計 | H23: =SUM(H16:H22) -> 0 | I23: =SUM(I16:I22) -> 0
B24: 3月 | C24: 内容 | D24: 予算 | E24: 金額 | F24: 9月 | G24: 内容 | H24: 予算 | I24: 金額
C25: ✈️ 旅行 | E25: =SUMIF('3月'!$B$35:$B$41,C25,'3月'!$D$35:$D$41) -> 0 | G25: ✈️ 旅行 | I25: =SUMIF('9月'!$B$35:$B$41,G25,'9月'!$D$35:$D$41) -> 0
C26: 🍴 食事 | E26: =SUMIF('3月'!$B$35:$B$41,C26,'3月'!$D$35:$D$41) -> 0 | G26: 🍴 食事 | I26: =SUMIF('9月'!$B$35:$B$41,G26,'9月'!$D$35:$D$41) -> 0
C27: 🏠 更新料 | E27: =SUMIF('3月'!$B$35:$B$41,C27,'3月'!$D$35:$D$41) -> 0 | G27: 🏠 更新料 | I27: =SUMIF('9月'!$B$35:$B$41,G27,'9月'!$D$35:$D$41) -> 0
C28: 🗒️ 保険 | E28: =SUMIF('3月'!$B$35:$B$41,C28,'3月'!$D$35:$D$41) -> 0 | G28: 🗒️ 保険 | I28: =SUMIF('9月'!$B$35:$B$41,G28,'9月'!$D$35:$D$41) -> 0
C29: 📠 家具・家電 | E29: =SUMIF('3月'!$B$35:$B$41,C29,'3月'!$D$35:$D$41) -> 0 | G29: 📠 家具・家電 | I29: =SUMIF('9月'!$B$35:$B$41,G29,'9月'!$D$35:$D$41) -> 0
C30: 🤰🏻 妊活 | E30: =SUMIF('3月'!$B$35:$B$41,C30,'3月'!$D$35:$D$41) -> 0 | G30: 🤰🏻 妊活 | I30: =SUMIF('9月'!$B$35:$B$41,G30,'9月'!$D$35:$D$41) -> 0
C31: ❓ その他 | E31: =SUMIF('3月'!$B$35:$B$41,C31,'3月'!$D$35:$D$41) -> 0 | G31: ❓ その他 | I31: =SUMIF('9月'!$B$35:$B$41,G31,'9月'!$D$35:$D$41) -> 0
C32: 合計 | D32: =SUM(D25:D31) -> 0 | E32: =SUM(E25:E31) -> 0 | G32: 合計 | H32: =SUM(H25:H31) -> 0 | I32: =SUM(I25:I31) -> 0
B33: 4月 | C33: 内容 | D33: 予算 | E33: 金額 | F33: 10月 | G33: 内容 | H33: 予算 | I33: 金額
C34: ✈️ 旅行 | E34: =SUMIF('4月'!$B$35:$B$41,C34,'4月'!$D$35:$D$41) -> 0 | G34: ✈️ 旅行 | I34: =SUMIF('10月'!$B$35:$B$41,G34,'10月'!$D$35:$D$41) -> 0
C35: 🍴 食事 | E35: =SUMIF('4月'!$B$35:$B$41,C35,'4月'!$D$35:$D$41) -> 0 | G35: 🍴 食事 | I35: =SUMIF('10月'!$B$35:$B$41,G35,'10月'!$D$35:$D$41) -> 0
C36: 🏠 更新料 | E36: =SUMIF('4月'!$B$35:$B$41,C36,'4月'!$D$35:$D$41) -> 0 | G36: 🏠 更新料 | I36: =SUMIF('10月'!$B$35:$B$41,G36,'10月'!$D$35:$D$41) -> 0
C37: 🗒️ 保険 | E37: =SUMIF('4月'!$B$35:$B$41,C37,'4月'!$D$35:$D$41) -> 0 | G37: 🗒️ 保険 | I37: =SUMIF('10月'!$B$35:$B$41,G37,'10月'!$D$35:$D$41) -> 0
C38: 📠 家具・家電 | E38: =SUMIF('4月'!$B$35:$B$41,C38,'4月'!$D$35:$D$41) -> 0 | G38: 📠 家具・家電 | I38: =SUMIF('10月'!$B$35:$B$41,G38,'10月'!$D$35:$D$41) -> 0
C39: 🤰🏻 妊活 | E39: =SUMIF('4月'!$B$35:$B$41,C39,'4月'!$D$35:$D$41) -> 0 | G39: 🤰🏻 妊活 | I39: =SUMIF('10月'!$B$35:$B$41,G39,'10月'!$D$35:$D$41) -> 0
C40: ❓ その他 | E40: =SUMIF('4月'!$B$35:$B$41,C40,'4月'!$D$35:$D$41) -> 0 | G40: ❓ その他 | I40: =SUMIF('10月'!$B$35:$B$41,G40,'10月'!$D$35:$D$41) -> 0
C41: 合計 | D41: =SUM(D34:D40) -> 0 | E41: =SUM(E34:E40) -> 0 | G41: 合計 | H41: =SUM(H34:H40) -> 0 | I41: =SUM(I34:I40) -> 0
B42: 5月 | C42: 内容 | D42: 予算 | E42: 金額 | F42: 11月 | G42: 内容 | H42: 予算 | I42: 金額
C43: ✈️ 旅行 | E43: =SUMIF('5月'!$B$35:$B$41,C43,'5月'!$D$35:$D$41) -> 0 | G43: ✈️ 旅行 | I43: =SUMIF('11月'!$B$35:$B$41,G43,'11月'!$D$35:$D$41) -> 0
C44: 🍴 食事 | E44: =SUMIF('5月'!$B$35:$B$41,C44,'5月'!$D$35:$D$41) -> 0 | G44: 🍴 食事 | I44: =SUMIF('11月'!$B$35:$B$41,G44,'11月'!$D$35:$D$41) -> 0
C45: 🏠 更新料 | E45: =SUMIF('5月'!$B$35:$B$41,C45,'5月'!$D$35:$D$41) -> 0 | G45: 🏠 更新料 | I45: =SUMIF('11月'!$B$35:$B$41,G45,'11月'!$D$35:$D$41) -> 0
C46: 🗒️ 保険 | E46: =SUMIF('5月'!$B$35:$B$41,C46,'5月'!$D$35:$D$41) -> 0 | G46: 🗒️ 保険 | I46: =SUMIF('11月'!$B$35:$B$41,G46,'11月'!$D$35:$D$41) -> 0
C47: 📠 家具・家電 | E47: =SUMIF('5月'!$B$35:$B$41,C47,'5月'!$D$35:$D$41) -> 0 | G47: 📠 家具・家電 | I47: =SUMIF('11月'!$B$35:$B$41,G47,'11月'!$D$35:$D$41) -> 0
C48: 🤰🏻 妊活 | E48: =SUMIF('5月'!$B$35:$B$41,C48,'5月'!$D$35:$D$41) -> 0 | G48: 🤰🏻 妊活 | I48: =SUMIF('11月'!$B$35:$B$41,G48,'11月'!$D$35:$D$41) -> 0
C49: ❓ その他 | E49: =SUMIF('5月'!$B$35:$B$41,C49,'5月'!$D$35:$D$41) -> 0 | G49: ❓ その他 | I49: =SUMIF('11月'!$B$35:$B$41,G49,'11月'!$D$35:$D$41) -> 0
C50: 合計 | D50: =SUM(D43:D49) -> 0 | E50: =SUM(E43:E49) -> 0 | G50: 合計 | H50: =SUM(H43:H49) -> 0 | I50: =SUM(I43:I49) -> 0
B51: 6月 | C51: 内容 | D51: 予算 | E51: 金額 | F51: 12月 | G51: 内容 | H51: 予算 | I51: 金額
C52: ✈️ 旅行 | E52: =SUMIF('6月'!$B$35:$B$41,C52,'6月'!$D$35:$D$41) -> 0 | G52: ✈️ 旅行 | I52: =SUMIF('12月'!$B$35:$B$41,G52,'12月'!$D$35:$D$41) -> 0
C53: 🍴 食事 | E53: =SUMIF('6月'!$B$35:$B$41,C53,'6月'!$D$35:$D$41) -> 0 | G53: 🍴 食事 | I53: =SUMIF('12月'!$B$35:$B$41,G53,'12月'!$D$35:$D$41) -> 0
C54: 🏠 更新料 | E54: =SUMIF('6月'!$B$35:$B$41,C54,'6月'!$D$35:$D$41) -> 0 | G54: 🏠 更新料 | I54: =SUMIF('12月'!$B$35:$B$41,G54,'12月'!$D$35:$D$41) -> 0
C55: 🗒️ 保険 | E55: =SUMIF('6月'!$B$35:$B$41,C55,'6月'!$D$35:$D$41) -> 0 | G55: 🗒️ 保険 | I55: =SUMIF('12月'!$B$35:$B$41,G55,'12月'!$D$35:$D$41) -> 0
C56: 📠 家具・家電 | E56: =SUMIF('6月'!$B$35:$B$41,C56,'6月'!$D$35:$D$41) -> 0 | G56: 📠 家具・家電 | I56: =SUMIF('12月'!$B$35:$B$41,G56,'12月'!$D$35:$D$41) -> 0
C57: 🤰🏻 妊活 | E57: =SUMIF('6月'!$B$35:$B$41,C57,'6月'!$D$35:$D$41) -> 0 | G57: 🤰🏻 妊活 | I57: =SUMIF('12月'!$B$35:$B$41,G57,'12月'!$D$35:$D$41) -> 0
C58: ❓ その他 | E58: =SUMIF('6月'!$B$35:$B$41,C58,'6月'!$D$35:$D$41) -> 0 | G58: ❓ その他 | I58: =SUMIF('12月'!$B$35:$B$41,G58,'12月'!$D$35:$D$41) -> 0
C59: 合計 | D59: =SUM(D52:D58) -> 0 | E59: =SUM(E52:E58) -> 0 | G59: 合計 | H59: =SUM(H52:H58) -> 0 | I59: =SUM(I52:I58) -> 0

Sheet 積立管理シート
B1: 積立管理シート | E1: ※グレーのセルは自動反映します
D3: 合計金額
D4: =D14+D23+D32+D41+D50+D59+G14+G23+G32+G41+G50+G59 -> 30000
B6: 1月 | C6: 内容 | D6: 金額 | E6: 7月 | F6: 内容 | G6: 金額
C7: 💴 特別費積み立て | D7: =SUMIF('1月'!$F$6:$F$13,C7,'1月'!$H$6:$H$13) -> 30000 | F7: 💴 特別費積み立て | G7: =SUMIF('7月'!$F$6:$F$13,F7,'7月'!$H$6:$H$13) -> 0
D8: =SUMIF('1月'!$F$6:$F$13,C8,'1月'!$H$6:$H$13) -> 0 | G8: =SUMIF('7月'!$F$6:$F$13,F8,'7月'!$H$6:$H$13) -> 0
D9: =SUMIF('1月'!$F$6:$F$13,C9,'1月'!$H$6:$H$13) -> 0 | G9: =SUMIF('7月'!$F$6:$F$13,F9,'7月'!$H$6:$H$13) -> 0
D10: =SUMIF('1月'!$F$6:$F$13,C10,'1月'!$H$6:$H$13) -> 0 | G10: =SUMIF('7月'!$F$6:$F$13,F10,'7月'!$H$6:$H$13) -> 0
D11: =SUMIF('1月'!$F$6:$F$13,C11,'1月'!$H$6:$H$13) -> 0 | G11: =SUMIF('7月'!$F$6:$F$13,F11,'7月'!$H$6:$H$13) -> 0
D12: =SUMIF('1月'!$F$6:$F$13,C12,'1月'!$H$6:$H$13) -> 0 | G12: =SUMIF('7月'!$F$6:$F$13,F12,'7月'!$H$6:$H$13) -> 0
D13: =SUMIF('1月'!$F$6:$F$13,C13,'1月'!$H$6:$H$13) -> 0 | G13: =SUMIF('7月'!$F$6:$F$13,F13,'7月'!$H$6:$H$13) -> 0
C14: 合計 | D14: =SUM(D7:D13) -> 30000 | F14: 合計 | G14: =SUM(G7:G13) -> 0
B15: 2月 | C15: 内容 | D15: 金額 | E15: 8月 | F15: 内容 | G15: 金額
C16: 💴 特別費積み立て | D16: =SUMIF('2月'!$F$6:$F$13,C16,'2月'!$H$6:$H$13) -> 0 | F16: 💴 特別費積み立て | G16: =SUMIF('8月'!$F$6:$F$13,F16,'8月'!$H$6:$H$13) -> 0
D17: =SUMIF('2月'!$F$6:$F$13,C17,'2月'!$H$6:$H$13) -> 0 | G17: =SUMIF('8月'!$F$6:$F$13,F17,'8月'!$H$6:$H$13) -> 0
D18: =SUMIF('2月'!$F$6:$F$13,C18,'2月'!$H$6:$H$13) -> 0 | G18: =SUMIF('8月'!$F$6:$F$13,F18,'8月'!$H$6:$H$13) -> 0
D19: =SUMIF('2月'!$F$6:$F$13,C19,'2月'!$H$6:$H$13) -> 0 | G19: =SUMIF('8月'!$F$6:$F$13,F19,'8月'!$H$6:$H$13) -> 0
D20: =SUMIF('2月'!$F$6:$F$13,C20,'2月'!$H$6:$H$13) -> 0 | G20: =SUMIF('8月'!$F$6:$F$13,F20,'8月'!$H$6:$H$13) -> 0
D21: =SUMIF('2月'!$F$6:$F$13,C21,'2月'!$H$6:$H$13) -> 0 | G21: =SUMIF('8月'!$F$6:$F$13,F21,'8月'!$H$6:$H$13) -> 0
D22: =SUMIF('2月'!$F$6:$F$13,C22,'2月'!$H$6:$H$13) -> 0 | G22: =SUMIF('8月'!$F$6:$F$13,F22,'8月'!$H$6:$H$13) -> 0
C23: 合計 | D23: =SUM(D16:D22) -> 0 | F23: 合計 | G23: =SUM(G16:G22) -> 0
B24: 3月 | C24: 内容 | D24: 金額 | E24: 9月 | F24: 内容 | G24: 金額
C25: 💴 特別費積み立て | D25: =SUMIF('3月'!$F$6:$F$13,C25,'3月'!$H$6:$H$13) -> 0 | F25: 💴 特別費積み立て | G25: =SUMIF('9月'!$F$6:$F$13,F25,'9月'!$H$6:$H$13) -> 0
D26: =SUMIF('3月'!$F$6:$F$13,C26,'3月'!$H$6:$H$13) -> 0 | G26: =SUMIF('9月'!$F$6:$F$13,F26,'9月'!$H$6:$H$13) -> 0
D27: =SUMIF('3月'!$F$6:$F$13,C27,'3月'!$H$6:$H$13) -> 0 | G27: =SUMIF('9月'!$F$6:$F$13,F27,'9月'!$H$6:$H$13) -> 0
D28: =SUMIF('3月'!$F$6:$F$13,C28,'3月'!$H$6:$H$13) -> 0 | G28: =SUMIF('9月'!$F$6:$F$13,F28,'9月'!$H$6:$H$13) -> 0
D29: =SUMIF('3月'!$F$6:$F$13,C29,'3月'!$H$6:$H$13) -> 0 | G29: =SUMIF('9月'!$F$6:$F$13,F29,'9月'!$H$6:$H$13) -> 0
D30: =SUMIF('3月'!$F$6:$F$13,C30,'3月'!$H$6:$H$13) -> 0 | G30: =SUMIF('9月'!$F$6:$F$13,F30,'9月'!$H$6:$H$13) -> 0
D31: =SUMIF('3月'!$F$6:$F$13,C31,'3月'!$H$6:$H$13) -> 0 | G31: =SUMIF('9月'!$F$6:$F$13,F31,'9月'!$H$6:$H$13) -> 0
C32: 合計 | D32: =SUM(D25:D31) -> 0 | F32: 合計 | G32: =SUM(G25:G31) -> 0
B33: 4月 | C33: 内容 | D33: 金額 | E33: 10月 | F33: 内容 | G33: 金額
C34: 💴 特別費積み立て | D34: =SUMIF('4月'!$F$6:$F$13,C34,'4月'!$H$6:$H$13) -> 0 | F34: 💴 特別費積み立て | G34: =SUMIF('10月'!$F$6:$F$13,F34,'10月'!$H$6:$H$13) -> 0
D35: =SUMIF('4月'!$F$6:$F$13,C35,'4月'!$H$6:$H$13) -> 0 | G35: =SUMIF('10月'!$F$6:$F$13,F35,'10月'!$H$6:$H$13) -> 0
D36: =SUMIF('4月'!$F$6:$F$13,C36,'4月'!$H$6:$H$13) -> 0 | G36: =SUMIF('10月'!$F$6:$F$13,F36,'10月'!$H$6:$H$13) -> 0
D37: =SUMIF('4月'!$F$6:$F$13,C37,'4月'!$H$6:$H$13) -> 0 | G37: =SUMIF('10月'!$F$6:$F$13,F37,'10月'!$H$6:$H$13) -> 0
D38: =SUMIF('4月'!$F$6:$F$13,C38,'4月'!$H$6:$H$13) -> 0 | G38: =SUMIF('10月'!$F$6:$F$13,F38,'10月'!$H$6:$H$13) -> 0
D39: =SUMIF('4月'!$F$6:$F$13,C39,'4月'!$H$6:$H$13) -> 0 | G39: =SUMIF('10月'!$F$6:$F$13,F39,'10月'!$H$6:$H$13) -> 0
D40: =SUMIF('4月'!$F$6:$F$13,C40,'4月'!$H$6:$H$13) -> 0 | G40: =SUMIF('10月'!$F$6:$F$13,F40,'10月'!$H$6:$H$13) -> 0
C41: 合計 | D41: =SUM(D34:D40) -> 0 | F41: 合計 | G41: =SUM(G34:G40) -> 0
B42: 5月 | C42: 内容 | D42: 金額 | E42: 11月 | F42: 内容 | G42: 金額
C43: 💴 特別費積み立て | D43: =SUMIF('5月'!$F$6:$F$13,C43,'5月'!$H$6:$H$13) -> 0 | F43: 💴 特別費積み立て | G43: =SUMIF('11月'!$F$6:$F$13,F43,'11月'!$H$6:$H$13) -> 0
D44: =SUMIF('5月'!$F$6:$F$13,C44,'5月'!$H$6:$H$13) -> 0 | G44: =SUMIF('11月'!$F$6:$F$13,F44,'11月'!$H$6:$H$13) -> 0
D45: =SUMIF('5月'!$F$6:$F$13,C45,'5月'!$H$6:$H$13) -> 0 | G45: =SUMIF('11月'!$F$6:$F$13,F45,'11月'!$H$6:$H$13) -> 0
D46: =SUMIF('5月'!$F$6:$F$13,C46,'5月'!$H$6:$H$13) -> 0 | G46: =SUMIF('11月'!$F$6:$F$13,F46,'11月'!$H$6:$H$13) -> 0
D47: =SUMIF('5月'!$F$6:$F$13,C47,'5月'!$H$6:$H$13) -> 0 | G47: =SUMIF('11月'!$F$6:$F$13,F47,'11月'!$H$6:$H$13) -> 0
D48: =SUMIF('5月'!$F$6:$F$13,C48,'5月'!$H$6:$H$13) -> 0 | G48: =SUMIF('11月'!$F$6:$F$13,F48,'11月'!$H$6:$H$13) -> 0
D49: =SUMIF('5月'!$F$6:$F$13,C49,'5月'!$H$6:$H$13) -> 0 | G49: =SUMIF('11月'!$F$6:$F$13,F49,'11月'!$H$6:$H$13) -> 0
C50: 合計 | D50: =SUM(D43:D49) -> 0 | F50: 合計 | G50: =SUM(G43:G49) -> 0
B51: 6月 | C51: 内容 | D51: 金額 | E51: 12月 | F51: 内容 | G51: 金額
C52: 💴 特別費積み立て | D52: =SUMIF('6月'!$F$6:$F$13,C52,'6月'!$H$6:$H$13) -> 0 | F52: 💴 特別費積み立て | G52: =SUMIF('12月'!$F$6:$F$13,F52,'12月'!$H$6:$H$13) -> 0
D53: =SUMIF('6月'!$F$6:$F$13,C53,'6月'!$H$6:$H$13) -> 0 | G53: =SUMIF('12月'!$F$6:$F$13,F53,'12月'!$H$6:$H$13) -> 0
D54: =SUMIF('6月'!$F$6:$F$13,C54,'6月'!$H$6:$H$13) -> 0 | G54: =SUMIF('12月'!$F$6:$F$13,F54,'12月'!$H$6:$H$13) -> 0
D55: =SUMIF('6月'!$F$6:$F$13,C55,'6月'!$H$6:$H$13) -> 0 | G55: =SUMIF('12月'!$F$6:$F$13,F55,'12月'!$H$6:$H$13) -> 0
D56: =SUMIF('6月'!$F$6:$F$13,C56,'6月'!$H$6:$H$13) -> 0 | G56: =SUMIF('12月'!$F$6:$F$13,F56,'12月'!$H$6:$H$13) -> 0
D57: =SUMIF('6月'!$F$6:$F$13,C57,'6月'!$H$6:$H$13) -> 0 | G57: =SUMIF('12月'!$F$6:$F$13,F57,'12月'!$H$6:$H$13) -> 0
D58: =SUMIF('6月'!$F$6:$F$13,C58,'6月'!$H$6:$H$13) -> 0 | G58: =SUMIF('12月'!$F$6:$F$13,F58,'12月'!$H$6:$H$13) -> 0
C59: 合計 | D59: =SUM(D52:D58) -> 0 | F59: 合計 | G59: =SUM(G52:G58) -> 0

Sheet 支払管理シート
B1: 支払管理シート | G1: ※グレーのセルは自動反映します
B4: 1月 | C4: 支払方法 | D4: 金額 | E4: 引落日 | F4: 引落口座 | G4: 7月 | H4: 内容 | I4: 金額 | J4: 引落日 | K4: 引落口座
C5: クレカＡ | D5: =SUMIF('1月'!$G$6:$G$13,C5,'1月'!$H$6:$H$13)+SUMIF('1月'!$C$19:$C58,C5,'1月'!$D$19:$D58)+SUMIF('1月'!$T$5:$T58,C5,'1月'!$X$5:$X58) -> 130000 | I5: =SUMIF('7月'!$G$6:$G$13,H5,'7月'!$H$6:$H$13)+SUMIF('7月'!$C$19:$C58,H5,'7月'!$D$19:$D58)+SUMIF('7月'!$T$5:$T58,H5,'7月'!$X$5:$X58) -> 0
C6: 現金 | D6: =SUMIF('1月'!$G$6:$G$13,C6,'1月'!$H$6:$H$13)+SUMIF('1月'!$C$19:$C58,C6,'1月'!$D$19:$D58)+SUMIF('1月'!$T$5:$T58,C6,'1月'!$X$5:$X58) -> 1000 | I6: =SUMIF('7月'!$G$6:$G$13,H6,'7月'!$H$6:$H$13)+SUMIF('7月'!$C$19:$C58,H6,'7月'!$D$19:$D58)+SUMIF('7月'!$T$5:$T58,H6,'7月'!$X$5:$X58) -> 0
C7: クレカＢ | D7: =SUMIF('1月'!$G$6:$G$13,C7,'1月'!$H$6:$H$13)+SUMIF('1月'!$C$19:$C58,C7,'1月'!$D$19:$D58)+SUMIF('1月'!$T$5:$T58,C7,'1月'!$X$5:$X58) -> 32000 | I7: =SUMIF('7月'!$G$6:$G$13,H7,'7月'!$H$6:$H$13)+SUMIF('7月'!$C$19:$C58,H7,'7月'!$D$19:$D58)+SUMIF('7月'!$T$5:$T58,H7,'7月'!$X$5:$X58) -> 0
C8: Ｃ銀行 | D8: =SUMIF('1月'!$G$6:$G$13,C8,'1月'!$H$6:$H$13)+SUMIF('1月'!$C$19:$C58,C8,'1月'!$D$19:$D58)+SUMIF('1月'!$T$5:$T58,C8,'1月'!$X$5:$X58) -> 7000 | I8: =SUMIF('7月'!$G$6:$G$13,H8,'7月'!$H$6:$H$13)+SUMIF('7月'!$C$19:$C58,H8,'7月'!$D$19:$D58)+SUMIF('7月'!$T$5:$T58,H8,'7月'!$X$5:$X58) -> 0
C9: Ｄ銀行 | D9: =SUMIF('1月'!$G$6:$G$13,C9,'1月'!$H$6:$H$13)+SUMIF('1月'!$C$19:$C58,C9,'1月'!$D$19:$D58)+SUMIF('1月'!$T$5:$T58,C9,'1月'!$X$5:$X58) -> 30000 | I9: =SUMIF('7月'!$G$6:$G$13,H9,'7月'!$H$6:$H$13)+SUMIF('7月'!$C$19:$C58,H9,'7月'!$D$19:$D58)+SUMIF('7月'!$T$5:$T58,H9,'7月'!$X$5:$X58) -> 0
D10: =SUMIF('1月'!$G$6:$G$13,C10,'1月'!$H$6:$H$13)+SUMIF('1月'!$C$19:$C58,C10,'1月'!$D$19:$D58)+SUMIF('1月'!$T$5:$T58,C10,'1月'!$X$5:$X58) -> 0 | I10: =SUMIF('7月'!$G$6:$G$13,H10,'7月'!$H$6:$H$13)+SUMIF('7月'!$C$19:$C58,H10,'7月'!$D$19:$D58)+SUMIF('7月'!$T$5:$T58,H10,'7月'!$X$5:$X58) -> 0
D11: =SUMIF('1月'!$G$6:$G$13,C11,'1月'!$H$6:$H$13)+SUMIF('1月'!$C$19:$C58,C11,'1月'!$D$19:$D58)+SUMIF('1月'!$T$5:$T58,C11,'1月'!$X$5:$X58) -> 0 | I11: =SUMIF('7月'!$G$6:$G$13,H11,'7月'!$H$6:$H$13)+SUMIF('7月'!$C$19:$C58,H11,'7月'!$D$19:$D58)+SUMIF('7月'!$T$5:$T58,H11,'7月'!$X$5:$X58) -> 0
C12: 合計 | D12: =SUM(D5:D11) -> 200000 | H12: 合計 | I12: =SUM(I5:I11) -> 0
B13: 2月 | C13: 内容 | D13: 金額 | E13: 引落日 | F13: 引落口座 | G13: 8月 | H13: 内容 | I13: 金額 | J13: 引落日 | K13: 引落口座
D14: =SUMIF('2月'!$G$6:$G$13,C14,'2月'!$H$6:$H$13)+SUMIF('2月'!$C$19:$C58,C14,'2月'!$D$19:$D58)+SUMIF('2月'!$T$5:$T58,C14,'2月'!$X$5:$X58) -> 0 | I14: =SUMIF('8月'!$G$6:$G$13,H14,'8月'!$H$6:$H$13)+SUMIF('8月'!$C$19:$C58,H14,'8月'!$D$19:$D58)+SUMIF('8月'!$T$5:$T58,H14,'8月'!$X$5:$X58) -> 0
D15: =SUMIF('2月'!$G$6:$G$13,C15,'2月'!$H$6:$H$13)+SUMIF('2月'!$C$19:$C58,C15,'2月'!$D$19:$D58)+SUMIF('2月'!$T$5:$T58,C15,'2月'!$X$5:$X58) -> 0 | I15: =SUMIF('8月'!$G$6:$G$13,H15,'8月'!$H$6:$H$13)+SUMIF('8月'!$C$19:$C58,H15,'8月'!$D$19:$D58)+SUMIF('8月'!$T$5:$T58,H15,'8月'!$X$5:$X58) -> 0
D16: =SUMIF('2月'!$G$6:$G$13,C16,'2月'!$H$6:$H$13)+SUMIF('2月'!$C$19:$C58,C16,'2月'!$D$19:$D58)+SUMIF('2月'!$T$5:$T58,C16,'2月'!$X$5:$X58) -> 0 | I16: =SUMIF('8月'!$G$6:$G$13,H16,'8月'!$H$6:$H$13)+SUMIF('8月'!$C$19:$C58,H16,'8月'!$D$19:$D58)+SUMIF('8月'!$T$5:$T58,H16,'8月'!$X$5:$X58) -> 0
D17: =SUMIF('2月'!$G$6:$G$13,C17,'2月'!$H$6:$H$13)+SUMIF('2月'!$C$19:$C58,C17,'2月'!$D$19:$D58)+SUMIF('2月'!$T$5:$T58,C17,'2月'!$X$5:$X58) -> 0 | I17: =SUMIF('8月'!$G$6:$G$13,H17,'8月'!$H$6:$H$13)+SUMIF('8月'!$C$19:$C58,H17,'8月'!$D$19:$D58)+SUMIF('8月'!$T$5:$T58,H17,'8月'!$X$5:$X58) -> 0
D18: =SUMIF('2月'!$G$6:$G$13,C18,'2月'!$H$6:$H$13)+SUMIF('2月'!$C$19:$C58,C18,'2月'!$D$19:$D58)+SUMIF('2月'!$T$5:$T58,C18,'2月'!$X$5:$X58) -> 0 | I18: =SUMIF('8月'!$G$6:$G$13,H18,'8月'!$H$6:$H$13)+SUMIF('8月'!$C$19:$C58,H18,'8月'!$D$19:$D58)+SUMIF('8月'!$T$5:$T58,H18,'8月'!$X$5:$X58) -> 0
D19: =SUMIF('2月'!$G$6:$G$13,C19,'2月'!$H$6:$H$13)+SUMIF('2月'!$C$19:$C58,C19,'2月'!$D$19:$D58)+SUMIF('2月'!$T$5:$T58,C19,'2月'!$X$5:$X58) -> 0 | I19: =SUMIF('8月'!$G$6:$G$13,H19,'8月'!$H$6:$H$13)+SUMIF('8月'!$C$19:$C58,H19,'8月'!$D$19:$D58)+SUMIF('8月'!$T$5:$T58,H19,'8月'!$X$5:$X58) -> 0
D20: =SUMIF('2月'!$G$6:$G$13,C20,'2月'!$H$6:$H$13)+SUMIF('2月'!$C$19:$C58,C20,'2月'!$D$19:$D58)+SUMIF('2月'!$T$5:$T58,C20,'2月'!$X$5:$X58) -> 0 | I20: =SUMIF('8月'!$G$6:$G$13,H20,'8月'!$H$6:$H$13)+SUMIF('8月'!$C$19:$C58,H20,'8月'!$D$19:$D58)+SUMIF('8月'!$T$5:$T58,H20,'8月'!$X$5:$X58) -> 0
C21: 合計 | D21: =SUM(D14:D20) -> 0 | H21: 合計 | I21: =SUM(I14:I20) -> 0
B22: 3月 | C22: 内容 | D22: 金額 | E22: 引落日 | F22: 引落口座 | G22: 9月 | H22: 内容 | I22: 金額 | J22: 引落日 | K22: 引落口座
D23: =SUMIF('3月'!$G$6:$G$13,C23,'3月'!$H$6:$H$13)+SUMIF('3月'!$C$19:$C58,C23,'3月'!$D$19:$D58)+SUMIF('3月'!$T$5:$T58,C23,'3月'!$X$5:$X58) -> 0 | I23: =SUMIF('9月'!$G$6:$G$13,H23,'9月'!$H$6:$H$13)+SUMIF('9月'!$C$19:$C58,H23,'9月'!$D$19:$D58)+SUMIF('9月'!$T$5:$T58,H23,'9月'!$X$5:$X58) -> 0
D24: =SUMIF('3月'!$G$6:$G$13,C24,'3月'!$H$6:$H$13)+SUMIF('3月'!$C$19:$C58,C24,'3月'!$D$19:$D58)+SUMIF('3月'!$T$5:$T58,C24,'3月'!$X$5:$X58) -> 0 | I24: =SUMIF('9月'!$G$6:$G$13,H24,'9月'!$H$6:$H$13)+SUMIF('9月'!$C$19:$C58,H24,'9月'!$D$19:$D58)+SUMIF('9月'!$T$5:$T58,H24,'9月'!$X$5:$X58) -> 0
D25: =SUMIF('3月'!$G$6:$G$13,C25,'3月'!$H$6:$H$13)+SUMIF('3月'!$C$19:$C58,C25,'3月'!$D$19:$D58)+SUMIF('3月'!$T$5:$T58,C25,'3月'!$X$5:$X58) -> 0 | I25: =SUMIF('9月'!$G$6:$G$13,H25,'9月'!$H$6:$H$13)+SUMIF('9月'!$C$19:$C58,H25,'9月'!$D$19:$D58)+SUMIF('9月'!$T$5:$T58,H25,'9月'!$X$5:$X58) -> 0
D26: =SUMIF('3月'!$G$6:$G$13,C26,'3月'!$H$6:$H$13)+SUMIF('3月'!$C$19:$C58,C26,'3月'!$D$19:$D58)+SUMIF('3月'!$T$5:$T58,C26,'3月'!$X$5:$X58) -> 0 | I26: =SUMIF('9月'!$G$6:$G$13,H26,'9月'!$H$6:$H$13)+SUMIF('9月'!$C$19:$C58,H26,'9月'!$D$19:$D58)+SUMIF('9月'!$T$5:$T58,H26,'9月'!$X$5:$X58) -> 0
D27: =SUMIF('3月'!$G$6:$G$13,C27,'3月'!$H$6:$H$13)+SUMIF('3月'!$C$19:$C58,C27,'3月'!$D$19:$D58)+SUMIF('3月'!$T$5:$T58,C27,'3月'!$X$5:$X58) -> 0 | I27: =SUMIF('9月'!$G$6:$G$13,H27,'9月'!$H$6:$H$13)+SUMIF('9月'!$C$19:$C58,H27,'9月'!$D$19:$D58)+SUMIF('9月'!$T$5:$T58,H27,'9月'!$X$5:$X58) -> 0
D28: =SUMIF('3月'!$G$6:$G$13,C28,'3月'!$H$6:$H$13)+SUMIF('3月'!$C$19:$C58,C28,'3月'!$D$19:$D58)+SUMIF('3月'!$T$5:$T58,C28,'3月'!$X$5:$X58) -> 0 | I28: =SUMIF('9月'!$G$6:$G$13,H28,'9月'!$H$6:$H$13)+SUMIF('9月'!$C$19:$C58,H28,'9月'!$D$19:$D58)+SUMIF('9月'!$T$5:$T58,H28,'9月'!$X$5:$X58) -> 0
D29: =SUMIF('3月'!$G$6:$G$13,C29,'3月'!$H$6:$H$13)+SUMIF('3月'!$C$19:$C58,C29,'3月'!$D$19:$D58)+SUMIF('3月'!$T$5:$T58,C29,'3月'!$X$5:$X58) -> 0 | I29: =SUMIF('9月'!$G$6:$G$13,H29,'9月'!$H$6:$H$13)+SUMIF('9月'!$C$19:$C58,H29,'9月'!$D$19:$D58)+SUMIF('9月'!$T$5:$T58,H29,'9月'!$X$5:$X58) -> 0
C30: 合計 | D30: =SUM(D23:D29) -> 0 | H30: 合計 | I30: =SUM(I23:I29) -> 0
B31: 4月 | C31: 内容 | D31: 金額 | E31: 引落日 | F31: 引落口座 | G31: 10月 | H31: 内容 | I31: 金額 | J31: 引落日 | K31: 引落口座
D32: =SUMIF('4月'!$G$6:$G$13,C32,'4月'!$H$6:$H$13)+SUMIF('4月'!$C$19:$C58,C32,'4月'!$D$19:$D58)+SUMIF('4月'!$T$5:$T58,C32,'4月'!$X$5:$X58) -> 0 | I32: =SUMIF('10月'!$G$6:$G$13,H32,'10月'!$H$6:$H$13)+SUMIF('10月'!$C$19:$C58,H32,'10月'!$D$19:$D58)+SUMIF('10月'!$T$5:$T58,H32,'10月'!$X$5:$X58) -> 0
D33: =SUMIF('4月'!$G$6:$G$13,C33,'4月'!$H$6:$H$13)+SUMIF('4月'!$C$19:$C58,C33,'4月'!$D$19:$D58)+SUMIF('4月'!$T$5:$T58,C33,'4月'!$X$5:$X58) -> 0 | I33: =SUMIF('10月'!$G$6:$G$13,H33,'10月'!$H$6:$H$13)+SUMIF('10月'!$C$19:$C58,H33,'10月'!$D$19:$D58)+SUMIF('10月'!$T$5:$T58,H33,'10月'!$X$5:$X58) -> 0
D34: =SUMIF('4月'!$G$6:$G$13,C34,'4月'!$H$6:$H$13)+SUMIF('4月'!$C$19:$C58,C34,'4月'!$D$19:$D58)+SUMIF('4月'!$T$5:$T58,C34,'4月'!$X$5:$X58) -> 0 | I34: =SUMIF('10月'!$G$6:$G$13,H34,'10月'!$H$6:$H$13)+SUMIF('10月'!$C$19:$C58,H34,'10月'!$D$19:$D58)+SUMIF('10月'!$T$5:$T58,H34,'10月'!$X$5:$X58) -> 0
D35: =SUMIF('4月'!$G$6:$G$13,C35,'4月'!$H$6:$H$13)+SUMIF('4月'!$C$19:$C58,C35,'4月'!$D$19:$D58)+SUMIF('4月'!$T$5:$T58,C35,'4月'!$X$5:$X58) -> 0 | I35: =SUMIF('10月'!$G$6:$G$13,H35,'10月'!$H$6:$H$13)+SUMIF('10月'!$C$19:$C58,H35,'10月'!$D$19:$D58)+SUMIF('10月'!$T$5:$T58,H35,'10月'!$X$5:$X58) -> 0
D36: =SUMIF('4月'!$G$6:$G$13,C36,'4月'!$H$6:$H$13)+SUMIF('4月'!$C$19:$C58,C36,'4月'!$D$19:$D58)+SUMIF('4月'!$T$5:$T58,C36,'4月'!$X$5:$X58) -> 0 | I36: =SUMIF('10月'!$G$6:$G$13,H36,'10月'!$H$6:$H$13)+SUMIF('10月'!$C$19:$C58,H36,'10月'!$D$19:$D58)+SUMIF('10月'!$T$5:$T58,H36,'10月'!$X$5:$X58) -> 0
D37: =SUMIF('4月'!$G$6:$G$13,C37,'4月'!$H$6:$H$13)+SUMIF('4月'!$C$19:$C58,C37,'4月'!$D$19:$D58)+SUMIF('4月'!$T$5:$T58,C37,'4月'!$X$5:$X58) -> 0 | I37: =SUMIF('10月'!$G$6:$G$13,H37,'10月'!$H$6:$H$13)+SUMIF('10月'!$C$19:$C58,H37,'10月'!$D$19:$D58)+SUMIF('10月'!$T$5:$T58,H37,'10月'!$X$5:$X58) -> 0
D38: =SUMIF('4月'!$G$6:$G$13,C38,'4月'!$H$6:$H$13)+SUMIF('4月'!$C$19:$C58,C38,'4月'!$D$19:$D58)+SUMIF('4月'!$T$5:$T58,C38,'4月'!$X$5:$X58) -> 0 | I38: =SUMIF('10月'!$G$6:$G$13,H38,'10月'!$H$6:$H$13)+SUMIF('10月'!$C$19:$C58,H38,'10月'!$D$19:$D58)+SUMIF('10月'!$T$5:$T58,H38,'10月'!$X$5:$X58) -> 0
C39: 合計 | D39: =SUM(D32:D38) -> 0 | H39: 合計 | I39: =SUM(I32:I38) -> 0
B40: 5月 | C40: 内容 | D40: 金額 | E40: 引落日 | F40: 引落口座 | G40: 11月 | H40: 内容 | I40: 金額 | J40: 引落日 | K40: 引落口座
D41: =SUMIF('5月'!$G$6:$G$13,C41,'5月'!$H$6:$H$13)+SUMIF('5月'!$C$19:$C58,C41,'5月'!$D$19:$D58)+SUMIF('5月'!$T$5:$T58,C41,'5月'!$X$5:$X58) -> 0 | I41: =SUMIF('11月'!$G$6:$G$13,H41,'11月'!$H$6:$H$13)+SUMIF('11月'!$C$19:$C58,H41,'11月'!$D$19:$D58)+SUMIF('11月'!$T$5:$T58,H41,'11月'!$X$5:$X58) -> 0
D42: =SUMIF('5月'!$G$6:$G$13,C42,'5月'!$H$6:$H$13)+SUMIF('5月'!$C$19:$C58,C42,'5月'!$D$19:$D58)+SUMIF('5月'!$T$5:$T58,C42,'5月'!$X$5:$X58) -> 0 | I42: =SUMIF('11月'!$G$6:$G$13,H42,'11月'!$H$6:$H$13)+SUMIF('11月'!$C$19:$C58,H42,'11月'!$D$19:$D58)+SUMIF('11月'!$T$5:$T58,H42,'11月'!$X$5:$X58) -> 0
D43: =SUMIF('5月'!$G$6:$G$13,C43,'5月'!$H$6:$H$13)+SUMIF('5月'!$C$19:$C58,C43,'5月'!$D$19:$D58)+SUMIF('5月'!$T$5:$T58,C43,'5月'!$X$5:$X58) -> 0 | I43: =SUMIF('11月'!$G$6:$G$13,H43,'11月'!$H$6:$H$13)+SUMIF('11月'!$C$19:$C58,H43,'11月'!$D$19:$D58)+SUMIF('11月'!$T$5:$T58,H43,'11月'!$X$5:$X58) -> 0
D44: =SUMIF('5月'!$G$6:$G$13,C44,'5月'!$H$6:$H$13)+SUMIF('5月'!$C$19:$C58,C44,'5月'!$D$19:$D58)+SUMIF('5月'!$T$5:$T58,C44,'5月'!$X$5:$X58) -> 0 | I44: =SUMIF('11月'!$G$6:$G$13,H44,'11月'!$H$6:$H$13)+SUMIF('11月'!$C$19:$C58,H44,'11月'!$D$19:$D58)+SUMIF('11月'!$T$5:$T58,H44,'11月'!$X$5:$X58) -> 0
D45: =SUMIF('5月'!$G$6:$G$13,C45,'5月'!$H$6:$H$13)+SUMIF('5月'!$C$19:$C58,C45,'5月'!$D$19:$D58)+SUMIF('5月'!$T$5:$T58,C45,'5月'!$X$5:$X58) -> 0 | I45: =SUMIF('11月'!$G$6:$G$13,H45,'11月'!$H$6:$H$13)+SUMIF('11月'!$C$19:$C58,H45,'11月'!$D$19:$D58)+SUMIF('11月'!$T$5:$T58,H45,'11月'!$X$5:$X58) -> 0
D46: =SUMIF('5月'!$G$6:$G$13,C46,'5月'!$H$6:$H$13)+SUMIF('5月'!$C$19:$C58,C46,'5月'!$D$19:$D58)+SUMIF('5月'!$T$5:$T58,C46,'5月'!$X$5:$X58) -> 0 | I46: =SUMIF('11月'!$G$6:$G$13,H46,'11月'!$H$6:$H$13)+SUMIF('11月'!$C$19:$C58,H46,'11月'!$D$19:$D58)+SUMIF('11月'!$T$5:$T58,H46,'11月'!$X$5:$X58) -> 0
D47: =SUMIF('5月'!$G$6:$G$13,C47,'5月'!$H$6:$H$13)+SUMIF('5月'!$C$19:$C58,C47,'5月'!$D$19:$D58)+SUMIF('5月'!$T$5:$T58,C47,'5月'!$X$5:$X58) -> 0 | I47: =SUMIF('11月'!$G$6:$G$13,H47,'11月'!$H$6:$H$13)+SUMIF('11月'!$C$19:$C58,H47,'11月'!$D$19:$D58)+SUMIF('11月'!$T$5:$T58,H47,'11月'!$X$5:$X58) -> 0
C48: 合計 | D48: =SUM(D41:D47) -> 0 | H48: 合計 | I48: =SUM(I41:I47) -> 0
B49: 6月 | C49: 内容 | D49: 金額 | E49: 引落日 | F49: 引落口座 | G49: 12月 | H49: 内容 | I49: 金額 | J49: 引落日 | K49: 引落口座
D50: =SUMIF('6月'!$G$6:$G$13,C50,'6月'!$H$6:$H$13)+SUMIF('6月'!$C$19:$C58,C50,'6月'!$D$19:$D58)+SUMIF('6月'!$T$5:$T58,C50,'6月'!$X$5:$X58) -> 0 | I50: =SUMIF('12月'!$G$6:$G$13,H50,'12月'!$H$6:$H$13)+SUMIF('12月'!$C$19:$C58,H50,'12月'!$D$19:$D58)+SUMIF('12月'!$T$5:$T58,H50,'12月'!$X$5:$X58) -> 0
D51: =SUMIF('6月'!$G$6:$G$13,C51,'6月'!$H$6:$H$13)+SUMIF('6月'!$C$19:$C58,C51,'6月'!$D$19:$D58)+SUMIF('6月'!$T$5:$T58,C51,'6月'!$X$5:$X58) -> 0 | I51: =SUMIF('12月'!$G$6:$G$13,H51,'12月'!$H$6:$H$13)+SUMIF('12月'!$C$19:$C58,H51,'12月'!$D$19:$D58)+SUMIF('12月'!$T$5:$T58,H51,'12月'!$X$5:$X58) -> 0
D52: =SUMIF('6月'!$G$6:$G$13,C52,'6月'!$H$6:$H$13)+SUMIF('6月'!$C$19:$C58,C52,'6月'!$D$19:$D58)+SUMIF('6月'!$T$5:$T58,C52,'6月'!$X$5:$X58) -> 0 | I52: =SUMIF('12月'!$G$6:$G$13,H52,'12月'!$H$6:$H$13)+SUMIF('12月'!$C$19:$C58,H52,'12月'!$D$19:$D58)+SUMIF('12月'!$T$5:$T58,H52,'12月'!$X$5:$X58) -> 0
D53: =SUMIF('6月'!$G$6:$G$13,C53,'6月'!$H$6:$H$13)+SUMIF('6月'!$C$19:$C58,C53,'6月'!$D$19:$D58)+SUMIF('6月'!$T$5:$T58,C53,'6月'!$X$5:$X58) -> 0 | I53: =SUMIF('12月'!$G$6:$G$13,H53,'12月'!$H$6:$H$13)+SUMIF('12月'!$C$19:$C58,H53,'12月'!$D$19:$D58)+SUMIF('12月'!$T$5:$T58,H53,'12月'!$X$5:$X58) -> 0
D54: =SUMIF('6月'!$G$6:$G$13,C54,'6月'!$H$6:$H$13)+SUMIF('6月'!$C$19:$C58,C54,'6月'!$D$19:$D58)+SUMIF('6月'!$T$5:$T58,C54,'6月'!$X$5:$X58) -> 0 | I54: =SUMIF('12月'!$G$6:$G$13,H54,'12月'!$H$6:$H$13)+SUMIF('12月'!$C$19:$C58,H54,'12月'!$D$19:$D58)+SUMIF('12月'!$T$5:$T58,H54,'12月'!$X$5:$X58) -> 0
D55: =SUMIF('6月'!$G$6:$G$13,C55,'6月'!$H$6:$H$13)+SUMIF('6月'!$C$19:$C58,C55,'6月'!$D$19:$D58)+SUMIF('6月'!$T$5:$T58,C55,'6月'!$X$5:$X58) -> 0 | I55: =SUMIF('12月'!$G$6:$G$13,H55,'12月'!$H$6:$H$13)+SUMIF('12月'!$C$19:$C58,H55,'12月'!$D$19:$D58)+SUMIF('12月'!$T$5:$T58,H55,'12月'!$X$5:$X58) -> 0
D56: =SUMIF('6月'!$G$6:$G$13,C56,'6月'!$H$6:$H$13)+SUMIF('6月'!$C$19:$C58,C56,'6月'!$D$19:$D58)+SUMIF('6月'!$T$5:$T58,C56,'6月'!$X$5:$X58) -> 0 | I56: =SUMIF('12月'!$G$6:$G$13,H56,'12月'!$H$6:$H$13)+SUMIF('12月'!$C$19:$C58,H56,'12月'!$D$19:$D58)+SUMIF('12月'!$T$5:$T58,H56,'12月'!$X$5:$X58) -> 0
C57: 合計 | D57: =SUM(D50:D56) -> 0 | H57: 合計 | I57: =SUM(I50:I56) -> 0

Sheet list
A1: 収入 | B1: 先取り貯金 | C1: 支出 | D1: 特別費 | E1: 満足度 | F1: 支払方法
A2: 💰 パパ給与 | B2: 💴 貯金 | C2: 🍙 食費 | D2: ✈️ 旅行 | E2: 〇 | F2: クレカＡ
A3: 💰 ママ給与 | B3: 💴 特別費積み立て | C3: 🧴 日用品 | D3: 🍴 食事 | E3: △ | F3: クレカＢ
A4: 💰 副業 | B4: 💴 NISA | C4: 📒 雑費 | D4: 🏠 更新料 | E4: ✕ | F4: Ｃ銀行
A5: 💰 配当金 | B5: 💴 投資 | C5: ⛺️ 趣味・娯楽 | D5: 🗒️ 保険 | F5: Ｄ銀行
A6: 💰 賞与 | B6: 💴 iDeCo | C6: 🍷 交際費 | D6: 📠 家具・家電 | F6: 現金
A7: 💰 臨時収入 | B7: 💴 貯金（臨時） | C7: 👚 衣服・美容 | D7: 🤰🏻 妊活
A8: 💰 児童手当 | B8: 💴 NISA（臨時） | C8: 🏥 健康・医療 | D8: ❓ その他
A9: 💰 配当金 | B9: 💴 投資（臨時） | C9: 🍼 子ども
A10: 💰 その他 | B10: 💴 その他 | C10: 🚃 交通費
C11: 🏠 住宅
C12: 💡 電気
C13: 🔥 ガス
C14: 🚰 水道
C15: 📱 通信費
C16: 📽️ サブスク
C17: 📃 保険
C18: 🚙 自動車
C19: 🎓 教養・教育
C20: 💳 現金・カード
C21: 💪 自己投資
C22: 👨🏻 パパお小遣い
... C24: ❓ その他
