Workbook

Sheet ✊自己実現
A1: 🌸自己実現シート【自分軸を整えて夢を叶える🌷】
B3: 🌸人生で叶えたい夢や目標はありますか？
B7: 🌸理想とする暮らしや、自分の姿はありますか？
A8: 5年後
A9: 10年後
A10: 20年後
A11: 老後
B13: 🌸過去、満足度の高かった＆低かった買い物や体験を記入してみましょう！
A14: 満足度 高い
A15: 満足度 低い
B17: 🌸ストレスがたまった時お金を使って発散することがありますか？ あれば過去支払ったものを記入しましょう！
B20: 🌸予算オーバーしがちな項目に対して、『お買い物のマイルール』を決めましょう！

Sheet 👪目標
A1: 🌸目標管理シート【ライフイベントの支出に備える】
A3: 💡人生における大きい支出に備えるため、目標額を決めておきましょう♪
A4: セルは自由に編集OK
A5: （不要な項目はスキップしてください）
B7: （〇万円） | C7: （〇年）
A8: 結婚 | B8: 目標金額 | C8: いつまでに
A9: 式場代
A11: 教育 | B11: 目標金額 | C11: いつまでに
A12: 子ども①人目
A13: 子ども②人目
A14: 子ども③人目
A15: 子ども④人目
A17: 住宅 | B17: 目標金額 | C17: いつまでに
A18: 引っ越し代
A19: 家具代
A21: 老後 | B21: 目標金額 | C21: いつまでに
A22: 夫
A23: 妻
A25: その他 | B25: 目標金額 | C25: いつまでに
A29: ※その他は、上記の項目以外で何かある場合は記入してください。

Sheet 👂ヒアリング
A1: 🌸ヒアリングシート
B3: 🌷保険一覧（現在入っている保険をすべて記入）
A4: 下に入力項目が続きます↓ | B4: 保険会社 | C4: 保険商品名 | D4: 料金 | E4: 見直しが 可能OR不可能？ | F4: 保険内容（年金や満期の受取額があれば何歳からいくらもらえるのかも記入）
D14: =SUM(D5:D13) -> 0
B16: 🌷サブスク一覧 | D16: 🌷通信費一覧（WIFI、スマホ）
B17: サブスク名 | C17: 料金 | D17: 通信会社 | E17: 料金
B27: 合計 | C27: =SUM(C18:C26) -> 0 | D27: 合計 | E27: =SUM(E18:E26) -> 0
B29: 🌷毎月の支払い金額（ご自身の家計簿と照らし合わせて項目を変更してください） | H29: ここは未記入で大丈夫です！
B30: 支出 | C30: 月額 | D30: 見直しが 可能OR不可能？ | E30: 理想の金額 | H30: 年額
B31: 家賃・住宅ローン | C31: 0 | D31: 可能 | E31: 0 | H31: =C31*12 -> 0
B32: 住宅管理費 | C32: 0 | D32: 不可能 | E32: 0 | H32: =C32*12 -> 0
B33: 車両ローン | C33: 0 | E33: 0 | H33: =C33*12 -> 0
B34: 駐車場代 | C34: 0 | E34: 0 | H34: =C34*12 -> 0
B35: テレビ契約料 | C35: 0 | E35: 0 | H35: =C35*12 -> 0
B36: 教育 | C36: 0 | E36: 0 | H36: =C36*12 -> 0
B37: 定期代 | C37: 0 | E37: 0 | H37: =C37*12 -> 0
B38: 食費 | C38: 0 | E38: 0 | H38: =C38*12 -> 0
B39: 水道光熱費 | C39: 0 | E39: 0 | H39: =C39*12 -> 0
B40: 日用品 | C40: 0 | E40: 0 | H40: =C40*12 -> 0
B41: 趣味・娯楽 | C41: 0 | E41: 0 | H41: =C41*12 -> 0
B42: 衣類・美容 | C42: 0 | E42: 0 | H42: =C42*12 -> 0
B43: 健康・医療費 | C43: 0 | E43: 0 | H43: =C43*12 -> 0
B44: 交際費 | C44: 0 | E44: 0 | H44: =C44*12 -> 0
... B46: ガソリン代 | C46: 0 | E46: 0 | H46: =C46*12 -> 0
C47: 0 | E47: 0 | H47: =C47*12 -> 0
C48: 0 | E48: 0 | H48: =C48*12 -> 0
C49: 0 | E49: 0 | H49: =C49*12 -> 0
C50: 0 | E50: 0 | H50: =C50*12 -> 0
B52: 🌷現在の投資額一覧（新NISA、IDECO、企業型確定拠出年金など）
B53: 銘柄 | C53: 月の積立額 | D53: 一括投資した額
B54: NISA
B55: NISA
B56: IDECO
B57: IDECO
B58: 企業型確定拠出年金
B59: 企業型確定拠出年金
B72: 合計 | C72: =SUM(C54:C62) -> 0 | D72: =SUM(D54:D62) -> 0
B75: 🌷ご家族の年齢と年収（手取り）ライフプラン表で活用します/
B76: 家族のお名前 | C76: 今年度の年齢 お子さんは 今年度の学年も | D76: 手取り年収
B77: 夫・一郎 | C77: 45歳 | D77: 500
B83: ※ライフプラン表作成のため、お子さんを望まれている場合は、 将来のお子さんのご予定（希望の人数分）もご入力お願いします
B85: 🌷現在の貯金額（現金） | C85: ※ライフプランシートで活用します

Sheet 🌷ライププラン
A1: 🌸ライフプラン表（万円）
C4: 年 | F4: 2025 | G4: =F4+1 -> 2026 | H4: =G4+1 -> 2027 | I4: =H4+1 -> 2028 | J4: =I4+1 -> 2029 | K4: =J4+1 -> 2030 | L4: =K4+1 -> 2031 | M4: =L4+1 -> 2032 | N4: =M4+1 -> 2033 | ... BK4: =BJ4+1 -> 2082
C5: 経過年数 | F5: 1 | G5: =F5+1 -> 2 | H5: =G5+1 -> 3 | I5: =H5+1 -> 4 | J5: =I5+1 -> 5 | K5: =J5+1 -> 6 | L5: =K5+1 -> 7 | M5: =L5+1 -> 8 | N5: =M5+1 -> 9 | ... BK5: =BJ5+1 -> 58
C6: 夫 | D6: の年齢 | F6: 40 | G6: =F6+1 -> 41 | H6: =G6+1 -> 42 | I6: =H6+1 -> 43 | J6: =I6+1 -> 44 | K6: =J6+1 -> 45 | L6: =K6+1 -> 46 | M6: =L6+1 -> 47 | N6: =M6+1 -> 48 | ... BK6: =BJ6+1 -> 97
C7: イベント | AE7: 退職
C8: 妻 | D8: の年齢 | F8: 33 | G8: =F8+1 -> 34 | H8: =G8+1 -> 35 | I8: =H8+1 -> 36 | J8: =I8+1 -> 37 | K8: =J8+1 -> 38 | L8: =K8+1 -> 39 | M8: =L8+1 -> 40 | N8: =M8+1 -> 41 | ... BK8: =BJ8+1 -> 90
C9: イベント
C10: 子ども | D10: の年齢 | F10: 6 | G10: =F10+1 -> 7 | H10: =G10+1 -> 8 | I10: =H10+1 -> 9 | J10: =I10+1 -> 10 | K10: =J10+1 -> 11 | L10: =K10+1 -> 12 | M10: =L10+1 -> 13 | N10: =M10+1 -> 14 | ... BK10: =BJ10+1 -> 63
C11: イベント
C12: 子ども | D12: の年齢 | F12: 4 | G12: =F12+1 -> 5 | H12: =G12+1 -> 6 | I12: =H12+1 -> 7 | J12: =I12+1 -> 8 | K12: =J12+1 -> 9 | L12: =K12+1 -> 10 | M12: =L12+1 -> 11 | N12: =M12+1 -> 12 | ... BK12: =BJ12+1 -> 61
C13: イベント
C14: 子ども | D14: の年齢 | F14: 1 | G14: =F14+1 -> 2 | H14: =G14+1 -> 3 | I14: =H14+1 -> 4 | J14: =I14+1 -> 5 | K14: =J14+1 -> 6 | L14: =K14+1 -> 7 | M14: =L14+1 -> 8 | N14: =M14+1 -> 9 | ... BK14: =BJ14+1 -> 58
C15: イベント
E17: 上昇率 | F17: 手取り
B18: 収入 | C18: 夫の収入 | E18: 0.015 | F18: 500 | G18: =F18+F18*$E18 -> 507.5 | H18: =G18+G18*$E18 -> 515.1125 | I18: =H18+H18*$E18 -> 522.83919 | J18: =I18+I18*$E18 -> 530.68178 | K18: =J18+J18*$E18 -> 538.642 | L18: =K18+K18*$E18 -> 546.72163 | M18: =L18+L18*$E18 -> 554.92246 | N18: =M18+M18*$E18 -> 563.24629 | ... U18: =T18+T18*$E18 -> 625.11603 | V18: 600 | W18: 600 | X18: 600 | Y18: 600 | Z18: 600 | AA18: 360 | AB18: 360 | AC18: 360 | AD18: 360 | AE18: 360 | AF18: 0 | AG18: 0 | AH18: 0 | AI18: 0 | AJ18: 0 | AK18: 0 | AL18: 0 | AM18: 0 | AN18: 0 | AO18: 0 | AP18: 0 | AQ18: 0 | AR18: 0 | AS18: 0 | AT18: 0 | AU18: 0 | AV18: 0 | AW18: 0 | AX18: 0 | AY18: 0 | AZ18: 0 | BA18: 0 | BB18: 0 | BC18: 0 | BD18: 0 | BE18: 0 | BF18: 0 | BG18: 0 | BH18: 0 | BI18: 0 | BJ18: 0 | BK18: 0
C19: 公的年金 | AE19: 275 | AF19: 275 | AG19: 275 | AH19: 275 | AI19: 275 | AJ19: 275 | AK19: 275 | AL19: 275 | AM19: 275 | AN19: 275 | AO19: 275 | AP19: 275 | AQ19: 275 | AR19: 275 | AS19: 275 | AT19: 275 | AU19: 275 | AV19: 275 | AW19: 275 | AX19: 275 | AY19: 275 | AZ19: 275 | BA19: 275 | BB19: 275 | BC19: 275 | BD19: 275 | BE19: 275 | BF19: 275 | BG19: 275 | BH19: 275 | BI19: 275 | BJ19: 275 | BK19: 275
C20: 私的年金 | AE20: 90 | AF20: 90 | AG20: 90 | AH20: 90 | AI20: 90 | AJ20: 90 | AK20: 90 | AL20: 90 | AM20: 90 | AN20: 90 | AO20: 90 | AP20: 90 | AQ20: 90 | AR20: 90 | AS20: 90 | AT20: 90 | AU20: 90 | AV20: 90 | AW20: 90 | AX20: 90 | AY20: 90 | AZ20: 90 | BA20: 90 | BB20: 90 | BC20: 90 | BD20: 90 | BE20: 90 | BF20: 90 | BG20: 90 | BH20: 90 | BI20: 90 | BJ20: 90 | BK20: 90
C21: 退職金
C22: 妻の収入 | E22: 0.015 | F22: 200 | G22: =F22+F22*$E22 -> 203 | H22: =G22+G22*$E22 -> 206.045 | I22: =H22+H22*$E22 -> 209.13567 | J22: =I22+I22*$E22 -> 212.27271 | K22: =J22+J22*$E22 -> 215.4568 | L22: =K22+K22*$E22 -> 218.68865 | M22: =L22+L22*$E22 -> 221.96898 | N22: =M22+M22*$E22 -> 225.29852 | ... AG22: =AF22+AF22*$E22 -> 298.96004 | AH22: 0 | AI22: 0 | AJ22: 0 | AK22: 0 | AL22: 0 | AM22: 0 | AN22: 0 | AO22: 0 | AP22: 0 | AQ22: 0 | AR22: 0 | AS22: 0 | AT22: 0 | AU22: 0 | AV22: 0 | AW22: 0 | AX22: 0 | AY22: 0 | AZ22: 0 | BA22: 0 | BB22: 0 | BC22: 0 | BD22: 0 | BE22: 0 | BF22: 0 | BG22: 0 | BH22: 0 | BI22: 0 | BJ22: 0 | BK22: 0
C23: 公的年金 | AL23: 180 | AM23: 180 | AN23: 180 | AO23: 180 | AP23: 180 | AQ23: 180 | AR23: 180 | AS23: 180 | AT23: 180 | AU23: 180 | AV23: 180 | AW23: 180 | AX23: 180 | AY23: 180 | AZ23: 180 | BA23: 180 | BB23: 180 | BC23: 180 | BD23: 180 | BE23: 180 | BF23: 180 | BG23: 180 | BH23: 180 | BI23: 180 | BJ23: 180 | BK23: 180
C24: 私的年金 | AL24: 60 | AM24: 60 | AN24: 60 | AO24: 60 | AP24: 60 | AQ24: 60 | AR24: 60 | AS24: 60 | AT24: 60 | AU24: 60 | AV24: 60 | AW24: 60 | AX24: 60 | AY24: 60 | AZ24: 60 | BA24: 60 | BB24: 60 | BC24: 60 | BD24: 60 | BE24: 60 | BF24: 60 | BG24: 60 | BH24: 60 | BI24: 60 | BJ24: 60 | BK24: 60
C25: 退職金
C26: その他の収入
C27: 収入合計① | F27: =SUM(F18:F26) -> 700 | G27: =SUM(G18:G26) -> 710.5 | H27: =SUM(H18:H26) -> 721.1575 | I27: =SUM(I18:I26) -> 731.97486 | J27: =SUM(J18:J26) -> 742.95449 | K27: =SUM(K18:K26) -> 754.0988 | L27: =SUM(L18:L26) -> 765.41028 | M27: =SUM(M18:M26) -> 776.89144 | ... BK27: =SUM(BK18:BK26) -> 605
B28: 固定費 | C28: 住宅 | F28: 180 | G28: =F28 -> 180 | H28: =G28 -> 180 | I28: =H28 -> 180 | J28: =I28 -> 180 | K28: =J28 -> 180 | L28: =K28 -> 180 | M28: =L28 -> 180 | N28: =M28 -> 180 | ... BK28: =BJ28 -> 180
C29: 住宅管理費 | F29: 0 | G29: =F29 -> 0 | H29: =G29 -> 0 | I29: =H29 -> 0 | J29: =I29 -> 0 | K29: =J29 -> 0 | L29: =K29 -> 0 | M29: =L29 -> 0 | N29: =M29 -> 0 | ... BK29: =BJ29 -> 0
C30: 車両ローン | F30: 12 | G30: =F30 -> 12 | H30: =G30 -> 12 | I30: =H30 -> 12 | J30: =I30 -> 12 | K30: =J30 -> 12 | L30: =K30 -> 12 | M30: =L30 -> 12 | N30: =M30 -> 12 | ... BK30: =BJ30 -> 12
C31: 駐車場代 | F31: 12 | G31: =F31 -> 12 | H31: =G31 -> 12 | I31: =H31 -> 12 | J31: =I31 -> 12 | K31: =J31 -> 12 | L31: =K31 -> 12 | M31: =L31 -> 12 | N31: =M31 -> 12 | ... BK31: =BJ31 -> 12
C32: テレビ契約料 | F32: 12 | G32: =F32 -> 12 | H32: =G32 -> 12 | I32: =H32 -> 12 | J32: =I32 -> 12 | K32: =J32 -> 12 | L32: =K32 -> 12 | M32: =L32 -> 12 | N32: =M32 -> 12 | ... BK32: =BJ32 -> 12
C33: 教育 | F33: 40 | G33: =F33 -> 40 | H33: =G33 -> 40 | I33: =H33 -> 40 | J33: =I33 -> 40 | K33: =J33 -> 40 | L33: 40 | M33: =L33 -> 40 | N33: =M33 -> 40 | O33: =N33 -> 40 | P33: =O33 -> 40 | Q33: =P33 -> 40 | R33: =Q33 -> 40 | S33: =R33 -> 40 | T33: =S33 -> 40 | ... BK33: =BJ33 -> 40
C34: 定期代 | F34: 40 | G34: =F34 -> 40 | H34: =G34 -> 40 | I34: =H34 -> 40 | J34: =I34 -> 40 | K34: =J34 -> 40 | L34: =K34 -> 40 | M34: =L34 -> 40 | N34: =M34 -> 40 | ... BK34: =BJ34 -> 40
C35: ※サブスク | F35: 1 | G35: =F35 -> 1 | H35: =G35 -> 1 | I35: =H35 -> 1 | J35: =I35 -> 1 | K35: =J35 -> 1 | L35: =K35 -> 1 | M35: =L35 -> 1 | N35: =M35 -> 1 | ... BK35: =BJ35 -> 1
C36: ※通信（wifi・スマホ） | F36: 12 | G36: =F36 -> 12 | H36: =G36 -> 12 | I36: =H36 -> 12 | J36: =I36 -> 12 | K36: =J36 -> 12 | L36: =K36 -> 12 | M36: =L36 -> 12 | N36: =M36 -> 12 | ... BK36: =BJ36 -> 12
C37: ※保険 | F37: 0 | G37: =F37 -> 0 | H37: =G37 -> 0 | I37: =H37 -> 0 | J37: =I37 -> 0 | K37: =J37 -> 0 | L37: =K37 -> 0 | M37: =L37 -> 0 | N37: =M37 -> 0 | ... BK37: =BJ37 -> 0
F38: 0 | G38: =F38 -> 0 | H38: =G38 -> 0 | I38: =H38 -> 0 | J38: =I38 -> 0 | K38: =J38 -> 0 | L38: =K38 -> 0 | M38: =L38 -> 0 | N38: =M38 -> 0 | ... BK38: =BJ38 -> 0
F39: 0 | G39: =F39 -> 0 | H39: =G39 -> 0 | I39: =H39 -> 0 | J39: =I39 -> 0 | K39: =J39 -> 0 | L39: =K39 -> 0 | M39: =L39 -> 0 | N39: =M39 -> 0 | ... BK39: =BJ39 -> 0
F40: 0 | G40: =F40 -> 0 | H40: =G40 -> 0 | I40: =H40 -> 0 | J40: =I40 -> 0 | K40: =J40 -> 0 | L40: =K40 -> 0 | M40: =L40 -> 0 | N40: =M40 -> 0 | ... BK40: =BJ40 -> 0
F41: 0 | G41: =F41 -> 0 | H41: =G41 -> 0 | I41: =H41 -> 0 | J41: =I41 -> 0 | K41: =J41 -> 0 | L41: =K41 -> 0 | M41: =L41 -> 0 | N41: =M41 -> 0 | ... BK41: =BJ41 -> 0
F42: 0 | G42: =F42 -> 0 | H42: =G42 -> 0 | I42: =H42 -> 0 | J42: =I42 -> 0 | K42: =J42 -> 0 | L42: =K42 -> 0 | M42: =L42 -> 0 | N42: =M42 -> 0 | ... BK42: =BJ42 -> 0
C43: 支出合計② | F43: =SUM(F28:F42) -> 309 | G43: =SUM(G28:G42) -> 309 | H43: =SUM(H28:H42) -> 309 | I43: =SUM(I28:I42) -> 309 | J43: =SUM(J28:J42) -> 309 | K43: =SUM(K28:K42) -> 309 | L43: =SUM(L28:L42) -> 309 | M43: =SUM(M28:M42) -> 309 | ... BK43: =SUM(BK28:BK42) -> 309
B44: 変動費 | C44: 食費 | E44: 0.005 | F44: 72 | G44: =F44+F44*$E44 -> 72.36 | H44: =G44+G44*$E44 -> 72.7218 | I44: =H44+H44*$E44 -> 73.085409 | J44: =I44+I44*$E44 -> 73.450836 | K44: =J44+J44*$E44 -> 73.81809 | L44: =K44+K44*$E44 -> 74.187181 | M44: =L44+L44*$E44 -> 74.558117 | N44: =M44+M44*$E44 -> 74.930907 | ... BK44: =BJ44+BJ44*$E44 -> 95.6749
C45: 水道光熱費 | E45: 0.005 | F45: 24 | G45: =F45+F45*$E45 -> 24.12 | H45: =G45+G45*$E45 -> 24.2406 | I45: =H45+H45*$E45 -> 24.361803 | J45: =I45+I45*$E45 -> 24.483612 | K45: =J45+J45*$E45 -> 24.60603 | L45: =K45+K45*$E45 -> 24.72906 | M45: =L45+L45*$E45 -> 24.852706 | N45: =M45+M45*$E45 -> 24.976969 | ... BK45: =BJ45+BJ45*$E45 -> 31.891633
C46: 日用品 | E46: 0.005 | F46: 24 | G46: =F46+F46*$E46 -> 24.12 | H46: =G46+G46*$E46 -> 24.2406 | I46: =H46+H46*$E46 -> 24.361803 | J46: =I46+I46*$E46 -> 24.483612 | K46: =J46+J46*$E46 -> 24.60603 | L46: =K46+K46*$E46 -> 24.72906 | M46: =L46+L46*$E46 -> 24.852706 | N46: =M46+M46*$E46 -> 24.976969 | ... BK46: =BJ46+BJ46*$E46 -> 31.891633
C47: 趣味・娯楽 | E47: 0.005 | F47: 36 | G47: =F47+F47*$E47 -> 36.18 | H47: =G47+G47*$E47 -> 36.3609 | I47: =H47+H47*$E47 -> 36.542704 | J47: =I47+I47*$E47 -> 36.725418 | K47: =J47+J47*$E47 -> 36.909045 | L47: =K47+K47*$E47 -> 37.09359 | M47: =L47+L47*$E47 -> 37.279058 | N47: =M47+M47*$E47 -> 37.465454 | ... BK47: =BJ47+BJ47*$E47 -> 47.83745
C48: 衣類・美容 | E48: 0.005 | F48: 24 | G48: =F48+F48*$E48 -> 24.12 | H48: =G48+G48*$E48 -> 24.2406 | I48: =H48+H48*$E48 -> 24.361803 | J48: =I48+I48*$E48 -> 24.483612 | K48: =J48+J48*$E48 -> 24.60603 | L48: =K48+K48*$E48 -> 24.72906 | M48: =L48+L48*$E48 -> 24.852706 | N48: =M48+M48*$E48 -> 24.976969 | ... BK48: =BJ48+BJ48*$E48 -> 31.891633
C49: 健康・医療 | E49: 0.005 | F49: 12 | G49: =F49+F49*$E49 -> 12.06 | H49: =G49+G49*$E49 -> 12.1203 | I49: =H49+H49*$E49 -> 12.180901 | J49: =I49+I49*$E49 -> 12.241806 | K49: =J49+J49*$E49 -> 12.303015 | L49: =K49+K49*$E49 -> 12.36453 | M49: =L49+L49*$E49 -> 12.426353 | N49: =M49+M49*$E49 -> 12.488485 | ... BK49: =BJ49+BJ49*$E49 -> 15.945817
C50: 交際費 | E50: 0.005 | F50: 36 | G50: =F50+F50*$E50 -> 36.18 | H50: =G50+G50*$E50 -> 36.3609 | I50: =H50+H50*$E50 -> 36.542704 | J50: =I50+I50*$E50 -> 36.725418 | K50: =J50+J50*$E50 -> 36.909045 | L50: =K50+K50*$E50 -> 37.09359 | M50: =L50+L50*$E50 -> 37.279058 | N50: =M50+M50*$E50 -> 37.465454 | ... BK50: =BJ50+BJ50*$E50 -> 47.83745
C51: 交通費 | E51: 0.005 | F51: 0 | G51: =F51+F51*$E51 -> 0 | H51: =G51+G51*$E51 -> 0 | I51: =H51+H51*$E51 -> 0 | J51: =I51+I51*$E51 -> 0 | K51: =J51+J51*$E51 -> 0 | L51: =K51+K51*$E51 -> 0 | M51: =L51+L51*$E51 -> 0 | N51: =M51+M51*$E51 -> 0 | ... BK51: =BJ51+BJ51*$E51 -> 0
C52: ガソリン代 | E52: 0.005 | F52: 20 | G52: =F52+F52*$E52 -> 20.1 | H52: =G52+G52*$E52 -> 20.2005 | I52: =H52+H52*$E52 -> 20.301503 | J52: =I52+I52*$E52 -> 20.40301 | K52: =J52+J52*$E52 -> 20.505025 | L52: =K52+K52*$E52 -> 20.60755 | M52: =L52+L52*$E52 -> 20.710588 | N52: =M52+M52*$E52 -> 20.814141 | ... BK52: =BJ52+BJ52*$E52 -> 26.576361
E53: 0.005 | F53: 0 | G53: =F53+F53*$E53 -> 0 | H53: =G53+G53*$E53 -> 0 | I53: =H53+H53*$E53 -> 0 | J53: =I53+I53*$E53 -> 0 | K53: =J53+J53*$E53 -> 0 | L53: =K53+K53*$E53 -> 0 | M53: =L53+L53*$E53 -> 0 | N53: =M53+M53*$E53 -> 0 | ... BK53: =BJ53+BJ53*$E53 -> 0
E54: 0.005 | F54: 0 | G54: =F54+F54*$E54 -> 0 | H54: =G54+G54*$E54 -> 0 | I54: =H54+H54*$E54 -> 0 | J54: =I54+I54*$E54 -> 0 | K54: =J54+J54*$E54 -> 0 | L54: =K54+K54*$E54 -> 0 | M54: =L54+L54*$E54 -> 0 | N54: =M54+M54*$E54 -> 0 | ... BK54: =BJ54+BJ54*$E54 -> 0
E55: 0.005 | F55: 0 | G55: =F55+F55*$E55 -> 0 | H55: =G55+G55*$E55 -> 0 | I55: =H55+H55*$E55 -> 0 | J55: =I55+I55*$E55 -> 0 | K55: =J55+J55*$E55 -> 0 | L55: =K55+K55*$E55 -> 0 | M55: =L55+L55*$E55 -> 0 | N55: =M55+M55*$E55 -> 0 | ... BK55: =BJ55+BJ55*$E55 -> 0
E56: 0.005 | F56: 0 | G56: =F56+F56*$E56 -> 0 | H56: =G56+G56*$E56 -> 0 | I56: =H56+H56*$E56 -> 0 | J56: =I56+I56*$E56 -> 0 | K56: =J56+J56*$E56 -> 0 | L56: =K56+K56*$E56 -> 0 | M56: =L56+L56*$E56 -> 0 | N56: =M56+M56*$E56 -> 0 | ... BK56: =BJ56+BJ56*$E56 -> 0
E57: 0.005 | F57: 0 | G57: =F57+F57*$E57 -> 0 | H57: =G57+G57*$E57 -> 0 | I57: =H57+H57*$E57 -> 0 | J57: =I57+I57*$E57 -> 0 | K57: =J57+J57*$E57 -> 0 | L57: =K57+K57*$E57 -> 0 | M57: =L57+L57*$E57 -> 0 | N57: =M57+M57*$E57 -> 0 | ... BK57: =BJ57+BJ57*$E57 -> 0
C58: 特別費（不定期支出） | F58: 150 | G58: =F58 -> 150 | H58: =G58 -> 150 | I58: =H58 -> 150 | J58: =I58 -> 150 | K58: =J58 -> 150 | L58: =K58 -> 150 | M58: =L58 -> 150 | N58: =M58 -> 150 | ... BK58: =BJ58 -> 150
C59: 支出合計③ | F59: =SUM(F44:F58) -> 398 | G59: =SUM(G44:G58) -> 399.24 | H59: =SUM(H44:H58) -> 400.4862 | I59: =SUM(I44:I58) -> 401.73863 | J59: =SUM(J44:J58) -> 402.99732 | K59: =SUM(K44:K58) -> 404.26231 | L59: =SUM(L44:L58) -> 405.53362 | M59: =SUM(M44:M58) -> 406.81129 | ... BK59: =SUM(BK44:BK58) -> 479.54688
B63: 年間の貯金額 | F63: =F27-(F43+F59) -> -7 | G63: =G27-(G43+G59) -> 2.26 | H63: =H27-(H43+H59) -> 11.6713 | I63: =I27-(I43+I59) -> 21.236231 | J63: =J27-(J43+J59) -> 30.957161 | K63: =K27-(K43+K59) -> 40.836492 | L63: =L27-(L43+L59) -> 50.876662 | M63: =M27-(M43+M59) -> 61.080149 | ... BK63: =BK27-(BK43+BK59) -> -183.54688

Sheet 📈資産推移
A1: 🌸資産残高の推移（万円）
B3: 🌸資産推移🌸 | E3: 2025 | F3: =E3+1 -> 2026 | G3: =F3+1 -> 2027 | H3: =G3+1 -> 2028 | I3: =H3+1 -> 2029 | J3: =I3+1 -> 2030 | K3: =J3+1 -> 2031 | L3: =K3+1 -> 2032 | M3: =L3+1 -> 2033 | ... BI3: =BH3+1 -> 2081
D4: 現在 | E4: 1 | F4: =E4+1 -> 2 | G4: =F4+1 -> 3 | H4: =G4+1 -> 4 | I4: =H4+1 -> 5 | J4: =I4+1 -> 6 | K4: =J4+1 -> 7 | L4: =K4+1 -> 8 | M4: =L4+1 -> 9 | ... BI4: =BH4+1 -> 57
B5: 現金 | C5: 1e-05 | D5: 0 | E5: =D5*(1+$C$5)+'🌷ライププラン'!F63-E11 -> -47 | F5: =E5*(1+$C$5)+'🌷ライププラン'!G63-F11 -> -84.74047 | G5: =F5*(1+$C$5)+'🌷ライププラン'!H63-G11 -> -113.07002 | H5: =G5*(1+$C$5)+'🌷ライププラン'!I63-H11 -> -131.83492 | I5: =H5*(1+$C$5)+'🌷ライププラン'!J63-I11 -> -140.87907 | J5: =I5*(1+$C$5)+'🌷ライププラン'!K63-J11 -> -140.04399 | K5: =J5*(1+$C$5)+'🌷ライププラン'!L63-K11 -> -129.16873 | L5: =K5*(1+$C$5)+'🌷ライププラン'!M63-L11 -> -108.08987 | ... BI5: =BH5*(1+$C$5)+'🌷ライププラン'!BJ63-BI11 -> -4930.4905
B6: 投資資産 | C6: 0.04 | D6: 0 | E6: ='🌱投信（ライフプラン用）'!E9/10000 -> 47.074804 | F6: ='🌱投信（ライフプラン用）'!E10/10000 -> 85.660093 | G6: ='🌱投信（ライフプラン用）'!E11/10000 -> 125.81741 | H6: ='🌱投信（ライフプラン用）'!E12/10000 -> 167.61079 | I6: ='🌱投信（ライフプラン用）'!E13/10000 -> 211.1069 | J6: ='🌱投信（ライフプラン用）'!E14/10000 -> 256.37511 | K6: ='🌱投信（ライフプラン用）'!E15/10000 -> 303.48762 | L6: ='🌱投信（ライフプラン用）'!E16/10000 -> 352.51956 | M6: ='🌱投信（ライフプラン用）'!E17/10000 -> 403.54914 | N6: ='🌱投信（ライフプラン用）'!E18/10000 -> 456.65774 | O6: ='🌱投信（ライフプラン用）'!E19/10000 -> 511.93007 | P6: ='🌱投信（ライフプラン用）'!E20/10000 -> 569.45428 | Q6: ='🌱投信（ライフプラン用）'!E21/10000 -> 629.32211 | R6: ='🌱投信（ライフプラン用）'!E22/10000 -> 691.62906 | S6: ='🌱投信（ライフプラン用）'!E23/10000 -> 756.47448 | T6: ='🌱投信（ライフプラン用）'!E24/10000 -> 823.96181 | U6: ='🌱投信（ライフプラン用）'!E25/10000 -> 894.19867 | V6: ='🌱投信（ライフプラン用）'!E26/10000 -> 967.29709 | W6: ='🌱投信（ライフプラン用）'!E27/10000 -> 1043.3737 | X6: ='🌱投信（ライフプラン用）'!E28/10000 -> 1122.5497 | Y6: ='🌱投信（ライフプラン用）'!E29/10000 -> 1204.9515 | Z6: ='🌱投信（ライフプラン用）'!E30/10000 -> 1290.7105 | AA6: ='🌱投信（ライフプラン用）'!E31/10000 -> 1379.9634 | AB6: ='🌱投信（ライフプラン用）'!E32/10000 -> 1472.8526 | AC6: ='🌱投信（ライフプラン用）'!E33/10000 -> 1569.5263 | AD6: ='🌱投信（ライフプラン用）'!E34/10000 -> 1670.1386 | AE6: ='🌱投信（ライフプラン用）'!E35/10000 -> 1774.85 | AF6: ='🌱投信（ライフプラン用）'!E36/10000 -> 1883.8275 | AG6: ='🌱投信（ライフプラン用）'!E37/10000 -> 1997.245 | AH6: ='🌱投信（ライフプラン用）'!E38/10000 -> 2115.2832 | AI6: ='🌱投信（ライフプラン用）'!E39/10000 -> 2238.1305 | AJ6: ='🌱投信（ライフプラン用）'!E40/10000 -> 2365.9828 | AK6: ='🌱投信（ライフプラン用）'!E41/10000 -> 2499.0439 | AL6: ='🌱投信（ライフプラン用）'!E42/10000 -> 2637.5262 | AM6: ='🌱投信（ライフプラン用）'!E43/10000 -> 2781.6505 | AN6: ='🌱投信（ライフプラン用）'!E44/10000 -> 2931.6466 | AO6: ='🌱投信（ライフプラン用）'!E45/10000 -> 3087.7538 | AP6: ='🌱投信（ライフプラン用）'!E46/10000 -> 3250.2211 | AQ6: ='🌱投信（ライフプラン用）'!E47/10000 -> 3419.3075 | AR6: ='🌱投信（ライフプラン用）'!E48/10000 -> 3595.2827 | AS6: ='🌱投信（ライフプラン用）'!E49/10000 -> 3778.4275 | AT6: ='🌱投信（ライフプラン用）'!E50/10000 -> 3969.0338 | AU6: ='🌱投信（ライフプラン用）'!E51/10000 -> 4167.4058 | AV6: ='🌱投信（ライフプラン用）'!E52/10000 -> 4373.8597 | AW6: ='🌱投信（ライフプラン用）'!E53/10000 -> 4588.7249 | AX6: ='🌱投信（ライフプラン用）'!E54/10000 -> 4812.344 | AY6: ='🌱投信（ライフプラン用）'!E55/10000 -> 5045.0737 | AZ6: ='🌱投信（ライフプラン用）'!E56/10000 -> 5287.2852 | BA6: ='🌱投信（ライフプラン用）'!E57/10000 -> 5539.3648 | BB6: ='🌱投信（ライフプラン用）'!E58/10000 -> 5801.7144 | BC6: ='🌱投信（ライフプラン用）'!E59 | BD6: ='🌱投信（ライフプラン用）'!AZ13 | BE6: ='🌱投信（ライフプラン用）'!BA13 | BF6: ='🌱投信（ライフプラン用）'!BB13 | BG6: ='🌱投信（ライフプラン用）'!BC13 | BH6: ='🌱投信（ライフプラン用）'!BD13 | BI6: ='🌱投信（ライフプラン用）'!BE13
B7: 不動産 | C7: -0.01 | D7: 0 | E7: =D7*(1+$C7) -> 0 | F7: =E7*(1+$C7) -> 0 | G7: =F7*(1+$C7) -> 0 | H7: =G7*(1+$C7) -> 0 | I7: =H7*(1+$C7) -> 0 | J7: =I7*(1+$C7) -> 0 | K7: =J7*(1+$C7) -> 0 | L7: =K7*(1+$C7) -> 0 | ... BI7: =BH7*(1+$C7) -> 0
B8: その他資産 | D8: 0 | E8: =D8 -> 0 | F8: =E8 -> 0 | G8: =F8 -> 0 | H8: =G8 -> 0 | I8: =H8 -> 0 | J8: =I8 -> 0 | K8: =J8 -> 0 | L8: =K8 -> 0 | ... BI8: =BH8 -> 0
B9: 負債（住宅ローン等） | D9: 0 | E9: 0 | F9: 0 | G9: 0 | H9: 0 | I9: 0 | J9: 0 | K9: 0 | L9: 0 | M9: 0 | N9: 0 | O9: 0 | P9: 0 | Q9: 0 | R9: 0 | S9: 0 | T9: 0 | U9: 0 | V9: 0 | W9: 0 | X9: 0 | Y9: 0 | Z9: 0 | AA9: 0 | AB9: 0 | AC9: 0 | AD9: 0 | AE9: 0 | AF9: 0 | AG9: 0 | AH9: 0 | AI9: 0 | AJ9: 0 | AK9: 0 | AL9: 0 | AM9: 0 | AN9: 0 | AO9: 0 | AP9: 0 | AQ9: 0 | AR9: 0 | AS9: 0 | AT9: 0 | AU9: 0 | AV9: 0 | AW9: 0 | AX9: 0 | AY9: 0 | AZ9: 0 | BA9: 0 | BB9: 0 | BC9: 0 | BD9: 0 | BE9: 0 | BF9: 0 | BG9: 0 | BH9: 0 | BI9: 0
B10: 純資産 | D10: =SUM(D5:D9) -> 0 | E10: =SUM(E5:E9) -> 0.074804057 | F10: =SUM(F5:F9) -> 0.91962283 | G10: =SUM(G5:G9) -> 12.747388 | H10: =SUM(H5:H9) -> 35.775873 | I10: =SUM(I5:I9) -> 70.227827 | J10: =SUM(J5:J9) -> 116.33112 | K10: =SUM(K5:K9) -> 174.31889 | ... BI10: =SUM(BI5:BI9) -> -4930.4905
B11: 投資信託(NISA/IDECO) | E11: 40 | F11: =+E11 -> 40 | G11: =F11 -> 40 | H11: =G11 -> 40 | I11: =H11 -> 40 | J11: =I11 -> 40 | K11: =J11 -> 40 | L11: =K11 -> 40 | M11: =L11 -> 40 | N11: =M11 -> 40 | ... X11: =W11 -> 40 | Y11: 0 | Z11: 0 | AA11: 0 | AB11: 0 | AC11: 0 | AD11: 0 | AE11: 0 | AF11: 0 | AG11: 0 | AH11: 0 | AI11: 0 | AJ11: 0 | AK11: 0 | AL11: 0 | AM11: 0 | AN11: 0 | AO11: 0 | AP11: 0 | AQ11: 0 | AR11: 0 | AS11: 0 | AT11: 0 | AU11: 0 | AV11: 0 | AW11: 0 | AX11: 0 | AY11: 0 | AZ11: 0 | BA11: 0 | BB11: 0 | BC11: 0 | BD11: 0 | BE11: 0 | BF11: 0 | BG11: 0 | BH11: 0 | BI11: 0
B12: 企業型ＤＣ | E12: 0 | F12: =E12 -> 0 | G12: =F12 -> 0 | H12: =G12 -> 0 | I12: =H12 -> 0 | J12: =I12 -> 0 | K12: =J12 -> 0 | L12: =K12 -> 0 | M12: =L12 -> 0 | ... BI12: =BH12 -> 0

Sheet 🌱投信（ライフプラン用）
A1: 🌸投資信託（複利計算ツール）
A3: 一括投資済の額 | B3: 月の積立額 | C3: 想定利回り | E3: ◆金融庁：つみたてシミュレーター
A4: 100000 | B4: 30000 | C4: 0.04 | E4: https://www.fsa.go.jp/policy/nisa2/tsumitate-simulator/
A8: 年 | B8: 年初残高 | C8: 年増加額 | D8: 利息 | E8: 年末残高 | F8: 投資額累計
A9: 1 | B9: =A4 -> 100000 | C9: =B$4*12 -> 360000 | D9: =E9-SUM(B9:C9) -> 10748.041 | E9: =B9*(1+C$4/12)^12+B$4/(C$4/12)*((1+C$4/12)^(A9*12)-1) -> 470748.04 | F9: =C9+B9 -> 460000
A10: =A9+1 -> 2 | B10: =E9 -> 470748.04 | C10: =B$4*12 -> 360000 | D10: =E10-SUM(B10:C10) -> 25852.888 | E10: =B$9*(1+C$4/12)^(A10*12)+B$4/(C$4/12)*((1+C$4/12)^(A10*12)-1) -> 856600.93 | F10: =F9+C10 -> 820000
A11: =A10+1 -> 3 | B11: =B10+C10+D10 -> 856600.93 | C11: =B$4*12 -> 360000 | D11: =E11-SUM(B11:C11) -> 41573.13 | E11: =B$9*(1+C$4/12)^(A11*12)+B$4/(C$4/12)*((1+C$4/12)^(A11*12)-1) -> 1258174.1 | F11: =F10+C11 -> 1180000
A12: =A11+1 -> 4 | B12: =B11+C11+D11 -> 1258174.1 | C12: =B$4*12 -> 360000 | D12: =E12-SUM(B12:C12) -> 57933.839 | E12: =B$9*(1+C$4/12)^(A12*12)+B$4/(C$4/12)*((1+C$4/12)^(A12*12)-1) -> 1676107.9 | F12: =F11+C12 -> 1540000
A13: =A12+1 -> 5 | B13: =B12+C12+D12 -> 1676107.9 | C13: =B$4*12 -> 360000 | D13: =E13-SUM(B13:C13) -> 74961.108 | E13: =B$9*(1+C$4/12)^(A13*12)+B$4/(C$4/12)*((1+C$4/12)^(A13*12)-1) -> 2111069 | F13: =F12+C13 -> 1900000
A14: =A13+1 -> 6 | B14: =B13+C13+D13 -> 2111069 | C14: =B$4*12 -> 360000 | D14: =E14-SUM(B14:C14) -> 92682.095 | E14: =B$9*(1+C$4/12)^(A14*12)+B$4/(C$4/12)*((1+C$4/12)^(A14*12)-1) -> 2563751.1 | F14: =F13+C14 -> 2260000
A15: =A14+1 -> 7 | B15: =B14+C14+D14 -> 2563751.1 | C15: =B$4*12 -> 360000 | D15: =E15-SUM(B15:C15) -> 111125.06 | E15: =B$9*(1+C$4/12)^(A15*12)+B$4/(C$4/12)*((1+C$4/12)^(A15*12)-1) -> 3034876.2 | F15: =F14+C15 -> 2620000
A16: =A15+1 -> 8 | B16: =B15+C15+D15 -> 3034876.2 | C16: =B$4*12 -> 360000 | D16: =E16-SUM(B16:C16) -> 130319.42 | E16: =B$9*(1+C$4/12)^(A16*12)+B$4/(C$4/12)*((1+C$4/12)^(A16*12)-1) -> 3525195.6 | F16: =F15+C16 -> 2980000
A17: =A16+1 -> 9 | B17: =B16+C16+D16 -> 3525195.6 | C17: =B$4*12 -> 360000 | D17: =E17-SUM(B17:C17) -> 150295.79 | E17: =B$9*(1+C$4/12)^(A17*12)+B$4/(C$4/12)*((1+C$4/12)^(A17*12)-1) -> 4035491.4 | F17: =F16+C17 -> 3340000
A18: =A17+1 -> 10 | B18: =B17+C17+D17 -> 4035491.4 | C18: =B$4*12 -> 360000 | D18: =E18-SUM(B18:C18) -> 171086.03 | E18: =B$9*(1+C$4/12)^(A18*12)+B$4/(C$4/12)*((1+C$4/12)^(A18*12)-1) -> 4566577.4 | F18: =F17+C18 -> 3700000
A19: =A18+1 -> 11 | B19: =B18+C18+D18 -> 4566577.4 | C19: =B$4*12 -> 360000 | D19: =E19-SUM(B19:C19) -> 192723.3 | E19: =B$9*(1+C$4/12)^(A19*12)+B$4/(C$4/12)*((1+C$4/12)^(A19*12)-1) -> 5119300.7 | F19: =F18+C19 -> 4060000
A20: =A19+1 -> 12 | B20: =B19+C19+D19 -> 5119300.7 | C20: =B$4*12 -> 360000 | D20: =E20-SUM(B20:C20) -> 215242.1 | E20: =B$9*(1+C$4/12)^(A20*12)+B$4/(C$4/12)*((1+C$4/12)^(A20*12)-1) -> 5694542.8 | F20: =F19+C20 -> 4420000
A21: =A20+1 -> 13 | B21: =B20+C20+D20 -> 5694542.8 | C21: =B$4*12 -> 360000 | D21: =E21-SUM(B21:C21) -> 238678.35 | E21: =B$9*(1+C$4/12)^(A21*12)+B$4/(C$4/12)*((1+C$4/12)^(A21*12)-1) -> 6293221.1 | F21: =F20+C21 -> 4780000
A22: =A21+1 -> 14 | B22: =B21+C21+D21 -> 6293221.1 | C22: =B$4*12 -> 360000 | D22: =E22-SUM(B22:C22) -> 263069.43 | E22: =B$9*(1+C$4/12)^(A22*12)+B$4/(C$4/12)*((1+C$4/12)^(A22*12)-1) -> 6916290.6 | F22: =F21+C22 -> 5140000
... A58: =A57+1 -> 50 | B58: =B57+C57+D57 -> 55393648 | C58: =B$4*12 -> 360000 | D58: =E58-SUM(B58:C58) -> 2263496.6 | E58: =B$9*(1+C$4/12)^(A58*12)+B$4/(C$4/12)*((1+C$4/12)^(A58*12)-1) -> 58017144 | F58: =F57+C58 -> 18100000

Sheet ✨行動計画
B1: 🌸行動計画シート（個別MTG時に使用します♪）
B3: 🌷行動計画
B4: 行動内容 | C4: 目標期日 | D4: チェック | E4: メモ
D5: FALSE
D6: FALSE
D7: FALSE
D8: FALSE
D9: FALSE
D10: FALSE
D11: FALSE
D12: FALSE
D13: FALSE
D14: FALSE
D15: FALSE
D16: FALSE
... D38: FALSE

Sheet 🌟資産配分
A1: 🌸資産配分（アセット・アロケーション）
B3: 🌸銘柄名🌸 | C3: 評価額 | D3: 国際株式 | E3: 国際債券 | F3: 国内株式 | G3: 国内債券 | H3: 新興国株式 | I3: 新興国債券 | J3: 国際REIT | K3: 国内REIT | L3: その他 | M3: 金 | N3: 現金 | O3: 合計 | P3: 評価額1 | Q3: 評価額2 | R3: 評価額3 | S3: 評価額4 | T3: 評価額5 | U3: 評価額6 | V3: 評価額7 | W3: 評価額8 | X3: 評価額9 | Y3: 評価額10
B4: 三菱ＵＦＪ－ｅＭＡＸＩＳ Ｓｌｉｍ 米国株式（Ｓ＆Ｐ５００） | C4: 1000000 | D4: 1 | O4: =IF(SUM('🌟資産配分'!$D4:$N4)=0,"",SUM('🌟資産配分'!$D4:$N4)) -> 1 | P4: ='🌟資産配分'!$C4*'🌟資産配分'!$D4 -> 1000000 | Q4: ='🌟資産配分'!$C4*'🌟資産配分'!$E4 -> 0 | R4: ='🌟資産配分'!$C4*'🌟資産配分'!$F4 -> 0 | S4: ='🌟資産配分'!$C4*'🌟資産配分'!$G4 -> 0 | T4: ='🌟資産配分'!$C4*'🌟資産配分'!$H4 -> 0 | U4: ='🌟資産配分'!$C4*'🌟資産配分'!$I4 -> 0 | V4: ='🌟資産配分'!$C4*'🌟資産配分'!$J4 -> 0 | W4: ='🌟資産配分'!$C4*'🌟資産配分'!$K4 -> 0 | X4: ='🌟資産配分'!$C4*'🌟資産配分'!$L4 -> 0 | Y4: ='🌟資産配分'!$C4*'🌟資産配分'!$N4 -> 0
B5: 三菱ＵＦＪ－ｅＭＡＸＩＳ Ｓｌｉｍ 全世界株式（オール・カントリー） | C5: 500000 | D5: 1 | O5: =IF(SUM('🌟資産配分'!$D5:$N5)=0,"",SUM('🌟資産配分'!$D5:$N5)) -> 1 | P5: ='🌟資産配分'!$C5*'🌟資産配分'!$D5 -> 500000 | Q5: ='🌟資産配分'!$C5*'🌟資産配分'!$E5 -> 0 | R5: ='🌟資産配分'!$C5*'🌟資産配分'!$F5 -> 0 | S5: ='🌟資産配分'!$C5*'🌟資産配分'!$G5 -> 0 | T5: ='🌟資産配分'!$C5*'🌟資産配分'!$H5 -> 0 | U5: ='🌟資産配分'!$C5*'🌟資産配分'!$I5 -> 0 | V5: ='🌟資産配分'!$C5*'🌟資産配分'!$J5 -> 0 | W5: ='🌟資産配分'!$C5*'🌟資産配分'!$K5 -> 0 | X5: ='🌟資産配分'!$C5*'🌟資産配分'!$L5 -> 0 | Y5: ='🌟資産配分'!$C5*'🌟資産配分'!$N5 -> 0
B6: 大和－ｉＦｒｅｅＮＥＸＴ ＦＡＮＧ＋インデックス | C6: 500000 | D6: 1 | O6: =IF(SUM('🌟資産配分'!$D6:$N6)=0,"",SUM('🌟資産配分'!$D6:$N6)) -> 1 | P6: ='🌟資産配分'!$C6*'🌟資産配分'!$D6 -> 500000 | Q6: ='🌟資産配分'!$C6*'🌟資産配分'!$E6 -> 0 | R6: ='🌟資産配分'!$C6*'🌟資産配分'!$F6 -> 0 | S6: ='🌟資産配分'!$C6*'🌟資産配分'!$G6 -> 0 | T6: ='🌟資産配分'!$C6*'🌟資産配分'!$H6 -> 0 | U6: ='🌟資産配分'!$C6*'🌟資産配分'!$I6 -> 0 | V6: ='🌟資産配分'!$C6*'🌟資産配分'!$J6 -> 0 | W6: ='🌟資産配分'!$C6*'🌟資産配分'!$K6 -> 0 | X6: ='🌟資産配分'!$C6*'🌟資産配分'!$L6 -> 0 | Y6: ='🌟資産配分'!$C6*'🌟資産配分'!$N6 -> 0
B7: ニッセイ－＜購入・換金手数料なし＞ニッセイＮＡＳＤＡＱ１００インデックスファンド | C7: 100000 | D7: 1 | O7: =IF(SUM('🌟資産配分'!$D7:$N7)=0,"",SUM('🌟資産配分'!$D7:$N7)) -> 1 | P7: ='🌟資産配分'!$C7*'🌟資産配分'!$D7 -> 100000 | Q7: ='🌟資産配分'!$C7*'🌟資産配分'!$E7 -> 0 | R7: ='🌟資産配分'!$C7*'🌟資産配分'!$F7 -> 0 | S7: ='🌟資産配分'!$C7*'🌟資産配分'!$G7 -> 0 | T7: ='🌟資産配分'!$C7*'🌟資産配分'!$H7 -> 0 | U7: ='🌟資産配分'!$C7*'🌟資産配分'!$I7 -> 0 | V7: ='🌟資産配分'!$C7*'🌟資産配分'!$J7 -> 0 | W7: ='🌟資産配分'!$C7*'🌟資産配分'!$K7 -> 0 | X7: ='🌟資産配分'!$C7*'🌟資産配分'!$L7 -> 0 | Y7: ='🌟資産配分'!$C7*'🌟資産配分'!$N7 -> 0
B8: 三菱ＵＦＪ－ｅＭＡＸＩＳ Ｓｌｉｍ 国内債券インデックス | C8: 300000 | G8: 1 | O8: =IF(SUM('🌟資産配分'!$D8:$N8)=0,"",SUM('🌟資産配分'!$D8:$N8)) -> 1 | P8: ='🌟資産配分'!$C8*'🌟資産配分'!$D8 -> 0 | Q8: ='🌟資産配分'!$C8*'🌟資産配分'!$E8 -> 0 | R8: ='🌟資産配分'!$C8*'🌟資産配分'!$F8 -> 0 | S8: ='🌟資産配分'!$C8*'🌟資産配分'!$G8 -> 300000 | T8: ='🌟資産配分'!$C8*'🌟資産配分'!$H8 -> 0 | U8: ='🌟資産配分'!$C8*'🌟資産配分'!$I8 -> 0 | V8: ='🌟資産配分'!$C8*'🌟資産配分'!$J8 -> 0 | W8: ='🌟資産配分'!$C8*'🌟資産配分'!$K8 -> 0 | X8: ='🌟資産配分'!$C8*'🌟資産配分'!$L8 -> 0 | Y8: ='🌟資産配分'!$C8*'🌟資産配分'!$N8 -> 0
O9: =IF(SUM('🌟資産配分'!$D9:$N9)=0,"",SUM('🌟資産配分'!$D9:$N9)) | P9: ='🌟資産配分'!$C9*'🌟資産配分'!$D9 -> 0 | Q9: ='🌟資産配分'!$C9*'🌟資産配分'!$E9 -> 0 | R9: ='🌟資産配分'!$C9*'🌟資産配分'!$F9 -> 0 | S9: ='🌟資産配分'!$C9*'🌟資産配分'!$G9 -> 0 | T9: ='🌟資産配分'!$C9*'🌟資産配分'!$H9 -> 0 | U9: ='🌟資産配分'!$C9*'🌟資産配分'!$I9 -> 0 | V9: ='🌟資産配分'!$C9*'🌟資産配分'!$J9 -> 0 | W9: ='🌟資産配分'!$C9*'🌟資産配分'!$K9 -> 0 | X9: ='🌟資産配分'!$C9*'🌟資産配分'!$L9 -> 0 | Y9: ='🌟資産配分'!$C9*'🌟資産配分'!$N9 -> 0
O10: =IF(SUM('🌟資産配分'!$D10:$N10)=0,"",SUM('🌟資産配分'!$D10:$N10)) | P10: ='🌟資産配分'!$C10*'🌟資産配分'!$D10 -> 0 | Q10: ='🌟資産配分'!$C10*'🌟資産配分'!$E10 -> 0 | R10: ='🌟資産配分'!$C10*'🌟資産配分'!$F10 -> 0 | S10: ='🌟資産配分'!$C10*'🌟資産配分'!$G10 -> 0 | T10: ='🌟資産配分'!$C10*'🌟資産配分'!$H10 -> 0 | U10: ='🌟資産配分'!$C10*'🌟資産配分'!$I10 -> 0 | V10: ='🌟資産配分'!$C10*'🌟資産配分'!$J10 -> 0 | W10: ='🌟資産配分'!$C10*'🌟資産配分'!$K10 -> 0 | X10: ='🌟資産配分'!$C10*'🌟資産配分'!$L10 -> 0 | Y10: ='🌟資産配分'!$C10*'🌟資産配分'!$N10 -> 0
O11: =IF(SUM('🌟資産配分'!$D11:$N11)=0,"",SUM('🌟資産配分'!$D11:$N11)) | P11: ='🌟資産配分'!$C11*'🌟資産配分'!$D11 -> 0 | Q11: ='🌟資産配分'!$C11*'🌟資産配分'!$E11 -> 0 | R11: ='🌟資産配分'!$C11*'🌟資産配分'!$F11 -> 0 | S11: ='🌟資産配分'!$C11*'🌟資産配分'!$G11 -> 0 | T11: ='🌟資産配分'!$C11*'🌟資産配分'!$H11 -> 0 | U11: ='🌟資産配分'!$C11*'🌟資産配分'!$I11 -> 0 | V11: ='🌟資産配分'!$C11*'🌟資産配分'!$J11 -> 0 | W11: ='🌟資産配分'!$C11*'🌟資産配分'!$K11 -> 0 | X11: ='🌟資産配分'!$C11*'🌟資産配分'!$L11 -> 0 | Y11: ='🌟資産配分'!$C11*'🌟資産配分'!$N11 -> 0
O12: =IF(SUM('🌟資産配分'!$D12:$N12)=0,"",SUM('🌟資産配分'!$D12:$N12)) | P12: ='🌟資産配分'!$C12*'🌟資産配分'!$D12 -> 0 | Q12: ='🌟資産配分'!$C12*'🌟資産配分'!$E12 -> 0 | R12: ='🌟資産配分'!$C12*'🌟資産配分'!$F12 -> 0 | S12: ='🌟資産配分'!$C12*'🌟資産配分'!$G12 -> 0 | T12: ='🌟資産配分'!$C12*'🌟資産配分'!$H12 -> 0 | U12: ='🌟資産配分'!$C12*'🌟資産配分'!$I12 -> 0 | V12: ='🌟資産配分'!$C12*'🌟資産配分'!$J12 -> 0 | W12: ='🌟資産配分'!$C12*'🌟資産配分'!$K12 -> 0 | X12: ='🌟資産配分'!$C12*'🌟資産配分'!$L12 -> 0 | Y12: ='🌟資産配分'!$C12*'🌟資産配分'!$N12 -> 0
O13: =IF(SUM('🌟資産配分'!$D13:$N13)=0,"",SUM('🌟資産配分'!$D13:$N13)) | P13: ='🌟資産配分'!$C13*'🌟資産配分'!$D13 -> 0 | Q13: ='🌟資産配分'!$C13*'🌟資産配分'!$E13 -> 0 | R13: ='🌟資産配分'!$C13*'🌟資産配分'!$F13 -> 0 | S13: ='🌟資産配分'!$C13*'🌟資産配分'!$G13 -> 0 | T13: ='🌟資産配分'!$C13*'🌟資産配分'!$H13 -> 0 | U13: ='🌟資産配分'!$C13*'🌟資産配分'!$I13 -> 0 | V13: ='🌟資産配分'!$C13*'🌟資産配分'!$J13 -> 0 | W13: ='🌟資産配分'!$C13*'🌟資産配分'!$K13 -> 0 | X13: ='🌟資産配分'!$C13*'🌟資産配分'!$L13 -> 0 | Y13: ='🌟資産配分'!$C13*'🌟資産配分'!$N13 -> 0
B14: ◆現金 | C14: 3000000 | N14: 1 | O14: =IF(SUM('🌟資産配分'!$D14:$N14)=0,"",SUM('🌟資産配分'!$D14:$N14)) -> 1 | P14: ='🌟資産配分'!$C14*'🌟資産配分'!$D14 -> 0 | Q14: ='🌟資産配分'!$C14*'🌟資産配分'!$E14 -> 0 | R14: ='🌟資産配分'!$C14*'🌟資産配分'!$F14 -> 0 | S14: ='🌟資産配分'!$C14*'🌟資産配分'!$G14 -> 0 | T14: ='🌟資産配分'!$C14*'🌟資産配分'!$H14 -> 0 | U14: ='🌟資産配分'!$C14*'🌟資産配分'!$I14 -> 0 | V14: ='🌟資産配分'!$C14*'🌟資産配分'!$J14 -> 0 | W14: ='🌟資産配分'!$C14*'🌟資産配分'!$K14 -> 0 | X14: ='🌟資産配分'!$C14*'🌟資産配分'!$L14 -> 0 | Y14: ='🌟資産配分'!$C14*'🌟資産配分'!$N14 -> 3000000
B15: 三菱ＵＦＪ－ｅＭＡＸＩＳ Ｓｌｉｍ バランス（８資産均等型） | D15: 0.25 | E15: 0.24 | F15: 0.12 | G15: 0.11 | J15: 0.12 | K15: 0.12 | L15: 0.04
C17: 理想 | E17: 現在 | G17: リバランス
C18: ％ | D18: 評価額 | E18: ％ | F18: 評価額 | G18: ％ | H18: 評価額
B19: =D3 -> 国際株式 | C19: 0.4 | D19: =IF(C19="","",$F$30*C19) -> 2160000 | E19: =IF(F19="","",F19/$F$30) -> 0.38888889 | F19: =IF(SUM('🌟資産配分'!$P$4:$P$14)=0,"",SUM('🌟資産配分'!$P$4:$P$14)) -> 2100000 | G19: =IFERROR(C19-E19,"") -> 0.011111111 | H19: =IFERROR(D19-F19,"") -> 60000
B20: =E3 -> 国際債券 | C20: 0 | D20: =IF(C20="","",$F$30*C20) -> 0 | E20: =IF(F20="","",F20/$F$30) | F20: =IF(SUM('🌟資産配分'!$Q$4:$Q$14)=0,"",SUM('🌟資産配分'!$Q$4:$Q$14)) | G20: =IFERROR(C20-E20,"") -> 0 | H20: =IFERROR(D20-F20,"") -> 0
B21: =F3 -> 国内株式 | C21: 0 | D21: =IF(C21="","",$F$30*C21) -> 0 | E21: =IF(F21="","",F21/$F$30) | F21: =IF(SUM('🌟資産配分'!$R$4:$R$14)=0,"",SUM('🌟資産配分'!$R$4:$R$14)) | G21: =IFERROR(C21-E21,"") -> 0 | H21: =IFERROR(D21-F21,"") -> 0
B22: =G3 -> 国内債券 | C22: 0.1 | D22: =IF(C22="","",$F$30*C22) -> 540000 | E22: =IF(F22="","",F22/$F$30) -> 0.055555556 | F22: =IF(SUM('🌟資産配分'!$S$4:$S$14)=0,"",SUM('🌟資産配分'!$S$4:$S$14)) -> 300000 | G22: =IFERROR(C22-E22,"") -> 0.044444444 | H22: =IFERROR(D22-F22,"") -> 240000
B23: =H3 -> 新興国株式 | C23: 0 | D23: =IF(C23="","",$F$30*C23) -> 0 | E23: =IF(F23="","",F23/$F$30) | F23: =IF(SUM('🌟資産配分'!$T$4:$T$14)=0,"",SUM('🌟資産配分'!$T$4:$T$14)) | G23: =IFERROR(C23-E23,"") -> 0 | H23: =IFERROR(D23-F23,"") -> 0
B24: =I3 -> 新興国債券 | C24: 0 | D24: =IF(C24="","",$F$30*C24) -> 0 | E24: =IF(F24="","",F24/$F$30) | F24: =IF(SUM('🌟資産配分'!$U$4:$U$14)=0,"",SUM('🌟資産配分'!$U$4:$U$14)) | G24: =IFERROR(C24-E24,"") -> 0 | H24: =IFERROR(D24-F24,"") -> 0
B25: =J3 -> 国際REIT | C25: 0 | D25: =IF(C25="","",$F$30*C25) -> 0 | E25: =IF(F25="","",F25/$F$30) | F25: =IF(SUM('🌟資産配分'!$V$4:$V$14)=0,"",SUM('🌟資産配分'!$V$4:$V$14)) | G25: =IFERROR(C25-E25,"") -> 0 | H25: =IFERROR(D25-F25,"") -> 0
B26: =K3 -> 国内REIT | C26: 0 | D26: =IF(C26="","",$F$30*C26) -> 0 | E26: =IF(F26="","",F26/$F$30) | F26: =IF(SUM('🌟資産配分'!$W$4:$W$14)=0,"",SUM('🌟資産配分'!$W$4:$W$14)) | G26: =IFERROR(C26-E26,"") -> 0 | H26: =IFERROR(D26-F26,"") -> 0
B27: =L3 -> その他 | C27: 0 | D27: =IF(C27="","",$F$30*C27) -> 0 | E27: =IF(F27="","",F27/$F$30) | F27: =IF(SUM('🌟資産配分'!$X$4:$X$14)=0,"",SUM('🌟資産配分'!$X$4:$X$14)) | G27: =IFERROR(C27-E27,"") -> 0 | H27: =IFERROR(D27-F27,"") -> 0
B28: 金 | C28: 0 | D28: =IF(C28="","",$F$30*C28) -> 0 | E28: =IF(F28="","",F28/$F$30) -> 0 | F28: 0 | G28: =IFERROR(C28-E28,"") -> 0 | H28: =IFERROR(D28-F28,"") -> 0
B29: =N3 -> 現金 | C29: 0.5 | D29: =IF(C29="","",$F$30*C29) -> 2700000 | E29: =IF(F29="","",F29/$F$30) -> 0.55555556 | F29: =IF(SUM('🌟資産配分'!$Y$4:$Y$14)=0,"",SUM('🌟資産配分'!$Y$4:$Y$14)) -> 3000000 | G29: =IFERROR(C29-E29,"") -> -0.055555556 | H29: =IFERROR(D29-F29,"") -> -300000
C30: =SUM(C19:C29) -> 1 | D30: =SUM(D19:D29) -> 5400000 | E30: =SUM(E19:E29) -> 1 | F30: =SUM(F19:F29) -> 5400000

Sheet 🌱投信（自由）
A1: 🌸投資信託（複利計算ツール）
A3: 一括投資済の額 | B3: 月の積立額 | C3: 想定利回り | E3: ◆金融庁：つみたてシミュレーター
A4: 0 | B4: 30000 | C4: 0.07 | E4: https://www.fsa.go.jp/policy/nisa2/tsumitate-simulator/
A8: 年 | B8: 年初残高 | C8: 年増加額 | D8: 利息 | E8: 年末残高 | F8: 投資額累計
A9: 1 | B9: =A4 -> 0 | C9: =B$4*12 -> 360000 | D9: =E9-SUM(B9:C9) -> 11777.559 | E9: =B9*(1+C$4/12)^12+B$4/(C$4/12)*((1+C$4/12)^(A9*12)-1) -> 371777.56 | F9: =C9+B9 -> 360000
A10: =A9+1 -> 2 | B10: =E9 -> 371777.56 | C10: =B$4*12 -> 360000 | D10: =E10-SUM(B10:C10) -> 38653.388 | E10: =B$9*(1+C$4/12)^(A10*12)+B$4/(C$4/12)*((1+C$4/12)^(A10*12)-1) -> 770430.95 | F10: =F9+C10 -> 720000
A11: =A10+1 -> 3 | B11: =B10+C10+D10 -> 770430.95 | C11: =B$4*12 -> 360000 | D11: =E11-SUM(B11:C11) -> 67472.074 | E11: =B$9*(1+C$4/12)^(A11*12)+B$4/(C$4/12)*((1+C$4/12)^(A11*12)-1) -> 1197903 | F11: =F10+C11 -> 1080000
A12: =A11+1 -> 4 | B12: =B11+C11+D11 -> 1197903 | C12: =B$4*12 -> 360000 | D12: =E12-SUM(B12:C12) -> 98374.065 | E12: =B$9*(1+C$4/12)^(A12*12)+B$4/(C$4/12)*((1+C$4/12)^(A12*12)-1) -> 1656277.1 | F12: =F11+C12 -> 1440000
A13: =A12+1 -> 5 | B13: =B12+C12+D12 -> 1656277.1 | C13: =B$4*12 -> 360000 | D13: =E13-SUM(B13:C13) -> 131509.96 | E13: =B$9*(1+C$4/12)^(A13*12)+B$4/(C$4/12)*((1+C$4/12)^(A13*12)-1) -> 2147787 | F13: =F12+C13 -> 1800000
A14: =A13+1 -> 6 | B14: =B13+C13+D13 -> 2147787 | C14: =B$4*12 -> 360000 | D14: =E14-SUM(B14:C14) -> 167041.26 | E14: =B$9*(1+C$4/12)^(A14*12)+B$4/(C$4/12)*((1+C$4/12)^(A14*12)-1) -> 2674828.3 | F14: =F13+C14 -> 2160000
A15: =A14+1 -> 7 | B15: =B14+C14+D14 -> 2674828.3 | C15: =B$4*12 -> 360000 | D15: =E15-SUM(B15:C15) -> 205141.11 | E15: =B$9*(1+C$4/12)^(A15*12)+B$4/(C$4/12)*((1+C$4/12)^(A15*12)-1) -> 3239969.4 | F15: =F14+C15 -> 2520000
A16: =A15+1 -> 8 | B16: =B15+C15+D15 -> 3239969.4 | C16: =B$4*12 -> 360000 | D16: =E16-SUM(B16:C16) -> 245995.21 | E16: =B$9*(1+C$4/12)^(A16*12)+B$4/(C$4/12)*((1+C$4/12)^(A16*12)-1) -> 3845964.6 | F16: =F15+C16 -> 2880000
A17: =A16+1 -> 9 | B17: =B16+C16+D16 -> 3845964.6 | C17: =B$4*12 -> 360000 | D17: =E17-SUM(B17:C17) -> 289802.65 | E17: =B$9*(1+C$4/12)^(A17*12)+B$4/(C$4/12)*((1+C$4/12)^(A17*12)-1) -> 4495767.3 | F17: =F16+C17 -> 3240000
A18: =A17+1 -> 10 | B18: =B17+C17+D17 -> 4495767.3 | C18: =B$4*12 -> 360000 | D18: =E18-SUM(B18:C18) -> 336776.94 | E18: =B$9*(1+C$4/12)^(A18*12)+B$4/(C$4/12)*((1+C$4/12)^(A18*12)-1) -> 5192544.2 | F18: =F17+C18 -> 3600000
A19: =A18+1 -> 11 | B19: =B18+C18+D18 -> 5192544.2 | C19: =B$4*12 -> 360000 | D19: =E19-SUM(B19:C19) -> 387147 | E19: =B$9*(1+C$4/12)^(A19*12)+B$4/(C$4/12)*((1+C$4/12)^(A19*12)-1) -> 5939691.2 | F19: =F18+C19 -> 3960000
A20: =A19+1 -> 12 | B20: =B19+C19+D19 -> 5939691.2 | C20: =B$4*12 -> 360000 | D20: =E20-SUM(B20:C20) -> 441158.32 | E20: =B$9*(1+C$4/12)^(A20*12)+B$4/(C$4/12)*((1+C$4/12)^(A20*12)-1) -> 6740849.5 | F20: =F19+C20 -> 4320000
A21: =A20+1 -> 13 | B21: =B20+C20+D20 -> 6740849.5 | C21: =B$4*12 -> 360000 | D21: =E21-SUM(B21:C21) -> 499074.12 | E21: =B$9*(1+C$4/12)^(A21*12)+B$4/(C$4/12)*((1+C$4/12)^(A21*12)-1) -> 7599923.7 | F21: =F20+C21 -> 4680000
A22: =A21+1 -> 14 | B22: =B21+C21+D21 -> 7599923.7 | C22: =B$4*12 -> 360000 | D22: =E22-SUM(B22:C22) -> 561176.65 | E22: =B$9*(1+C$4/12)^(A22*12)+B$4/(C$4/12)*((1+C$4/12)^(A22*12)-1) -> 8521100.3 | F22: =F21+C22 -> 5040000
... A58: =A57+1 -> 50 | B58: =B57+C57+D57 -> 1.5207671e+08 | C58: =B$4*12 -> 360000 | D58: =E58-SUM(B58:C58) -> 11005415 | E58: =B$9*(1+C$4/12)^(A58*12)+B$4/(C$4/12)*((1+C$4/12)^(A58*12)-1) -> 1.6344213e+08 | F58: =F57+C58 -> 18000000
